Workbook

Sheet Palancas
A1: Aumentar venta | B1: Disminuir venta
A2: Oportunidades SEO | B2: Disminuir inversión en ads
A3: Oportunidades imágenes | B3: Sacar/ Modificar AON | P3: Busqueda
A4: Oportunidad clip | B4: Sacar/ Modificar DOD/Relámpago | Q4: Oportunidades SEO
A5: Republicar por mala experiencia/reseñas | Q5: Oportunidades imágenes/Clips
A6: Profundizar DOD | Q6: Republicar por mala experiencia/reseñas
A7: Aplicar descuentos mayoristas
A8: Aplicar Relámpago
A9: Subir el gasto en publicidad
A10: Profundizar AON
A11: Aplicar CMR
A12: Oportunidades logísticas (FULL, FLEX)
A13: Oportunidad ficha técnica
A14: Mayoristas
A15: Imagenes con AI
A18: Venta | B18: Impresiones | C18: CTR | D18: CVR
B19: SEO | C19: Imagen de portada | D19: SEO
B20: Metodos logisticos | D20: Fotos
B21: Reseñas | D21: Promesa de envio
B22: Historial de venta | D22: reseñas
B23: Categorizacion | D23: preguntas
B24: Ads | D24: etc
B28: ancho cm | C28: largo cm | D28: alto cm | E28: peso kg
A29: BANCOGYM001 | B29: 33 | C29: 81 | D29: 21 | E29: 12.6
A30: BATERIAELE001 | B30: 46 | C30: 77 | D30: 32 | E30: 19
A31: BICE003 | B31: 18 | C31: 82 | D31: 66 | E31: 17.1
A32: BICE004 | B32: 19 | C32: 90 | D32: 75 | E32: 22.1
A33: BICE005MAGNETIC | B33: 18 | C33: 92 | D33: 77 | E33: 24.3
A34: FRAZADAKING003AZUL | B34: 14 | C34: 35 | D34: 42 | E34: 1.75
A35: FRAZADAKING003GRIS | B35: 14 | C35: 35 | D35: 42 | E35: 1.68
A36: FRAZADAQUEEN004AZUL | B36: 11 | C36: 36 | D36: 43 | E36: 1.5
A37: FRAZADAQUEEN004GRIS | B37: 11 | C37: 36 | D37: 43 | E37: 1.5
A38: MONCURGAMER27 | B38: 13 | C38: 68 | D38: 44 | E38: 4.8
A39: MONCURGAMER34 | B39: 19 | C39: 98 | D39: 50 | E39: 7.8
A40: TROTAELEC002
A41: TROTAELEC003 | B41: 14 | C41: 126 | D41: 50.7 | E41: 20.4

Sheet Intro - Productos 2026
A1: SKU | B1: Maestro producto | C1: MELI | D1: Cuena de titulo | E1: CATALOGO | F1: FALA | G1: Cantidad de caracteres | H1: PREICO FULL | I1: % | J1: AON | K1: % | L1: DOD | M1: % | N1: Categoria a publicar | O1: Descripcion | P1: Velocidad Semanal Inicial | Q1: Mes Inicial | R1: Velocidad Semanal Madura | S1: Mes maduro | T1: Mes desarrollo | U1: variacion % FULL-AON | V1: variacion% AON-DOD | W1: Ancho / cm | X1: Largo / cm | Y1: Alto / cm | Z1: Peso | AA1: Comentarios | AB1: CBM Unitario
A2: FUNGUI002 | B2: - | C2: - | D2: =LEN(C2) -> 1 | E2: - | F2: - | G2: - | H2: 22990 | I2: 39.3 | J2: 18990 | K2: 43.3 | L2: 16990 | M2: 38.4 | N2: - | O2: - | P2: - | Q2: - | R2: - | S2: - | T2: - | U2: =1-(J2/H2) -> 0.17398869 | V2: =1-(L2/J2) -> 0.10531859 | W2: - | X2: - | Y2: - | Z2: - | AB2: =W2*X2*Y2/1000000 -> #VALUE!
A3: MOCHBOMBA001 | B3: - | C3: - | D3: =LEN(C3) -> 1 | E3: - | F3: - | G3: - | H3: 79990 | I3: 41.7 | J3: 69990 | K3: 35.5 | L3: 64990 | M3: 31.7 | N3: - | O3: - | P3: - | Q3: - | R3: - | S3: - | T3: - | U3: =1-(J3/H3) -> 0.12501563 | V3: =1-(L3/J3) -> 0.071438777 | W3: - | X3: - | Y3: - | Z3: - | AB3: =W3*X3*Y3/1000000 -> #VALUE!
A4: MOCHBOMBA002 | B4: - | C4: - | D4: =LEN(C4) -> 1 | E4: - | F4: - | G4: - | H4: 79990 | I4: 39.7 | J4: 69990 | K4: 33.2 | L4: 64990 | M4: 29.2 | N4: - | O4: - | P4: - | Q4: - | R4: - | S4: - | T4: - | U4: =1-(J4/H4) -> 0.12501563 | V4: =1-(L4/J4) -> 0.071438777 | W4: - | X4: - | Y4: - | Z4: - | AB4: =W4*X4*Y4/1000000 -> #VALUE!
A5: MOCHBOMBA003 | B5: - | C5: - | D5: =LEN(C5) -> 1 | E5: - | F5: - | G5: - | H5: 69990 | I5: 39.2 | J5: 64990 | K5: 35.6 | L5: 59990 | M5: 31.5 | N5: - | O5: - | P5: - | Q5: - | R5: - | S5: - | T5: - | U5: =1-(J5/H5) -> 0.071438777 | V5: =1-(L5/J5) -> 0.076934913 | W5: - | X5: - | Y5: - | Z5: - | AB5: =W5*X5*Y5/1000000 -> #VALUE!
A6: MOCHVIAJE010 | B6: - | C6: - | D6: =LEN(C6) -> 1 | E6: - | F6: - | G6: - | H6: 49990 | I6: 43.5 | J6: 44990 | K6: 38.9 | L6: 39990 | M6: 33.1 | N6: - | O6: - | P6: - | Q6: - | R6: - | S6: - | T6: - | U6: =1-(J6/H6) -> 0.10002 | V6: =1-(L6/J6) -> 0.11113581 | W6: - | X6: - | Y6: - | Z6: - | AB6: =W6*X6*Y6/1000000 -> #VALUE!
A7: MOCHVIAJE011 | B7: - | C7: - | D7: =LEN(C7) -> 1 | E7: - | F7: - | G7: - | H7: 44990 | I7: 60.6 | J7: 39990 | K7: 47.9 | L7: 34990 | M7: 42.6 | N7: - | O7: - | P7: - | Q7: - | R7: - | S7: - | T7: - | U7: =1-(J7/H7) -> 0.11113581 | V7: =1-(L7/J7) -> 0.12503126 | W7: - | X7: - | Y7: - | Z7: - | AB7: =W7*X7*Y7/1000000 -> #VALUE!
A8: BICE003 | B8: - | C8: - | D8: =LEN(C8) -> 1 | E8: - | F8: - | G8: - | H8: 129990 | I8: 35.8 | J8: 119990 | K8: 31.7 | L8: 109990 | M8: 26.9 | N8: - | O8: - | P8: - | Q8: - | R8: - | S8: - | T8: - | U8: =1-(J8/H8) -> 0.076928995 | V8: =1-(L8/J8) -> 0.083340278 | W8: - | X8: - | Y8: - | Z8: - | AB8: =W8*X8*Y8/1000000 -> #VALUE!
A9: BICE004 | B9: - | C9: - | D9: =LEN(C9) -> 1 | E9: - | F9: - | G9: - | H9: 169990 | I9: 37.5 | J9: 159990 | K9: 34.5 | L9: 149990 | M9: 31.1 | N9: - | O9: - | P9: - | Q9: - | R9: - | S9: - | T9: - | U9: =1-(J9/H9) -> 0.05882699 | V9: =1-(L9/J9) -> 0.062503906 | W9: - | X9: - | Y9: - | Z9: - | AB9: =W9*X9*Y9/1000000 -> #VALUE!
A10: BICE005MAGNETIC | B10: - | C10: - | D10: =LEN(C10) -> 1 | E10: - | F10: - | G10: - | H10: 199990 | I10: 39.7 | J10: 179990 | K10: 34.6 | L10: 169990 | M10: 31.7 | N10: - | O10: - | P10: - | Q10: - | R10: - | S10: - | T10: - | U10: =1-(J10/H10) -> 0.100005 | V10: =1-(L10/J10) -> 0.055558642 | W10: - | X10: - | Y10: - | Z10: - | AB10: =W10*X10*Y10/1000000 -> #VALUE!
A11: FRAZADAKING003AZUL | B11: - | C11: Frazada King Polar 300gsm Homely 250x230 Cm Azul Manta Lisa | D11: =LEN(C11) -> 59 | E11: Frazada King Polar 300gsm Homely 250x230 Cm Azul Manta Lisa Super Suave | F11: - | G11: - | H11: 39990 | I11: 56.1 | J11: 29990 | K11: 46.5 | L11: 24990 | M11: 33.8 | N11: - | O11: - | P11: - | Q11: - | R11: - | S11: - | T11: - | U11: =1-(J11/H11) -> 0.25006252 | V11: =1-(L11/J11) -> 0.16672224 | W11: - | X11: - | Y11: - | Z11: - | AB11: =W11*X11*Y11/1000000 -> #VALUE!
A12: FRAZADAKING003GRIS | B12: - | C12: Frazada King Polar 300gsm Homely 250x230 Cm Gris Manta Lisa | D12: =LEN(C12) -> 59 | E12: Frazada King Polar 300gsm Homely 250x230 Cm Gris Manta Lisa Super Suave | F12: - | G12: - | H12: 39990 | I12: 56.1 | J12: 29990 | K12: 46.5 | L12: 24990 | M12: 33.8 | N12: - | O12: - | P12: - | Q12: - | R12: - | S12: - | T12: - | U12: =1-(J12/H12) -> 0.25006252 | V12: =1-(L12/J12) -> 0.16672224 | W12: - | X12: - | Y12: - | Z12: - | AB12: =W12*X12*Y12/1000000 -> #VALUE!
A13: FRAZADAQUEEN004AZUL | B13: - | C13: Frazada 2 Plazas Polar 300gsm Homely 220x220 Cm Azul Queen | D13: =LEN(C13) -> 58 | E13: Frazada 2 Plazas Polar 300gsm Homely 220x220 Cm Azul Manta Lisa Queen Super Suave | F13: - | G13: - | H13: 24990 | I13: 42.3 | J13: 18990 | K13: 42.5 | L13: 16990 | M13: 37.4 | N13: - | O13: - | P13: - | Q13: - | R13: - | S13: - | T13: - | U13: =1-(J13/H13) -> 0.24009604 | V13: =1-(L13/J13) -> 0.10531859 | W13: - | X13: - | Y13: - | Z13: - | AB13: =W13*X13*Y13/1000000 -> #VALUE!
... A15: COLCHONETALIS002NEG | B15: - | C15: - | D15: =LEN(C15) -> 1 | E15: - | F15: - | G15: - | H15: 18990 | I15: 42.2 | J15: 16990 | K15: 37.2 | L15: 14990 | M15: 30.8 | N15: - | O15: - | P15: - | Q15: - | R15: - | S15: - | T15: - | U15: =1-(J15/H15) -> 0.10531859 | V15: =1-(L15/J15) -> 0.1177163 | W15: - | X15: - | Y15: - | Z15: - | AB15: =W15*X15*Y15/1000000 -> #VALUE!
A16: GUIELE004 | B16: - | D16: =LEN(C16) -> 0 | H16: 199990 | I16: 50.4 | J16: 179990 | K16: 46.5 | L16: 159990 | M16: 41.7 | N16: - | O16: - | P16: - | Q16: - | R16: - | S16: - | T16: - | U16: =1-(J16/H16) -> 0.100005 | V16: =1-(L16/J16) -> 0.11111728 | W16: 16 | X16: 105 | Y16: 45 | Z16: 7.6 | AB16: =W16*X16*Y16/1000000 -> 0.0756
A17: GUIELE002ZURDO | B17: - | D17: =LEN(C17) -> 0 | H17: 199990 | I17: 50.4 | J17: 179990 | K17: 46.5 | L17: 159990 | M17: 41.7 | N17: - | O17: - | P17: - | Q17: - | R17: - | S17: - | T17: - | U17: =1-(J17/H17) -> 0.100005 | V17: =1-(L17/J17) -> 0.11111728 | W17: 16 | X17: 105 | Y17: 45 | Z17: 7.6 | AB17: =W17*X17*Y17/1000000 -> 0.0756
A18: AMPLIFBAJO001 | B18: - | D18: =LEN(C18) -> 0 | H18: 59990 | I18: 47.4 | J18: 49990 | K18: 39.9 | L18: 44990 | M18: 34.9 | N18: - | O18: - | P18: - | Q18: - | R18: - | S18: - | T18: - | U18: =1-(J18/H18) -> 0.16669445 | V18: =1-(L18/J18) -> 0.10002 | W18: 13 | X18: 31 | Y18: 34 | Z18: 3.75 | AB18: =W18*X18*Y18/1000000 -> 0.013702
A19: CALIENTACAM2P | B19: - | H19: 59990 | I19: {=IF(OR(H19=0, H19=""), 0, 1 - ((((XLOOKUP($A19, 'datos de inventario'!$A:$A, 'datos de inventario'!$D:$D, 0) * 'datos de inventario'!$K$2) + (XLOOKUP($A19, 'datos de inventario'!$A:$A, 'datos de inventario'!$F:$F, 0) * 'datos de inventario'!$K$3 * 'datos de inventario'!$K$4)) * 1.19 + (H19 * 0.15) + XLOOKUP(MAX($Z19, (XLOOKUP($A19, 'datos de inventario'!$A:$A, 'datos de inventario'!$F:$F, 0) * 1000000 / 4000)) + 0.1, Tarifas!$A$2:$A$33, IF(H19 <= 9989, Tarifas!$B$2:$B$33, IF(H19 <= 19989, Tarifas!$C$2:$C$33, Tarifas!$D$2:$D$33)), "Peso excedido", 1)) / H19))} -> 0.46109277 | J19: 49990 | K19: {=IF(OR(J19=0, J19=""), 0, 1 - ((((XLOOKUP($A19, 'datos de inventario'!$A:$A, 'datos de inventario'!$D:$D, 0) * 'datos de inventario'!$K$2) + (XLOOKUP($A19, 'datos de inventario'!$A:$A, 'datos de inventario'!$F:$F, 0) * 'datos de inventario'!$K$3 * 'datos de inventario'!$K$4)) * 1.19 + (J19 * 0.15) + XLOOKUP(MAX($Z19, (XLOOKUP($A19, 'datos de inventario'!$A:$A, 'datos de inventario'!$F:$F, 0) * 1000000 / 4000)) + 0.1, Tarifas!$A$2:$A$33, IF(J19 <= 9989, Tarifas!$B$2:$B$33, IF(J19 <= 19989, Tarifas!$C$2:$C$33, Tarifas!$D$2:$D$33)), "Peso excedido", 1)) / J19))} -> 0.38329577 | L19: 44990 | M19: {=IF(OR(L19=0, L19=""), 0, 1 - ((((XLOOKUP($A19, 'datos de inventario'!$A:$A, 'datos de inventario'!$D:$D, 0) * 'datos de inventario'!$K$2) + (XLOOKUP($A19, 'datos de inventario'!$A:$A, 'datos de inventario'!$F:$F, 0) * 'datos de inventario'!$K$3 * 'datos de inventario'!$K$4)) * 1.19 + (L19 * 0.15) + XLOOKUP(MAX($Z19, (XLOOKUP($A19, 'datos de inventario'!$A:$A, 'datos de inventario'!$F:$F, 0) * 1000000 / 4000)) + 0.1, Tarifas!$A$2:$A$33, IF(L19 <= 9989, Tarifas!$B$2:$B$33, IF(L19 <= 19989, Tarifas!$C$2:$C$33, Tarifas!$D$2:$D$33)), "Peso excedido", 1)) / L19))} -> 0.33142822 | N19: - | O19: - | P19: - | Q19: - | R19: - | S19: - | T19: - | U19: =1-(J19/H19) -> 0.16669445 | V19: =1-(L19/J19) -> 0.10002 | W19: 14.5 | X19: 40 | Y19: 35 | Z19: 2.2 | AB19: =W19*X19*Y19/1000000 -> 0.0203
A20: CALIENTACAMKING | B20: - | H20: 149990 | I20: {=IF(OR(H20=0, H20=""), 0, 1 - ((((XLOOKUP($A20, 'datos de inventario'!$A:$A, 'datos de inventario'!$D:$D, 0) * 'datos de inventario'!$K$2) + (XLOOKUP($A20, 'datos de inventario'!$A:$A, 'datos de inventario'!$F:$F, 0) * 'datos de inventario'!$K$3 * 'datos de inventario'!$K$4)) * 1.19 + (H20 * 0.15) + XLOOKUP(MAX($Z20, (XLOOKUP($A20, 'datos de inventario'!$A:$A, 'datos de inventario'!$F:$F, 0) * 1000000 / 4000)) + 0.1, Tarifas!$A$2:$A$33, IF(H20 <= 9989, Tarifas!$B$2:$B$33, IF(H20 <= 19989, Tarifas!$C$2:$C$33, Tarifas!$D$2:$D$33)), "Peso excedido", 1)) / H20))} -> 0.6751267 | J20: 99990 | K20: {=IF(OR(J20=0, J20=""), 0, 1 - ((((XLOOKUP($A20, 'datos de inventario'!$A:$A, 'datos de inventario'!$D:$D, 0) * 'datos de inventario'!$K$2) + (XLOOKUP($A20, 'datos de inventario'!$A:$A, 'datos de inventario'!$F:$F, 0) * 'datos de inventario'!$K$3 * 'datos de inventario'!$K$4)) * 1.19 + (J20 * 0.15) + XLOOKUP(MAX($Z20, (XLOOKUP($A20, 'datos de inventario'!$A:$A, 'datos de inventario'!$F:$F, 0) * 1000000 / 4000)) + 0.1, Tarifas!$A$2:$A$33, IF(J20 <= 9989, Tarifas!$B$2:$B$33, IF(J20 <= 19989, Tarifas!$C$2:$C$33, Tarifas!$D$2:$D$33)), "Peso excedido", 1)) / J20))} -> 0.5876813 | L20: 89990 | M20: {=IF(OR(L20=0, L20=""), 0, 1 - ((((XLOOKUP($A20, 'datos de inventario'!$A:$A, 'datos de inventario'!$D:$D, 0) * 'datos de inventario'!$K$2) + (XLOOKUP($A20, 'datos de inventario'!$A:$A, 'datos de inventario'!$F:$F, 0) * 'datos de inventario'!$K$3 * 'datos de inventario'!$K$4)) * 1.19 + (L20 * 0.15) + XLOOKUP(MAX($Z20, (XLOOKUP($A20, 'datos de inventario'!$A:$A, 'datos de inventario'!$F:$F, 0) * 1000000 / 4000)) + 0.1, Tarifas!$A$2:$A$33, IF(L20 <= 9989, Tarifas!$B$2:$B$33, IF(L20 <= 19989, Tarifas!$C$2:$C$33, Tarifas!$D$2:$D$33)), "Peso excedido", 1)) / L20))} -> 0.55853154 | N20: - | O20: - | P20: - | Q20: - | R20: - | S20: - | T20: - | U20: =1-(J20/H20) -> 0.33335556 | V20: =1-(L20/J20) -> 0.10001 | W20: 19 | X20: 40 | Y20: 35 | Z20: 2.88 | AB20: =W20*X20*Y20/1000000 -> 0.0266
A21: KITGLUCOMETRO001 | B21: - | H21: 18990 | I21: {=IF(OR(H21=0, H21=""), 0, 1 - ((((XLOOKUP($A21, 'datos de inventario'!$A:$A, 'datos de inventario'!$D:$D, 0) * 'datos de inventario'!$K$2) + (XLOOKUP($A21, 'datos de inventario'!$A:$A, 'datos de inventario'!$F:$F, 0) * 'datos de inventario'!$K$3 * 'datos de inventario'!$K$4)) * 1.19 + (H21 * 0.15) + XLOOKUP(MAX($Z21, (XLOOKUP($A21, 'datos de inventario'!$A:$A, 'datos de inventario'!$F:$F, 0) * 1000000 / 4000)) + 0.1, Tarifas!$A$2:$A$33, IF(H21 <= 9989, Tarifas!$B$2:$B$33, IF(H21 <= 19989, Tarifas!$C$2:$C$33, Tarifas!$D$2:$D$33)), "Peso excedido", 1)) / H21))} -> 0.4103486 | J21: 16990 | K21: {=IF(OR(J21=0, J21=""), 0, 1 - ((((XLOOKUP($A21, 'datos de inventario'!$A:$A, 'datos de inventario'!$D:$D, 0) * 'datos de inventario'!$K$2) + (XLOOKUP($A21, 'datos de inventario'!$A:$A, 'datos de inventario'!$F:$F, 0) * 'datos de inventario'!$K$3 * 'datos de inventario'!$K$4)) * 1.19 + (J21 * 0.15) + XLOOKUP(MAX($Z21, (XLOOKUP($A21, 'datos de inventario'!$A:$A, 'datos de inventario'!$F:$F, 0) * 1000000 / 4000)) + 0.1, Tarifas!$A$2:$A$33, IF(J21 <= 9989, Tarifas!$B$2:$B$33, IF(J21 <= 19989, Tarifas!$C$2:$C$33, Tarifas!$D$2:$D$33)), "Peso excedido", 1)) / J21))} -> 0.35859447 | L21: 14990 | M21: {=IF(OR(L21=0, L21=""), 0, 1 - ((((XLOOKUP($A21, 'datos de inventario'!$A:$A, 'datos de inventario'!$D:$D, 0) * 'datos de inventario'!$K$2) + (XLOOKUP($A21, 'datos de inventario'!$A:$A, 'datos de inventario'!$F:$F, 0) * 'datos de inventario'!$K$3 * 'datos de inventario'!$K$4)) * 1.19 + (L21 * 0.15) + XLOOKUP(MAX($Z21, (XLOOKUP($A21, 'datos de inventario'!$A:$A, 'datos de inventario'!$F:$F, 0) * 1000000 / 4000)) + 0.1, Tarifas!$A$2:$A$33, IF(L21 <= 9989, Tarifas!$B$2:$B$33, IF(L21 <= 19989, Tarifas!$C$2:$C$33, Tarifas!$D$2:$D$33)), "Peso excedido", 1)) / L21))} -> 0.29303002 | N21: - | O21: - | P21: - | Q21: - | R21: - | S21: - | T21: - | U21: =1-(J21/H21) -> 0.10531859 | V21: =1-(L21/J21) -> 0.1177163 | W21: 4.5 | X21: 11.5 | Y21: 16 | Z21: 0.256 | AB21: =W21*X21*Y21/1000000 -> 0.000828
A22: PACKLANCETAS50U | B22: - | H22: 4990 | I22: {=IF(OR(H22=0, H22=""), 0, 1 - ((((XLOOKUP($A22, 'datos de inventario'!$A:$A, 'datos de inventario'!$D:$D, 0) * 'datos de inventario'!$K$2) + (XLOOKUP($A22, 'datos de inventario'!$A:$A, 'datos de inventario'!$F:$F, 0) * 'datos de inventario'!$K$3 * 'datos de inventario'!$K$4)) * 1.19 + (H22 * 0.15) + XLOOKUP(MAX($Z22, (XLOOKUP($A22, 'datos de inventario'!$A:$A, 'datos de inventario'!$F:$F, 0) * 1000000 / 4000)) + 0.1, Tarifas!$A$2:$A$33, IF(H22 <= 9989, Tarifas!$B$2:$B$33, IF(H22 <= 19989, Tarifas!$C$2:$C$33, Tarifas!$D$2:$D$33)), "Peso excedido", 1)) / H22))} -> 0.60585471 | J22: 3990 | K22: {=IF(OR(J22=0, J22=""), 0, 1 - ((((XLOOKUP($A22, 'datos de inventario'!$A:$A, 'datos de inventario'!$D:$D, 0) * 'datos de inventario'!$K$2) + (XLOOKUP($A22, 'datos de inventario'!$A:$A, 'datos de inventario'!$F:$F, 0) * 'datos de inventario'!$K$3 * 'datos de inventario'!$K$4)) * 1.19 + (J22 * 0.15) + XLOOKUP(MAX($Z22, (XLOOKUP($A22, 'datos de inventario'!$A:$A, 'datos de inventario'!$F:$F, 0) * 1000000 / 4000)) + 0.1, Tarifas!$A$2:$A$33, IF(J22 <= 9989, Tarifas!$B$2:$B$33, IF(J22 <= 19989, Tarifas!$C$2:$C$33, Tarifas!$D$2:$D$33)), "Peso excedido", 1)) / J22))} -> 0.54466541 | L22: 2990 | M22: {=IF(OR(L22=0, L22=""), 0, 1 - ((((XLOOKUP($A22, 'datos de inventario'!$A:$A, 'datos de inventario'!$D:$D, 0) * 'datos de inventario'!$K$2) + (XLOOKUP($A22, 'datos de inventario'!$A:$A, 'datos de inventario'!$F:$F, 0) * 'datos de inventario'!$K$3 * 'datos de inventario'!$K$4)) * 1.19 + (L22 * 0.15) + XLOOKUP(MAX($Z22, (XLOOKUP($A22, 'datos de inventario'!$A:$A, 'datos de inventario'!$F:$F, 0) * 1000000 / 4000)) + 0.1, Tarifas!$A$2:$A$33, IF(L22 <= 9989, Tarifas!$B$2:$B$33, IF(L22 <= 19989, Tarifas!$C$2:$C$33, Tarifas!$D$2:$D$33)), "Peso excedido", 1)) / L22))} -> 0.44254682 | N22: - | O22: - | P22: - | Q22: - | R22: - | S22: - | T22: - | U22: =1-(J22/H22) -> 0.2004008 | V22: =1-(L22/J22) -> 0.25062657 | W22: 4 | X22: 4 | Y22: 6 | Z22: 0.024 | AB22: =W22*X22*Y22/1000000 -> 9.6e-05
A23: PACKTIRAS50U | B23: - | H23: 12990 | I23: {=IF(OR(H23=0, H23=""), 0, 1 - ((((XLOOKUP($A23, 'datos de inventario'!$A:$A, 'datos de inventario'!$D:$D, 0) * 'datos de inventario'!$K$2) + (XLOOKUP($A23, 'datos de inventario'!$A:$A, 'datos de inventario'!$F:$F, 0) * 'datos de inventario'!$K$3 * 'datos de inventario'!$K$4)) * 1.19 + (H23 * 0.15) + XLOOKUP(MAX($Z23, (XLOOKUP($A23, 'datos de inventario'!$A:$A, 'datos de inventario'!$F:$F, 0) * 1000000 / 4000)) + 0.1, Tarifas!$A$2:$A$33, IF(H23 <= 9989, Tarifas!$B$2:$B$33, IF(H23 <= 19989, Tarifas!$C$2:$C$33, Tarifas!$D$2:$D$33)), "Peso excedido", 1)) / H23))} -> 0.53998749 | J23: 11990 | K23: {=IF(OR(J23=0, J23=""), 0, 1 - ((((XLOOKUP($A23, 'datos de inventario'!$A:$A, 'datos de inventario'!$D:$D, 0) * 'datos de inventario'!$K$2) + (XLOOKUP($A23, 'datos de inventario'!$A:$A, 'datos de inventario'!$F:$F, 0) * 'datos de inventario'!$K$3 * 'datos de inventario'!$K$4)) * 1.19 + (J23 * 0.15) + XLOOKUP(MAX($Z23, (XLOOKUP($A23, 'datos de inventario'!$A:$A, 'datos de inventario'!$F:$F, 0) * 1000000 / 4000)) + 0.1, Tarifas!$A$2:$A$33, IF(J23 <= 9989, Tarifas!$B$2:$B$33, IF(J23 <= 19989, Tarifas!$C$2:$C$33, Tarifas!$D$2:$D$33)), "Peso excedido", 1)) / J23))} -> 0.51413157 | L23: 10990 | M23: {=IF(OR(L23=0, L23=""), 0, 1 - ((((XLOOKUP($A23, 'datos de inventario'!$A:$A, 'datos de inventario'!$D:$D, 0) * 'datos de inventario'!$K$2) + (XLOOKUP($A23, 'datos de inventario'!$A:$A, 'datos de inventario'!$F:$F, 0) * 'datos de inventario'!$K$3 * 'datos de inventario'!$K$4)) * 1.19 + (L23 * 0.15) + XLOOKUP(MAX($Z23, (XLOOKUP($A23, 'datos de inventario'!$A:$A, 'datos de inventario'!$F:$F, 0) * 1000000 / 4000)) + 0.1, Tarifas!$A$2:$A$33, IF(L23 <= 9989, Tarifas!$B$2:$B$33, IF(L23 <= 19989, Tarifas!$C$2:$C$33, Tarifas!$D$2:$D$33)), "Peso excedido", 1)) / L23))} -> 0.48357029 | N23: - | O23: - | P23: - | Q23: - | R23: - | S23: - | T23: - | U23: =1-(J23/H23) -> 0.076982294 | V23: =1-(L23/J23) -> 0.083402836 | W23: 3.5 | X23: 4 | Y23: 6 | Z23: 0.026 | AB23: =W23*X23*Y23/1000000 -> 8.4e-05
A24: ACV004NEGRA | B24: - | H24: 26990 | I24: {=IF(OR(H24=0, H24=""), 0, 1 - ((((XLOOKUP($A24, 'datos de inventario'!$A:$A, 'datos de inventario'!$D:$D, 0) * 'datos de inventario'!$K$2) + (XLOOKUP($A24, 'datos de inventario'!$A:$A, 'datos de inventario'!$F:$F, 0) * 'datos de inventario'!$K$3 * 'datos de inventario'!$K$4)) * 1.19 + (H24 * 0.15) + XLOOKUP(MAX($Z24, (XLOOKUP($A24, 'datos de inventario'!$A:$A, 'datos de inventario'!$F:$F, 0) * 1000000 / 4000)) + 0.1, Tarifas!$A$2:$A$33, IF(H24 <= 9989, Tarifas!$B$2:$B$33, IF(H24 <= 19989, Tarifas!$C$2:$C$33, Tarifas!$D$2:$D$33)), "Peso excedido", 1)) / H24))} -> 0.38214881 | J24: 24990 | K24: {=IF(OR(J24=0, J24=""), 0, 1 - ((((XLOOKUP($A24, 'datos de inventario'!$A:$A, 'datos de inventario'!$D:$D, 0) * 'datos de inventario'!$K$2) + (XLOOKUP($A24, 'datos de inventario'!$A:$A, 'datos de inventario'!$F:$F, 0) * 'datos de inventario'!$K$3 * 'datos de inventario'!$K$4)) * 1.19 + (J24 * 0.15) + XLOOKUP(MAX($Z24, (XLOOKUP($A24, 'datos de inventario'!$A:$A, 'datos de inventario'!$F:$F, 0) * 1000000 / 4000)) + 0.1, Tarifas!$A$2:$A$33, IF(J24 <= 9989, Tarifas!$B$2:$B$33, IF(J24 <= 19989, Tarifas!$C$2:$C$33, Tarifas!$D$2:$D$33)), "Peso excedido", 1)) / J24))} -> 0.34470574 | L24: 18990 | M24: {=IF(OR(L24=0, L24=""), 0, 1 - ((((XLOOKUP($A24, 'datos de inventario'!$A:$A, 'datos de inventario'!$D:$D, 0) * 'datos de inventario'!$K$2) + (XLOOKUP($A24, 'datos de inventario'!$A:$A, 'datos de inventario'!$F:$F, 0) * 'datos de inventario'!$K$3 * 'datos de inventario'!$K$4)) * 1.19 + (L24 * 0.15) + XLOOKUP(MAX($Z24, (XLOOKUP($A24, 'datos de inventario'!$A:$A, 'datos de inventario'!$F:$F, 0) * 1000000 / 4000)) + 0.1, Tarifas!$A$2:$A$33, IF(L24 <= 9989, Tarifas!$B$2:$B$33, IF(L24 <= 19989, Tarifas!$C$2:$C$33, Tarifas!$D$2:$D$33)), "Peso excedido", 1)) / L24))} -> 0.357251 | N24: - | O24: - | P24: - | Q24: - | R24: - | S24: - | T24: - | U24: =1-(J24/H24) -> 0.074101519 | V24: =1-(L24/J24) -> 0.24009604 | W24: 17 | X24: 41 | Y24: 17 | Z24: 1.44 | AB24: =W24*X24*Y24/1000000 -> 0.011849
A25: PACKUKE003 | B25: - | H25: 44990 | I25: {=IF(OR(H25=0, H25=""), 0, 1 - ((((XLOOKUP($A25, 'datos de inventario'!$A:$A, 'datos de inventario'!$D:$D, 0) * 'datos de inventario'!$K$2) + (XLOOKUP($A25, 'datos de inventario'!$A:$A, 'datos de inventario'!$F:$F, 0) * 'datos de inventario'!$K$3 * 'datos de inventario'!$K$4)) * 1.19 + (H25 * 0.15) + XLOOKUP(MAX($Z25, (XLOOKUP($A25, 'datos de inventario'!$A:$A, 'datos de inventario'!$F:$F, 0) * 1000000 / 4000)) + 0.1, Tarifas!$A$2:$A$33, IF(H25 <= 9989, Tarifas!$B$2:$B$33, IF(H25 <= 19989, Tarifas!$C$2:$C$33, Tarifas!$D$2:$D$33)), "Peso excedido", 1)) / H25))} -> 0.45490287 | J25: 39990 | K25: {=IF(OR(J25=0, J25=""), 0, 1 - ((((XLOOKUP($A25, 'datos de inventario'!$A:$A, 'datos de inventario'!$D:$D, 0) * 'datos de inventario'!$K$2) + (XLOOKUP($A25, 'datos de inventario'!$A:$A, 'datos de inventario'!$F:$F, 0) * 'datos de inventario'!$K$3 * 'datos de inventario'!$K$4)) * 1.19 + (J25 * 0.15) + XLOOKUP(MAX($Z25, (XLOOKUP($A25, 'datos de inventario'!$A:$A, 'datos de inventario'!$F:$F, 0) * 1000000 / 4000)) + 0.1, Tarifas!$A$2:$A$33, IF(J25 <= 9989, Tarifas!$B$2:$B$33, IF(J25 <= 19989, Tarifas!$C$2:$C$33, Tarifas!$D$2:$D$33)), "Peso excedido", 1)) / J25))} -> 0.40550338 | L25: 34990 | M25: {=IF(OR(L25=0, L25=""), 0, 1 - ((((XLOOKUP($A25, 'datos de inventario'!$A:$A, 'datos de inventario'!$D:$D, 0) * 'datos de inventario'!$K$2) + (XLOOKUP($A25, 'datos de inventario'!$A:$A, 'datos de inventario'!$F:$F, 0) * 'datos de inventario'!$K$3 * 'datos de inventario'!$K$4)) * 1.19 + (L25 * 0.15) + XLOOKUP(MAX($Z25, (XLOOKUP($A25, 'datos de inventario'!$A:$A, 'datos de inventario'!$F:$F, 0) * 1000000 / 4000)) + 0.1, Tarifas!$A$2:$A$33, IF(L25 <= 9989, Tarifas!$B$2:$B$33, IF(L25 <= 19989, Tarifas!$C$2:$C$33, Tarifas!$D$2:$D$33)), "Peso excedido", 1)) / L25))} -> 0.34198571 | N25: - | O25: - | P25: - | Q25: - | R25: - | S25: - | T25: - | U25: =1-(J25/H25) -> 0.11113581 | V25: =1-(L25/J25) -> 0.12503126 | W25: 9 | X25: 22.5 | Y25: 58 | Z25: 0.8 | AB25: =W25*X25*Y25/1000000 -> 0.011745
A26: SILLARUEDA001 | B26: - | H26: 119990 | I26: {=IF(OR(H26=0, H26=""), 0, 1 - ((((XLOOKUP($A26, 'datos de inventario'!$A:$A, 'datos de inventario'!$D:$D, 0) * 'datos de inventario'!$K$2) + (XLOOKUP($A26, 'datos de inventario'!$A:$A, 'datos de inventario'!$F:$F, 0) * 'datos de inventario'!$K$3 * 'datos de inventario'!$K$4)) * 1.19 + (H26 * 0.15) + XLOOKUP(MAX($Z26, (XLOOKUP($A26, 'datos de inventario'!$A:$A, 'datos de inventario'!$F:$F, 0) * 1000000 / 4000)) + 0.1, Tarifas!$A$2:$A$33, IF(H26 <= 9989, Tarifas!$B$2:$B$33, IF(H26 <= 19989, Tarifas!$C$2:$C$33, Tarifas!$D$2:$D$33)), "Peso excedido", 1)) / H26))} -> 0.25039941 | J26: 109990 | K26: {=IF(OR(J26=0, J26=""), 0, 1 - ((((XLOOKUP($A26, 'datos de inventario'!$A:$A, 'datos de inventario'!$D:$D, 0) * 'datos de inventario'!$K$2) + (XLOOKUP($A26, 'datos de inventario'!$A:$A, 'datos de inventario'!$F:$F, 0) * 'datos de inventario'!$K$3 * 'datos de inventario'!$K$4)) * 1.19 + (J26 * 0.15) + XLOOKUP(MAX($Z26, (XLOOKUP($A26, 'datos de inventario'!$A:$A, 'datos de inventario'!$F:$F, 0) * 1000000 / 4000)) + 0.1, Tarifas!$A$2:$A$33, IF(J26 <= 9989, Tarifas!$B$2:$B$33, IF(J26 <= 19989, Tarifas!$C$2:$C$33, Tarifas!$D$2:$D$33)), "Peso excedido", 1)) / J26))} -> 0.19588531 | L26: 99990 | M26: {=IF(OR(L26=0, L26=""), 0, 1 - ((((XLOOKUP($A26, 'datos de inventario'!$A:$A, 'datos de inventario'!$D:$D, 0) * 'datos de inventario'!$K$2) + (XLOOKUP($A26, 'datos de inventario'!$A:$A, 'datos de inventario'!$F:$F, 0) * 'datos de inventario'!$K$3 * 'datos de inventario'!$K$4)) * 1.19 + (L26 * 0.15) + XLOOKUP(MAX($Z26, (XLOOKUP($A26, 'datos de inventario'!$A:$A, 'datos de inventario'!$F:$F, 0) * 1000000 / 4000)) + 0.1, Tarifas!$A$2:$A$33, IF(L26 <= 9989, Tarifas!$B$2:$B$33, IF(L26 <= 19989, Tarifas!$C$2:$C$33, Tarifas!$D$2:$D$33)), "Peso excedido", 1)) / L26))} -> 0.1304673 | N26: - | O26: - | P26: - | Q26: - | R26: - | S26: - | T26: - | U26: =1-(J26/H26) -> 0.083340278 | V26: =1-(L26/J26) -> 0.090917356 | W26: 25 | X26: 87 | Y26: 88 | Z26: 14.04 | AB26: =W26*X26*Y26/1000000 -> 0.1914
A27: CUCHILLOSANTOKU002 | B27: - | H27: 29990 | I27: {=IF(OR(H27=0, H27=""), 0, 1 - ((((XLOOKUP($A27, 'datos de inventario'!$A:$A, 'datos de inventario'!$D:$D, 0) * 'datos de inventario'!$K$2) + (XLOOKUP($A27, 'datos de inventario'!$A:$A, 'datos de inventario'!$F:$F, 0) * 'datos de inventario'!$K$3 * 'datos de inventario'!$K$4)) * 1.19 + (H27 * 0.15) + XLOOKUP(MAX($Z27, (XLOOKUP($A27, 'datos de inventario'!$A:$A, 'datos de inventario'!$F:$F, 0) * 1000000 / 4000)) + 0.1, Tarifas!$A$2:$A$33, IF(H27 <= 9989, Tarifas!$B$2:$B$33, IF(H27 <= 19989, Tarifas!$C$2:$C$33, Tarifas!$D$2:$D$33)), "Peso excedido", 1)) / H27))} -> 0.54379652 | J27: 24990 | K27: {=IF(OR(J27=0, J27=""), 0, 1 - ((((XLOOKUP($A27, 'datos de inventario'!$A:$A, 'datos de inventario'!$D:$D, 0) * 'datos de inventario'!$K$2) + (XLOOKUP($A27, 'datos de inventario'!$A:$A, 'datos de inventario'!$F:$F, 0) * 'datos de inventario'!$K$3 * 'datos de inventario'!$K$4)) * 1.19 + (J27 * 0.15) + XLOOKUP(MAX($Z27, (XLOOKUP($A27, 'datos de inventario'!$A:$A, 'datos de inventario'!$F:$F, 0) * 1000000 / 4000)) + 0.1, Tarifas!$A$2:$A$33, IF(J27 <= 9989, Tarifas!$B$2:$B$33, IF(J27 <= 19989, Tarifas!$C$2:$C$33, Tarifas!$D$2:$D$33)), "Peso excedido", 1)) / J27))} -> 0.48253131 | L27: 18990 | M27: {=IF(OR(L27=0, L27=""), 0, 1 - ((((XLOOKUP($A27, 'datos de inventario'!$A:$A, 'datos de inventario'!$D:$D, 0) * 'datos de inventario'!$K$2) + (XLOOKUP($A27, 'datos de inventario'!$A:$A, 'datos de inventario'!$F:$F, 0) * 'datos de inventario'!$K$3 * 'datos de inventario'!$K$4)) * 1.19 + (L27 * 0.15) + XLOOKUP(MAX($Z27, (XLOOKUP($A27, 'datos de inventario'!$A:$A, 'datos de inventario'!$F:$F, 0) * 1000000 / 4000)) + 0.1, Tarifas!$A$2:$A$33, IF(L27 <= 9989, Tarifas!$B$2:$B$33, IF(L27 <= 19989, Tarifas!$C$2:$C$33, Tarifas!$D$2:$D$33)), "Peso excedido", 1)) / L27))} -> 0.4828045 | N27: - | O27: - | P27: - | Q27: - | R27: - | S27: - | T27: - | U27: =1-(J27/H27) -> 0.16672224 | V27: =1-(L27/J27) -> 0.24009604 | W27: 8 | X27: 38 | Y27: 3 | Z27: 0.41 | AB27: =W27*X27*Y27/1000000 -> 0.000912
A28: MATYOG003NEG | B28: - | H28: 18990 | I28: {=IF(OR(H28=0, H28=""), 0, 1 - ((((XLOOKUP($A28, 'datos de inventario'!$A:$A, 'datos de inventario'!$D:$D, 0) * 'datos de inventario'!$K$2) + (XLOOKUP($A28, 'datos de inventario'!$A:$A, 'datos de inventario'!$F:$F, 0) * 'datos de inventario'!$K$3 * 'datos de inventario'!$K$4)) * 1.19 + (H28 * 0.15) + XLOOKUP(MAX($Z29, (XLOOKUP($A28, 'datos de inventario'!$A:$A, 'datos de inventario'!$F:$F, 0) * 1000000 / 4000)) + 0.1, Tarifas!$A$2:$A$33, IF(H28 <= 9989, Tarifas!$B$2:$B$33, IF(H28 <= 19989, Tarifas!$C$2:$C$33, Tarifas!$D$2:$D$33)), "Peso excedido", 1)) / H28))} -> 0.42901132 | J28: 17990 | K28: {=IF(OR(J28=0, J28=""), 0, 1 - ((((XLOOKUP($A28, 'datos de inventario'!$A:$A, 'datos de inventario'!$D:$D, 0) * 'datos de inventario'!$K$2) + (XLOOKUP($A28, 'datos de inventario'!$A:$A, 'datos de inventario'!$F:$F, 0) * 'datos de inventario'!$K$3 * 'datos de inventario'!$K$4)) * 1.19 + (J28 * 0.15) + XLOOKUP(MAX($Z29, (XLOOKUP($A28, 'datos de inventario'!$A:$A, 'datos de inventario'!$F:$F, 0) * 1000000 / 4000)) + 0.1, Tarifas!$A$2:$A$33, IF(J28 <= 9989, Tarifas!$B$2:$B$33, IF(J28 <= 19989, Tarifas!$C$2:$C$33, Tarifas!$D$2:$D$33)), "Peso excedido", 1)) / J28))} -> 0.40561006 | L28: 16990 | M28: {=IF(OR(L28=0, L28=""), 0, 1 - ((((XLOOKUP($A28, 'datos de inventario'!$A:$A, 'datos de inventario'!$D:$D, 0) * 'datos de inventario'!$K$2) + (XLOOKUP($A28, 'datos de inventario'!$A:$A, 'datos de inventario'!$F:$F, 0) * 'datos de inventario'!$K$3 * 'datos de inventario'!$K$4)) * 1.19 + (L28 * 0.15) + XLOOKUP(MAX($Z29, (XLOOKUP($A28, 'datos de inventario'!$A:$A, 'datos de inventario'!$F:$F, 0) * 1000000 / 4000)) + 0.1, Tarifas!$A$2:$A$33, IF(L28 <= 9989, Tarifas!$B$2:$B$33, IF(L28 <= 19989, Tarifas!$C$2:$C$33, Tarifas!$D$2:$D$33)), "Peso excedido", 1)) / L28))} -> 0.37945409 | N28: - | O28: - | P28: - | Q28: - | R28: - | S28: - | T28: - | U28: =1-(J28/H28) -> 0.052659294 | V28: =1-(L28/J28) -> 0.055586437 | W28: 15 | X28: 15 | Y28: 61 | Z28: 1.048 | AB28: =W28*X28*Y28/1000000 -> 0.013725
A29: CUCHI002 | W29: 8 | X29: 39 | Y29: 3 | Z29: 0.38 | AB29: =W29*X29*Y29/1000000 -> 0.000936
A30: MATYOGNBR002ROS | B30: - | H30: 19980 | I30: {=IF(OR(H30=0, H30=""), 0, 1 - ((((XLOOKUP($A30, 'datos de inventario'!$A:$A, 'datos de inventario'!$D:$D, 0) * 'datos de inventario'!$K$2) + (XLOOKUP($A30, 'datos de inventario'!$A:$A, 'datos de inventario'!$F:$F, 0) * 'datos de inventario'!$K$3 * 'datos de inventario'!$K$4)) * 1.19 + (H30 * 0.15) + XLOOKUP(MAX($Z30, (XLOOKUP($A30, 'datos de inventario'!$A:$A, 'datos de inventario'!$F:$F, 0) * 1000000 / 4000)) + 0.1, Tarifas!$A$2:$A$33, IF(H30 <= 9989, Tarifas!$B$2:$B$33, IF(H30 <= 19989, Tarifas!$C$2:$C$33, Tarifas!$D$2:$D$33)), "Peso excedido", 1)) / H30))} -> 0.40135798 | J30: 18990 | K30: {=IF(OR(J30=0, J30=""), 0, 1 - ((((XLOOKUP($A30, 'datos de inventario'!$A:$A, 'datos de inventario'!$D:$D, 0) * 'datos de inventario'!$K$2) + (XLOOKUP($A30, 'datos de inventario'!$A:$A, 'datos de inventario'!$F:$F, 0) * 'datos de inventario'!$K$3 * 'datos de inventario'!$K$4)) * 1.19 + (J30 * 0.15) + XLOOKUP(MAX($Z30, (XLOOKUP($A30, 'datos de inventario'!$A:$A, 'datos de inventario'!$F:$F, 0) * 1000000 / 4000)) + 0.1, Tarifas!$A$2:$A$33, IF(J30 <= 9989, Tarifas!$B$2:$B$33, IF(J30 <= 19989, Tarifas!$C$2:$C$33, Tarifas!$D$2:$D$33)), "Peso excedido", 1)) / J30))} -> 0.37796906 | L30: 17990 | M30: {=IF(OR(L30=0, L30=""), 0, 1 - ((((XLOOKUP($A30, 'datos de inventario'!$A:$A, 'datos de inventario'!$D:$D, 0) * 'datos de inventario'!$K$2) + (XLOOKUP($A30, 'datos de inventario'!$A:$A, 'datos de inventario'!$F:$F, 0) * 'datos de inventario'!$K$3 * 'datos de inventario'!$K$4)) * 1.19 + (L30 * 0.15) + XLOOKUP(MAX($Z30, (XLOOKUP($A30, 'datos de inventario'!$A:$A, 'datos de inventario'!$F:$F, 0) * 1000000 / 4000)) + 0.1, Tarifas!$A$2:$A$33, IF(L30 <= 9989, Tarifas!$B$2:$B$33, IF(L30 <= 19989, Tarifas!$C$2:$C$33, Tarifas!$D$2:$D$33)), "Peso excedido", 1)) / L30))} -> 0.35173054 | N30: - | O30: - | P30: - | Q30: - | R30: - | S30: - | T30: - | U30: =1-(J30/H30) -> 0.04954955 | V30: =1-(L30/J30) -> 0.052659294 | W30: 20 | X30: 20 | Y30: 64 | Z30: 0.988 | AB30: =W30*X30*Y30/1000000 -> 0.0256
A31: LAMPARAMES002NEG | B31: - | H31: 22990 | I31: {=IF(OR(H31=0, H31=""), 0, 1 - ((((XLOOKUP($A31, 'datos de inventario'!$A:$A, 'datos de inventario'!$D:$D, 0) * 'datos de inventario'!$K$2) + (XLOOKUP($A31, 'datos de inventario'!$A:$A, 'datos de inventario'!$F:$F, 0) * 'datos de inventario'!$K$3 * 'datos de inventario'!$K$4)) * 1.19 + (H31 * 0.15) + XLOOKUP(MAX($Z31, (XLOOKUP($A31, 'datos de inventario'!$A:$A, 'datos de inventario'!$F:$F, 0) * 1000000 / 4000)) + 0.1, Tarifas!$A$2:$A$33, IF(H31 <= 9989, Tarifas!$B$2:$B$33, IF(H31 <= 19989, Tarifas!$C$2:$C$33, Tarifas!$D$2:$D$33)), "Peso excedido", 1)) / H31))} -> 0.31075544 | J31: 19980 | K31: {=IF(OR(J31=0, J31=""), 0, 1 - ((((XLOOKUP($A31, 'datos de inventario'!$A:$A, 'datos de inventario'!$D:$D, 0) * 'datos de inventario'!$K$2) + (XLOOKUP($A31, 'datos de inventario'!$A:$A, 'datos de inventario'!$F:$F, 0) * 'datos de inventario'!$K$3 * 'datos de inventario'!$K$4)) * 1.19 + (J31 * 0.15) + XLOOKUP(MAX($Z31, (XLOOKUP($A31, 'datos de inventario'!$A:$A, 'datos de inventario'!$F:$F, 0) * 1000000 / 4000)) + 0.1, Tarifas!$A$2:$A$33, IF(J31 <= 9989, Tarifas!$B$2:$B$33, IF(J31 <= 19989, Tarifas!$C$2:$C$33, Tarifas!$D$2:$D$33)), "Peso excedido", 1)) / J31))} -> 0.3401285 | L31: 17990 | M31: {=IF(OR(L31=0, L31=""), 0, 1 - ((((XLOOKUP($A31, 'datos de inventario'!$A:$A, 'datos de inventario'!$D:$D, 0) * 'datos de inventario'!$K$2) + (XLOOKUP($A31, 'datos de inventario'!$A:$A, 'datos de inventario'!$F:$F, 0) * 'datos de inventario'!$K$3 * 'datos de inventario'!$K$4)) * 1.19 + (L31 * 0.15) + XLOOKUP(MAX($Z31, (XLOOKUP($A31, 'datos de inventario'!$A:$A, 'datos de inventario'!$F:$F, 0) * 1000000 / 4000)) + 0.1, Tarifas!$A$2:$A$33, IF(L31 <= 9989, Tarifas!$B$2:$B$33, IF(L31 <= 19989, Tarifas!$C$2:$C$33, Tarifas!$D$2:$D$33)), "Peso excedido", 1)) / L31))} -> 0.28372804 | N31: - | O31: - | P31: - | Q31: - | R31: - | S31: - | T31: - | U31: =1-(J31/H31) -> 0.13092649 | V31: =1-(L31/J31) -> 0.0995996 | W31: 13 | X31: 42 | Y31: 5 | Z31: 0.66 | AB31: =W31*X31*Y31/1000000 -> 0.00273
A32: TIRASNASALE30U001 | B32: - | H32: 18990 | I32: {=IF(OR(H32=0, H32=""), 0, 1 - ((((XLOOKUP($A32, 'datos de inventario'!$A:$A, 'datos de inventario'!$D:$D, 0) * 'datos de inventario'!$K$2) + (XLOOKUP($A32, 'datos de inventario'!$A:$A, 'datos de inventario'!$F:$F, 0) * 'datos de inventario'!$K$3 * 'datos de inventario'!$K$4)) * 1.19 + (H32 * 0.15) + XLOOKUP(MAX($Z32, (XLOOKUP($A32, 'datos de inventario'!$A:$A, 'datos de inventario'!$F:$F, 0) * 1000000 / 4000)) + 0.1, Tarifas!$A$2:$A$33, IF(H32 <= 9989, Tarifas!$B$2:$B$33, IF(H32 <= 19989, Tarifas!$C$2:$C$33, Tarifas!$D$2:$D$33)), "Peso excedido", 1)) / H32))} -> 0.62924302 | J32: 14990 | K32: {=IF(OR(J32=0, J32=""), 0, 1 - ((((XLOOKUP($A32, 'datos de inventario'!$A:$A, 'datos de inventario'!$D:$D, 0) * 'datos de inventario'!$K$2) + (XLOOKUP($A32, 'datos de inventario'!$A:$A, 'datos de inventario'!$F:$F, 0) * 'datos de inventario'!$K$3 * 'datos de inventario'!$K$4)) * 1.19 + (J32 * 0.15) + XLOOKUP(MAX($Z32, (XLOOKUP($A32, 'datos de inventario'!$A:$A, 'datos de inventario'!$F:$F, 0) * 1000000 / 4000)) + 0.1, Tarifas!$A$2:$A$33, IF(J32 <= 9989, Tarifas!$B$2:$B$33, IF(J32 <= 19989, Tarifas!$C$2:$C$33, Tarifas!$D$2:$D$33)), "Peso excedido", 1)) / J32))} -> 0.57033522 | L32: 12990 | M32: {=IF(OR(L32=0, L32=""), 0, 1 - ((((XLOOKUP($A32, 'datos de inventario'!$A:$A, 'datos de inventario'!$D:$D, 0) * 'datos de inventario'!$K$2) + (XLOOKUP($A32, 'datos de inventario'!$A:$A, 'datos de inventario'!$F:$F, 0) * 'datos de inventario'!$K$3 * 'datos de inventario'!$K$4)) * 1.19 + (L32 * 0.15) + XLOOKUP(MAX($Z32, (XLOOKUP($A32, 'datos de inventario'!$A:$A, 'datos de inventario'!$F:$F, 0) * 1000000 / 4000)) + 0.1, Tarifas!$A$2:$A$33, IF(L32 <= 9989, Tarifas!$B$2:$B$33, IF(L32 <= 19989, Tarifas!$C$2:$C$33, Tarifas!$D$2:$D$33)), "Peso excedido", 1)) / L32))} -> 0.52727675 | N32: - | O32: - | P32: - | Q32: - | R32: - | S32: - | T32: - | U32: =1-(J32/H32) -> 0.21063718 | V32: =1-(L32/J32) -> 0.13342228 | W32: 2 | X32: 7 | Y32: 10 | Z32: 0.032 | AB32: =W32*X32*Y32/1000000 -> 0.00014
A33: BOTASCOMPRESION001 | B33: - | H33: 89990 | I33: {=IF(OR(H33=0, H33=""), 0, 1 - ((((XLOOKUP($A33, 'datos de inventario'!$A:$A, 'datos de inventario'!$D:$D, 0) * 'datos de inventario'!$K$2) + (XLOOKUP($A33, 'datos de inventario'!$A:$A, 'datos de inventario'!$F:$F, 0) * 'datos de inventario'!$K$3 * 'datos de inventario'!$K$4)) * 1.19 + (H33 * 0.15) + XLOOKUP(MAX($Z33, (XLOOKUP($A33, 'datos de inventario'!$A:$A, 'datos de inventario'!$F:$F, 0) * 1000000 / 4000)) + 0.1, Tarifas!$A$2:$A$33, IF(H33 <= 9989, Tarifas!$B$2:$B$33, IF(H33 <= 19989, Tarifas!$C$2:$C$33, Tarifas!$D$2:$D$33)), "Peso excedido", 1)) / H33))} -> 0.4546344 | J33: 79990 | K33: {=IF(OR(J33=0, J33=""), 0, 1 - ((((XLOOKUP($A33, 'datos de inventario'!$A:$A, 'datos de inventario'!$D:$D, 0) * 'datos de inventario'!$K$2) + (XLOOKUP($A33, 'datos de inventario'!$A:$A, 'datos de inventario'!$F:$F, 0) * 'datos de inventario'!$K$3 * 'datos de inventario'!$K$4)) * 1.19 + (J33 * 0.15) + XLOOKUP(MAX($Z33, (XLOOKUP($A33, 'datos de inventario'!$A:$A, 'datos de inventario'!$F:$F, 0) * 1000000 / 4000)) + 0.1, Tarifas!$A$2:$A$33, IF(J33 <= 9989, Tarifas!$B$2:$B$33, IF(J33 <= 19989, Tarifas!$C$2:$C$33, Tarifas!$D$2:$D$33)), "Peso excedido", 1)) / J33))} -> 0.40520752 | L33: 69990 | M33: {=IF(OR(L33=0, L33=""), 0, 1 - ((((XLOOKUP($A33, 'datos de inventario'!$A:$A, 'datos de inventario'!$D:$D, 0) * 'datos de inventario'!$K$2) + (XLOOKUP($A33, 'datos de inventario'!$A:$A, 'datos de inventario'!$F:$F, 0) * 'datos de inventario'!$K$3 * 'datos de inventario'!$K$4)) * 1.19 + (L33 * 0.15) + XLOOKUP(MAX($Z33, (XLOOKUP($A33, 'datos de inventario'!$A:$A, 'datos de inventario'!$F:$F, 0) * 1000000 / 4000)) + 0.1, Tarifas!$A$2:$A$33, IF(L33 <= 9989, Tarifas!$B$2:$B$33, IF(L33 <= 19989, Tarifas!$C$2:$C$33, Tarifas!$D$2:$D$33)), "Peso excedido", 1)) / L33))} -> 0.34165666 | N33: - | O33: - | P33: - | Q33: - | R33: - | S33: - | T33: - | U33: =1-(J33/H33) -> 0.11112346 | V33: =1-(L33/J33) -> 0.12501563 | W33: 7.5 | X33: 36 | Y33: 28 | Z33: 1.8 | AB33: =W33*X33*Y33/1000000 -> 0.00756
A34: DISCOGOMA5KG | B34: - | H34: 18990 | I34: {=IF(OR(H34=0, H34=""), 0, 1 - ((((XLOOKUP($A34, 'datos de inventario'!$A:$A, 'datos de inventario'!$D:$D, 0) * 'datos de inventario'!$K$2) + (XLOOKUP($A34, 'datos de inventario'!$A:$A, 'datos de inventario'!$F:$F, 0) * 'datos de inventario'!$K$3 * 'datos de inventario'!$K$4)) * 1.19 + (H34 * 0.15) + XLOOKUP(MAX($Z34, (XLOOKUP($A34, 'datos de inventario'!$A:$A, 'datos de inventario'!$F:$F, 0) * 1000000 / 4000)) + 0.1, Tarifas!$A$2:$A$33, IF(H34 <= 9989, Tarifas!$B$2:$B$33, IF(H34 <= 19989, Tarifas!$C$2:$C$33, Tarifas!$D$2:$D$33)), "Peso excedido", 1)) / H34))} -> 0.39643227 | J34: 16990 | K34: {=IF(OR(J34=0, J34=""), 0, 1 - ((((XLOOKUP($A34, 'datos de inventario'!$A:$A, 'datos de inventario'!$D:$D, 0) * 'datos de inventario'!$K$2) + (XLOOKUP($A34, 'datos de inventario'!$A:$A, 'datos de inventario'!$F:$F, 0) * 'datos de inventario'!$K$3 * 'datos de inventario'!$K$4)) * 1.19 + (J34 * 0.15) + XLOOKUP(MAX($Z34, (XLOOKUP($A34, 'datos de inventario'!$A:$A, 'datos de inventario'!$F:$F, 0) * 1000000 / 4000)) + 0.1, Tarifas!$A$2:$A$33, IF(J34 <= 9989, Tarifas!$B$2:$B$33, IF(J34 <= 19989, Tarifas!$C$2:$C$33, Tarifas!$D$2:$D$33)), "Peso excedido", 1)) / J34))} -> 0.34303995 | L34: 14990 | M34: {=IF(OR(L34=0, L34=""), 0, 1 - ((((XLOOKUP($A34, 'datos de inventario'!$A:$A, 'datos de inventario'!$D:$D, 0) * 'datos de inventario'!$K$2) + (XLOOKUP($A34, 'datos de inventario'!$A:$A, 'datos de inventario'!$F:$F, 0) * 'datos de inventario'!$K$3 * 'datos de inventario'!$K$4)) * 1.19 + (L34 * 0.15) + XLOOKUP(MAX($Z34, (XLOOKUP($A34, 'datos de inventario'!$A:$A, 'datos de inventario'!$F:$F, 0) * 1000000 / 4000)) + 0.1, Tarifas!$A$2:$A$33, IF(L34 <= 9989, Tarifas!$B$2:$B$33, IF(L34 <= 19989, Tarifas!$C$2:$C$33, Tarifas!$D$2:$D$33)), "Peso excedido", 1)) / L34))} -> 0.27540018 | N34: - | O34: - | P34: - | Q34: - | R34: - | S34: - | T34: - | U34: =1-(J34/H34) -> 0.10531859 | V34: =1-(L34/J34) -> 0.1177163 | W34: 3 | X34: 47 | Y34: 47 | Z34: 5.4 | AB34: =W34*X34*Y34/1000000 -> 0.006627
A35: DISCOGOMA10KG | B35: - | H35: 44990 | I35: {=IF(OR(H35=0, H35=""), 0, 1 - ((((XLOOKUP($A35, 'datos de inventario'!$A:$A, 'datos de inventario'!$D:$D, 0) * 'datos de inventario'!$K$2) + (XLOOKUP($A35, 'datos de inventario'!$A:$A, 'datos de inventario'!$F:$F, 0) * 'datos de inventario'!$K$3 * 'datos de inventario'!$K$4)) * 1.19 + (H35 * 0.15) + XLOOKUP(MAX($Z35, (XLOOKUP($A35, 'datos de inventario'!$A:$A, 'datos de inventario'!$F:$F, 0) * 1000000 / 4000)) + 0.1, Tarifas!$A$2:$A$33, IF(H35 <= 9989, Tarifas!$B$2:$B$33, IF(H35 <= 19989, Tarifas!$C$2:$C$33, Tarifas!$D$2:$D$33)), "Peso excedido", 1)) / H35))} -> 0.39426174 | J35: 39990 | K35: {=IF(OR(J35=0, J35=""), 0, 1 - ((((XLOOKUP($A35, 'datos de inventario'!$A:$A, 'datos de inventario'!$D:$D, 0) * 'datos de inventario'!$K$2) + (XLOOKUP($A35, 'datos de inventario'!$A:$A, 'datos de inventario'!$F:$F, 0) * 'datos de inventario'!$K$3 * 'datos de inventario'!$K$4)) * 1.19 + (J35 * 0.15) + XLOOKUP(MAX($Z35, (XLOOKUP($A35, 'datos de inventario'!$A:$A, 'datos de inventario'!$F:$F, 0) * 1000000 / 4000)) + 0.1, Tarifas!$A$2:$A$33, IF(J35 <= 9989, Tarifas!$B$2:$B$33, IF(J35 <= 19989, Tarifas!$C$2:$C$33, Tarifas!$D$2:$D$33)), "Peso excedido", 1)) / J35))} -> 0.33728021 | L35: 37990 | M35: {=IF(OR(L35=0, L35=""), 0, 1 - ((((XLOOKUP($A35, 'datos de inventario'!$A:$A, 'datos de inventario'!$D:$D, 0) * 'datos de inventario'!$K$2) + (XLOOKUP($A35, 'datos de inventario'!$A:$A, 'datos de inventario'!$F:$F, 0) * 'datos de inventario'!$K$3 * 'datos de inventario'!$K$4)) * 1.19 + (L35 * 0.15) + XLOOKUP(MAX($Z35, (XLOOKUP($A35, 'datos de inventario'!$A:$A, 'datos de inventario'!$F:$F, 0) * 1000000 / 4000)) + 0.1, Tarifas!$A$2:$A$33, IF(L35 <= 9989, Tarifas!$B$2:$B$33, IF(L35 <= 19989, Tarifas!$C$2:$C$33, Tarifas!$D$2:$D$33)), "Peso excedido", 1)) / L35))} -> 0.31028785 | N35: - | O35: - | P35: - | Q35: - | R35: - | S35: - | T35: - | U35: =1-(J35/H35) -> 0.11113581 | V35: =1-(L35/J35) -> 0.050012503 | W35: 4 | X35: 47 | Y35: 47 | Z35: 10.3 | AB35: =W35*X35*Y35/1000000 -> 0.008836
A36: DISCOGOMA15KG | B36: - | H36: 59990 | I36: {=IF(OR(H36=0, H36=""), 0, 1 - ((((XLOOKUP($A36, 'datos de inventario'!$A:$A, 'datos de inventario'!$D:$D, 0) * 'datos de inventario'!$K$2) + (XLOOKUP($A36, 'datos de inventario'!$A:$A, 'datos de inventario'!$F:$F, 0) * 'datos de inventario'!$K$3 * 'datos de inventario'!$K$4)) * 1.19 + (H36 * 0.15) + XLOOKUP(MAX($Z36, (XLOOKUP($A36, 'datos de inventario'!$A:$A, 'datos de inventario'!$F:$F, 0) * 1000000 / 4000)) + 0.1, Tarifas!$A$2:$A$33, IF(H36 <= 9989, Tarifas!$B$2:$B$33, IF(H36 <= 19989, Tarifas!$C$2:$C$33, Tarifas!$D$2:$D$33)), "Peso excedido", 1)) / H36))} -> 0.39160785 | J36: 54990 | K36: {=IF(OR(J36=0, J36=""), 0, 1 - ((((XLOOKUP($A36, 'datos de inventario'!$A:$A, 'datos de inventario'!$D:$D, 0) * 'datos de inventario'!$K$2) + (XLOOKUP($A36, 'datos de inventario'!$A:$A, 'datos de inventario'!$F:$F, 0) * 'datos de inventario'!$K$3 * 'datos de inventario'!$K$4)) * 1.19 + (J36 * 0.15) + XLOOKUP(MAX($Z36, (XLOOKUP($A36, 'datos de inventario'!$A:$A, 'datos de inventario'!$F:$F, 0) * 1000000 / 4000)) + 0.1, Tarifas!$A$2:$A$33, IF(J36 <= 9989, Tarifas!$B$2:$B$33, IF(J36 <= 19989, Tarifas!$C$2:$C$33, Tarifas!$D$2:$D$33)), "Peso excedido", 1)) / J36))} -> 0.34992826 | L36: 49990 | M36: {=IF(OR(L36=0, L36=""), 0, 1 - ((((XLOOKUP($A36, 'datos de inventario'!$A:$A, 'datos de inventario'!$D:$D, 0) * 'datos de inventario'!$K$2) + (XLOOKUP($A36, 'datos de inventario'!$A:$A, 'datos de inventario'!$F:$F, 0) * 'datos de inventario'!$K$3 * 'datos de inventario'!$K$4)) * 1.19 + (L36 * 0.15) + XLOOKUP(MAX($Z36, (XLOOKUP($A36, 'datos de inventario'!$A:$A, 'datos de inventario'!$F:$F, 0) * 1000000 / 4000)) + 0.1, Tarifas!$A$2:$A$33, IF(L36 <= 9989, Tarifas!$B$2:$B$33, IF(L36 <= 19989, Tarifas!$C$2:$C$33, Tarifas!$D$2:$D$33)), "Peso excedido", 1)) / L36))} -> 0.29991108 | N36: - | O36: - | P36: - | Q36: - | R36: - | S36: - | T36: - | U36: =1-(J36/H36) -> 0.083347225 | V36: =1-(L36/J36) -> 0.090925623 | W36: 6 | X36: 47 | Y36: 47 | Z36: 15.5 | AB36: =W36*X36*Y36/1000000 -> 0.013254
A37: DISCOGOMA20KG | B37: - | H37: 74990 | I37: {=IF(OR(H37=0, H37=""), 0, 1 - ((((XLOOKUP($A37, 'datos de inventario'!$A:$A, 'datos de inventario'!$D:$D, 0) * 'datos de inventario'!$K$2) + (XLOOKUP($A37, 'datos de inventario'!$A:$A, 'datos de inventario'!$F:$F, 0) * 'datos de inventario'!$K$3 * 'datos de inventario'!$K$4)) * 1.19 + (H37 * 0.15) + XLOOKUP(MAX($Z37, (XLOOKUP($A37, 'datos de inventario'!$A:$A, 'datos de inventario'!$F:$F, 0) * 1000000 / 4000)) + 0.1, Tarifas!$A$2:$A$33, IF(H37 <= 9989, Tarifas!$B$2:$B$33, IF(H37 <= 19989, Tarifas!$C$2:$C$33, Tarifas!$D$2:$D$33)), "Peso excedido", 1)) / H37))} -> 0.38000933 | J37: 69990 | K37: {=IF(OR(J37=0, J37=""), 0, 1 - ((((XLOOKUP($A37, 'datos de inventario'!$A:$A, 'datos de inventario'!$D:$D, 0) * 'datos de inventario'!$K$2) + (XLOOKUP($A37, 'datos de inventario'!$A:$A, 'datos de inventario'!$F:$F, 0) * 'datos de inventario'!$K$3 * 'datos de inventario'!$K$4)) * 1.19 + (J37 * 0.15) + XLOOKUP(MAX($Z37, (XLOOKUP($A37, 'datos de inventario'!$A:$A, 'datos de inventario'!$F:$F, 0) * 1000000 / 4000)) + 0.1, Tarifas!$A$2:$A$33, IF(J37 <= 9989, Tarifas!$B$2:$B$33, IF(J37 <= 19989, Tarifas!$C$2:$C$33, Tarifas!$D$2:$D$33)), "Peso excedido", 1)) / J37))} -> 0.34643377 | L37: 64990 | M37: {=IF(OR(L37=0, L37=""), 0, 1 - ((((XLOOKUP($A37, 'datos de inventario'!$A:$A, 'datos de inventario'!$D:$D, 0) * 'datos de inventario'!$K$2) + (XLOOKUP($A37, 'datos de inventario'!$A:$A, 'datos de inventario'!$F:$F, 0) * 'datos de inventario'!$K$3 * 'datos de inventario'!$K$4)) * 1.19 + (L37 * 0.15) + XLOOKUP(MAX($Z37, (XLOOKUP($A37, 'datos de inventario'!$A:$A, 'datos de inventario'!$F:$F, 0) * 1000000 / 4000)) + 0.1, Tarifas!$A$2:$A$33, IF(L37 <= 9989, Tarifas!$B$2:$B$33, IF(L37 <= 19989, Tarifas!$C$2:$C$33, Tarifas!$D$2:$D$33)), "Peso excedido", 1)) / L37))} -> 0.30769194 | N37: - | O37: - | P37: - | Q37: - | R37: - | S37: - | T37: - | U37: =1-(J37/H37) -> 0.066675557 | V37: =1-(L37/J37) -> 0.071438777 | W37: 7 | X37: 47 | Y37: 47 | Z37: 20.6 | AB37: =W37*X37*Y37/1000000 -> 0.015463
A38: MAN30KGCRO | B38: - | H38: 99990 | I38: {=IF(OR(H38=0, H38=""), 0, 1 - ((((XLOOKUP($A38, 'datos de inventario'!$A:$A, 'datos de inventario'!$D:$D, 0) * 'datos de inventario'!$K$2) + (XLOOKUP($A38, 'datos de inventario'!$A:$A, 'datos de inventario'!$F:$F, 0) * 'datos de inventario'!$K$3 * 'datos de inventario'!$K$4)) * 1.19 + (H38 * 0.15) + XLOOKUP(MAX($Z38, (XLOOKUP($A38, 'datos de inventario'!$A:$A, 'datos de inventario'!$F:$F, 0) * 1000000 / 4000)) + 0.1, Tarifas!$A$2:$A$33, IF(H38 <= 9989, Tarifas!$B$2:$B$33, IF(H38 <= 19989, Tarifas!$C$2:$C$33, Tarifas!$D$2:$D$33)), "Peso excedido", 1)) / H38))} -> 0.35002158 | J38: 89990 | K38: {=IF(OR(J38=0, J38=""), 0, 1 - ((((XLOOKUP($A38, 'datos de inventario'!$A:$A, 'datos de inventario'!$D:$D, 0) * 'datos de inventario'!$K$2) + (XLOOKUP($A38, 'datos de inventario'!$A:$A, 'datos de inventario'!$F:$F, 0) * 'datos de inventario'!$K$3 * 'datos de inventario'!$K$4)) * 1.19 + (J38 * 0.15) + XLOOKUP(MAX($Z38, (XLOOKUP($A38, 'datos de inventario'!$A:$A, 'datos de inventario'!$F:$F, 0) * 1000000 / 4000)) + 0.1, Tarifas!$A$2:$A$33, IF(J38 <= 9989, Tarifas!$B$2:$B$33, IF(J38 <= 19989, Tarifas!$C$2:$C$33, Tarifas!$D$2:$D$33)), "Peso excedido", 1)) / J38))} -> 0.29446225 | L38: 84990 | M38: {=IF(OR(L38=0, L38=""), 0, 1 - ((((XLOOKUP($A38, 'datos de inventario'!$A:$A, 'datos de inventario'!$D:$D, 0) * 'datos de inventario'!$K$2) + (XLOOKUP($A38, 'datos de inventario'!$A:$A, 'datos de inventario'!$F:$F, 0) * 'datos de inventario'!$K$3 * 'datos de inventario'!$K$4)) * 1.19 + (L38 * 0.15) + XLOOKUP(MAX($Z38, (XLOOKUP($A38, 'datos de inventario'!$A:$A, 'datos de inventario'!$F:$F, 0) * 1000000 / 4000)) + 0.1, Tarifas!$A$2:$A$33, IF(L38 <= 9989, Tarifas!$B$2:$B$33, IF(L38 <= 19989, Tarifas!$C$2:$C$33, Tarifas!$D$2:$D$33)), "Peso excedido", 1)) / L38))} -> 0.26177971 | N38: - | O38: - | P38: - | Q38: - | R38: - | S38: - | T38: - | U38: =1-(J38/H38) -> 0.10001 | V38: =1-(L38/J38) -> 0.055561729 | W38: 32 | X38: 41.5 | Y38: 18 | Z38: 30 | AB38: =W38*X38*Y38/1000000 -> 0.023904
A39: HEXBAR23KG | B39: - | H39: 129990 | I39: {=IF(OR(H39=0, H39=""), 0, 1 - ((((XLOOKUP($A39, 'datos de inventario'!$A:$A, 'datos de inventario'!$D:$D, 0) * 'datos de inventario'!$K$2) + (XLOOKUP($A39, 'datos de inventario'!$A:$A, 'datos de inventario'!$F:$F, 0) * 'datos de inventario'!$K$3 * 'datos de inventario'!$K$4)) * 1.19 + (H39 * 0.15) + XLOOKUP(MAX($Z39, (XLOOKUP($A39, 'datos de inventario'!$A:$A, 'datos de inventario'!$F:$F, 0) * 1000000 / 4000)) + 0.1, Tarifas!$A$2:$A$33, IF(H39 <= 9989, Tarifas!$B$2:$B$33, IF(H39 <= 19989, Tarifas!$C$2:$C$33, Tarifas!$D$2:$D$33)), "Peso excedido", 1)) / H39))} -> 0.48185789 | J39: 119990 | K39: {=IF(OR(J39=0, J39=""), 0, 1 - ((((XLOOKUP($A39, 'datos de inventario'!$A:$A, 'datos de inventario'!$D:$D, 0) * 'datos de inventario'!$K$2) + (XLOOKUP($A39, 'datos de inventario'!$A:$A, 'datos de inventario'!$F:$F, 0) * 'datos de inventario'!$K$3 * 'datos de inventario'!$K$4)) * 1.19 + (J39 * 0.15) + XLOOKUP(MAX($Z39, (XLOOKUP($A39, 'datos de inventario'!$A:$A, 'datos de inventario'!$F:$F, 0) * 1000000 / 4000)) + 0.1, Tarifas!$A$2:$A$33, IF(J39 <= 9989, Tarifas!$B$2:$B$33, IF(J39 <= 19989, Tarifas!$C$2:$C$33, Tarifas!$D$2:$D$33)), "Peso excedido", 1)) / J39))} -> 0.45117683 | L39: 109990 | M39: {=IF(OR(L39=0, L39=""), 0, 1 - ((((XLOOKUP($A39, 'datos de inventario'!$A:$A, 'datos de inventario'!$D:$D, 0) * 'datos de inventario'!$K$2) + (XLOOKUP($A39, 'datos de inventario'!$A:$A, 'datos de inventario'!$F:$F, 0) * 'datos de inventario'!$K$3 * 'datos de inventario'!$K$4)) * 1.19 + (L39 * 0.15) + XLOOKUP(MAX($Z39, (XLOOKUP($A39, 'datos de inventario'!$A:$A, 'datos de inventario'!$F:$F, 0) * 1000000 / 4000)) + 0.1, Tarifas!$A$2:$A$33, IF(L39 <= 9989, Tarifas!$B$2:$B$33, IF(L39 <= 19989, Tarifas!$C$2:$C$33, Tarifas!$D$2:$D$33)), "Peso excedido", 1)) / L39))} -> 0.41491688 | N39: - | O39: - | P39: - | Q39: - | R39: - | S39: - | T39: - | U39: =1-(J39/H39) -> 0.076928995 | V39: =1-(L39/J39) -> 0.083340278 | W39: 57 | X39: 142 | Y39: 10 | Z39: 22.3 | AB39: =W39*X39*Y39/1000000 -> 0.08094
A40: TECLM004 | W40: 11.5 | X40: 102 | Y40: 30 | Z40: 4.154 | AB40: =W40*X40*Y40/1000000 -> 0.03519
A41: STRAPGYM001 | B41: Straps Correas Levantamiento De Pesas Gym | C41: Lifting Straps Muñequeras Overfit Gym Correas Levantamientos | D41: =LEN(C41) -> 60 | E41: Lifting Straps Muñequeras Overfit Gym Correas Para Levantamientos De Pesas Y Barras | H41: 7990 | I41: {=IF(OR(H41=0, H41=""), 0, 1 - ((((XLOOKUP($A41, 'datos de inventario'!$A:$A, 'datos de inventario'!$D:$D, 0) * 'datos de inventario'!$K$2) + (XLOOKUP($A41, 'datos de inventario'!$A:$A, 'datos de inventario'!$F:$F, 0) * 'datos de inventario'!$K$3 * 'datos de inventario'!$K$4)) * 1.19 + (H41 * 0.15) + XLOOKUP(MAX($Z41, (XLOOKUP($A41, 'datos de inventario'!$A:$A, 'datos de inventario'!$F:$F, 0) * 1000000 / 4000)) + 0.1, Tarifas!$A$2:$A$33, IF(H41 <= 9989, Tarifas!$B$2:$B$33, IF(H41 <= 19989, Tarifas!$C$2:$C$33, Tarifas!$D$2:$D$33)), "Peso excedido", 1)) / H41))} -> 0.45037165 | J41: 6990 | K41: {=IF(OR(J41=0, J41=""), 0, 1 - ((((XLOOKUP($A41, 'datos de inventario'!$A:$A, 'datos de inventario'!$D:$D, 0) * 'datos de inventario'!$K$2) + (XLOOKUP($A41, 'datos de inventario'!$A:$A, 'datos de inventario'!$F:$F, 0) * 'datos de inventario'!$K$3 * 'datos de inventario'!$K$4)) * 1.19 + (J41 * 0.15) + XLOOKUP(MAX($Z41, (XLOOKUP($A41, 'datos de inventario'!$A:$A, 'datos de inventario'!$F:$F, 0) * 1000000 / 4000)) + 0.1, Tarifas!$A$2:$A$33, IF(J41 <= 9989, Tarifas!$B$2:$B$33, IF(J41 <= 19989, Tarifas!$C$2:$C$33, Tarifas!$D$2:$D$33)), "Peso excedido", 1)) / J41))} -> 0.39320021 | L41: 5990 | M41: {=IF(OR(L41=0, L41=""), 0, 1 - ((((XLOOKUP($A41, 'datos de inventario'!$A:$A, 'datos de inventario'!$D:$D, 0) * 'datos de inventario'!$K$2) + (XLOOKUP($A41, 'datos de inventario'!$A:$A, 'datos de inventario'!$F:$F, 0) * 'datos de inventario'!$K$3 * 'datos de inventario'!$K$4)) * 1.19 + (L41 * 0.15) + XLOOKUP(MAX($Z41, (XLOOKUP($A41, 'datos de inventario'!$A:$A, 'datos de inventario'!$F:$F, 0) * 1000000 / 4000)) + 0.1, Tarifas!$A$2:$A$33, IF(L41 <= 9989, Tarifas!$B$2:$B$33, IF(L41 <= 19989, Tarifas!$C$2:$C$33, Tarifas!$D$2:$D$33)), "Peso excedido", 1)) / L41))} -> 0.31693982 | N41: Vestuario y CalzadoRopa DeportivaOtrosMunequera Levantamiento de Pesas | AB41: =W41*X41*Y41/1000000 -> 0
A42: GUANTESGYM001 | B42: Guantes gym entrenamiento pesas talla L | C42: Guantes Gym Deportivos Overfit Talla L Entrenamiento Pesas | D42: =LEN(C42) -> 58 | E42: Guantes Gym Deportivos Overfit Talla L Entrenamiento Levantamiento Pesas Fitness | H42: 8990 | I42: {=IF(OR(H42=0, H42=""), 0, 1 - ((((XLOOKUP($A42, 'datos de inventario'!$A:$A, 'datos de inventario'!$D:$D, 0) * 'datos de inventario'!$K$2) + (XLOOKUP($A42, 'datos de inventario'!$A:$A, 'datos de inventario'!$F:$F, 0) * 'datos de inventario'!$K$3 * 'datos de inventario'!$K$4)) * 1.19 + (H42 * 0.15) + XLOOKUP(MAX($Z42, (XLOOKUP($A42, 'datos de inventario'!$A:$A, 'datos de inventario'!$F:$F, 0) * 1000000 / 4000)) + 0.1, Tarifas!$A$2:$A$33, IF(H42 <= 9989, Tarifas!$B$2:$B$33, IF(H42 <= 19989, Tarifas!$C$2:$C$33, Tarifas!$D$2:$D$33)), "Peso excedido", 1)) / H42))} -> 0.4115639 | J42: 7990 | K42: {=IF(OR(J42=0, J42=""), 0, 1 - ((((XLOOKUP($A42, 'datos de inventario'!$A:$A, 'datos de inventario'!$D:$D, 0) * 'datos de inventario'!$K$2) + (XLOOKUP($A42, 'datos de inventario'!$A:$A, 'datos de inventario'!$F:$F, 0) * 'datos de inventario'!$K$3 * 'datos de inventario'!$K$4)) * 1.19 + (J42 * 0.15) + XLOOKUP(MAX($Z42, (XLOOKUP($A42, 'datos de inventario'!$A:$A, 'datos de inventario'!$F:$F, 0) * 1000000 / 4000)) + 0.1, Tarifas!$A$2:$A$33, IF(J42 <= 9989, Tarifas!$B$2:$B$33, IF(J42 <= 19989, Tarifas!$C$2:$C$33, Tarifas!$D$2:$D$33)), "Peso excedido", 1)) / J42))} -> 0.3566908 | L42: 6990 | M42: {=IF(OR(L42=0, L42=""), 0, 1 - ((((XLOOKUP($A42, 'datos de inventario'!$A:$A, 'datos de inventario'!$D:$D, 0) * 'datos de inventario'!$K$2) + (XLOOKUP($A42, 'datos de inventario'!$A:$A, 'datos de inventario'!$F:$F, 0) * 'datos de inventario'!$K$3 * 'datos de inventario'!$K$4)) * 1.19 + (L42 * 0.15) + XLOOKUP(MAX($Z42, (XLOOKUP($A42, 'datos de inventario'!$A:$A, 'datos de inventario'!$F:$F, 0) * 1000000 / 4000)) + 0.1, Tarifas!$A$2:$A$33, IF(L42 <= 9989, Tarifas!$B$2:$B$33, IF(L42 <= 19989, Tarifas!$C$2:$C$33, Tarifas!$D$2:$D$33)), "Peso excedido", 1)) / L42))} -> 0.28611724 | N42: Vestuario y CalzadoRopa DeportivaGuantes | AB42: =W42*X42*Y42/1000000 -> 0
A43: GUANTESGYM002 | B43: Guantes gym entrenamiento fitness talla L | C43: Guantes Gym Deportivos Overfit Talla L Entrenamiento Fitness | D43: =LEN(C43) -> 60 | E43: Guantes Gym Deportivos Overfit Talla L Entrenamiento Levantamiento Fitness Pesas | H43: 10990 | I43: {=IF(OR(H43=0, H43=""), 0, 1 - ((((XLOOKUP($A43, 'datos de inventario'!$A:$A, 'datos de inventario'!$D:$D, 0) * 'datos de inventario'!$K$2) + (XLOOKUP($A43, 'datos de inventario'!$A:$A, 'datos de inventario'!$F:$F, 0) * 'datos de inventario'!$K$3 * 'datos de inventario'!$K$4)) * 1.19 + (H43 * 0.15) + XLOOKUP(MAX($Z43, (XLOOKUP($A43, 'datos de inventario'!$A:$A, 'datos de inventario'!$F:$F, 0) * 1000000 / 4000)) + 0.1, Tarifas!$A$2:$A$33, IF(H43 <= 9989, Tarifas!$B$2:$B$33, IF(H43 <= 19989, Tarifas!$C$2:$C$33, Tarifas!$D$2:$D$33)), "Peso excedido", 1)) / H43))} -> 0.37700086 | J43: 9990 | K43: {=IF(OR(J43=0, J43=""), 0, 1 - ((((XLOOKUP($A43, 'datos de inventario'!$A:$A, 'datos de inventario'!$D:$D, 0) * 'datos de inventario'!$K$2) + (XLOOKUP($A43, 'datos de inventario'!$A:$A, 'datos de inventario'!$F:$F, 0) * 'datos de inventario'!$K$3 * 'datos de inventario'!$K$4)) * 1.19 + (J43 * 0.15) + XLOOKUP(MAX($Z43, (XLOOKUP($A43, 'datos de inventario'!$A:$A, 'datos de inventario'!$F:$F, 0) * 1000000 / 4000)) + 0.1, Tarifas!$A$2:$A$33, IF(J43 <= 9989, Tarifas!$B$2:$B$33, IF(J43 <= 19989, Tarifas!$C$2:$C$33, Tarifas!$D$2:$D$33)), "Peso excedido", 1)) / J43))} -> 0.3296536 | L43: 8990 | M43: {=IF(OR(L43=0, L43=""), 0, 1 - ((((XLOOKUP($A43, 'datos de inventario'!$A:$A, 'datos de inventario'!$D:$D, 0) * 'datos de inventario'!$K$2) + (XLOOKUP($A43, 'datos de inventario'!$A:$A, 'datos de inventario'!$F:$F, 0) * 'datos de inventario'!$K$3 * 'datos de inventario'!$K$4)) * 1.19 + (L43 * 0.15) + XLOOKUP(MAX($Z43, (XLOOKUP($A43, 'datos de inventario'!$A:$A, 'datos de inventario'!$F:$F, 0) * 1000000 / 4000)) + 0.1, Tarifas!$A$2:$A$33, IF(L43 <= 9989, Tarifas!$B$2:$B$33, IF(L43 <= 19989, Tarifas!$C$2:$C$33, Tarifas!$D$2:$D$33)), "Peso excedido", 1)) / L43))} -> 0.29401997 | N43: Vestuario y CalzadoRopa DeportivaGuantes | AB43: =W43*X43*Y43/1000000 -> 0
A44: BARRALED002BLA | B44: Luz barra Led 30cm Portátil sensor de movimiento blanca | C44: Aplique Pared Luz Led Hosser Barra Con Sensor De Movimiento | D44: =LEN(C44) -> 59 | E44: Aplique Pared Luz Led Hosser Barra Con Sensor De Movimiento Blanco | H44: 18990 | I44: {=IF(OR(H44=0, H44=""), 0, 1 - ((((XLOOKUP($A44, 'datos de inventario'!$A:$A, 'datos de inventario'!$D:$D, 0) * 'datos de inventario'!$K$2) + (XLOOKUP($A44, 'datos de inventario'!$A:$A, 'datos de inventario'!$F:$F, 0) * 'datos de inventario'!$K$3 * 'datos de inventario'!$K$4)) * 1.19 + (H44 * 0.15) + XLOOKUP(MAX($Z44, (XLOOKUP($A44, 'datos de inventario'!$A:$A, 'datos de inventario'!$F:$F, 0) * 1000000 / 4000)) + 0.1, Tarifas!$A$2:$A$33, IF(H44 <= 9989, Tarifas!$B$2:$B$33, IF(H44 <= 19989, Tarifas!$C$2:$C$33, Tarifas!$D$2:$D$33)), "Peso excedido", 1)) / H44))} -> 0.64837138 | J44: 14990 | K44: {=IF(OR(J44=0, J44=""), 0, 1 - ((((XLOOKUP($A44, 'datos de inventario'!$A:$A, 'datos de inventario'!$D:$D, 0) * 'datos de inventario'!$K$2) + (XLOOKUP($A44, 'datos de inventario'!$A:$A, 'datos de inventario'!$F:$F, 0) * 'datos de inventario'!$K$3 * 'datos de inventario'!$K$4)) * 1.19 + (J44 * 0.15) + XLOOKUP(MAX($Z44, (XLOOKUP($A44, 'datos de inventario'!$A:$A, 'datos de inventario'!$F:$F, 0) * 1000000 / 4000)) + 0.1, Tarifas!$A$2:$A$33, IF(J44 <= 9989, Tarifas!$B$2:$B$33, IF(J44 <= 19989, Tarifas!$C$2:$C$33, Tarifas!$D$2:$D$33)), "Peso excedido", 1)) / J44))} -> 0.59456788 | L44: 13990 | M44: {=IF(OR(L44=0, L44=""), 0, 1 - ((((XLOOKUP($A44, 'datos de inventario'!$A:$A, 'datos de inventario'!$D:$D, 0) * 'datos de inventario'!$K$2) + (XLOOKUP($A44, 'datos de inventario'!$A:$A, 'datos de inventario'!$F:$F, 0) * 'datos de inventario'!$K$3 * 'datos de inventario'!$K$4)) * 1.19 + (L44 * 0.15) + XLOOKUP(MAX($Z44, (XLOOKUP($A44, 'datos de inventario'!$A:$A, 'datos de inventario'!$F:$F, 0) * 1000000 / 4000)) + 0.1, Tarifas!$A$2:$A$33, IF(L44 <= 9989, Tarifas!$B$2:$B$33, IF(L44 <= 19989, Tarifas!$C$2:$C$33, Tarifas!$D$2:$D$33)), "Peso excedido", 1)) / L44))} -> 0.57630969 | N44: Hogar y MueblesIluminación para el HogarLámparasApliques de ParedAplique | AB44: =W44*X44*Y44/1000000 -> 0
A45: CABLETRENZACC2M | B45: Cable conexion USB C A USB C 2 metros | C45: Cable Usb C A C 2 Metros Iphone Samsung Carga Rapida Hosser | D45: =LEN(C45) -> 59 | E45: Cable Usb Tipo C A C 2 metros Carga Rapida Iphone Samsung 100 Watts Hosser Trenzado Negro | F45: Cable Usb C A C 2 Metros Iphone Samsung Carga Rapida Hosser | G45: =LEN(F45) -> 59 | H45: 12990 | I45: {=IF(OR(H45=0, H45=""), 0, 1 - ((((XLOOKUP($A45, 'datos de inventario'!$A:$A, 'datos de inventario'!$D:$D, 0) * 'datos de inventario'!$K$2) + (XLOOKUP($A45, 'datos de inventario'!$A:$A, 'datos de inventario'!$F:$F, 0) * 'datos de inventario'!$K$3 * 'datos de inventario'!$K$4)) * 1.19 + (H45 * 0.15) + XLOOKUP(MAX($Z45, (XLOOKUP($A45, 'datos de inventario'!$A:$A, 'datos de inventario'!$F:$F, 0) * 1000000 / 4000)) + 0.1, Tarifas!$A$2:$A$33, IF(H45 <= 9989, Tarifas!$B$2:$B$33, IF(H45 <= 19989, Tarifas!$C$2:$C$33, Tarifas!$D$2:$D$33)), "Peso excedido", 1)) / H45))} -> 0.56108732 | J45: 9990 | K45: {=IF(OR(J45=0, J45=""), 0, 1 - ((((XLOOKUP($A45, 'datos de inventario'!$A:$A, 'datos de inventario'!$D:$D, 0) * 'datos de inventario'!$K$2) + (XLOOKUP($A45, 'datos de inventario'!$A:$A, 'datos de inventario'!$F:$F, 0) * 'datos de inventario'!$K$3 * 'datos de inventario'!$K$4)) * 1.19 + (J45 * 0.15) + XLOOKUP(MAX($Z45, (XLOOKUP($A45, 'datos de inventario'!$A:$A, 'datos de inventario'!$F:$F, 0) * 1000000 / 4000)) + 0.1, Tarifas!$A$2:$A$33, IF(J45 <= 9989, Tarifas!$B$2:$B$33, IF(J45 <= 19989, Tarifas!$C$2:$C$33, Tarifas!$D$2:$D$33)), "Peso excedido", 1)) / J45))} -> 0.47432675 | L45: 8990 | M45: {=IF(OR(L45=0, L45=""), 0, 1 - ((((XLOOKUP($A45, 'datos de inventario'!$A:$A, 'datos de inventario'!$D:$D, 0) * 'datos de inventario'!$K$2) + (XLOOKUP($A45, 'datos de inventario'!$A:$A, 'datos de inventario'!$F:$F, 0) * 'datos de inventario'!$K$3 * 'datos de inventario'!$K$4)) * 1.19 + (L45 * 0.15) + XLOOKUP(MAX($Z45, (XLOOKUP($A45, 'datos de inventario'!$A:$A, 'datos de inventario'!$F:$F, 0) * 1000000 / 4000)) + 0.1, Tarifas!$A$2:$A$33, IF(L45 <= 9989, Tarifas!$B$2:$B$33, IF(L45 <= 19989, Tarifas!$C$2:$C$33, Tarifas!$D$2:$D$33)), "Peso excedido", 1)) / L45))} -> 0.45478579 | N45: Celulares y TelefoníaAccesorios para CelularesCables de DatosUgreen Cargador | P45: 2.3 | Q45: =(P45/7)*30 -> 9.8571429 | R45: 7 | S45: =(R45/7)*30 -> 30 | T45: 45992 | U45: =1-(J45/H45) -> 0.23094688 | V45: =1-(L45/J45) -> 0.1001001 | AB45: =W45*X45*Y45/1000000 -> 0
A46: CABLETRENZAUSBC5M | B46: Cable conexion USB A USB C 5 metros | C46: Cable Usb Tipo C To Usb 5 M Iphone Samsung Hosser Carga Rapi | D46: =LEN(C46) -> 60 | E46: Cable Usb Tipo C To Usb 5 metros Carga rapida Iphone Samsung 60 Watts Hosser Trenzado Negro | F46: Cable Usb Tipo C To Usb 5 M Iphone Samsung Hosser Carga Rapida | G46: =LEN(F46) -> 62 | H46: 11990 | I46: {=IF(OR(H46=0, H46=""), 0, 1 - ((((XLOOKUP($A46, 'datos de inventario'!$A:$A, 'datos de inventario'!$D:$D, 0) * 'datos de inventario'!$K$2) + (XLOOKUP($A46, 'datos de inventario'!$A:$A, 'datos de inventario'!$F:$F, 0) * 'datos de inventario'!$K$3 * 'datos de inventario'!$K$4)) * 1.19 + (H46 * 0.15) + XLOOKUP(MAX($Z46, (XLOOKUP($A46, 'datos de inventario'!$A:$A, 'datos de inventario'!$F:$F, 0) * 1000000 / 4000)) + 0.1, Tarifas!$A$2:$A$33, IF(H46 <= 9989, Tarifas!$B$2:$B$33, IF(H46 <= 19989, Tarifas!$C$2:$C$33, Tarifas!$D$2:$D$33)), "Peso excedido", 1)) / H46))} -> 0.42223409 | J46: 9990 | K46: {=IF(OR(J46=0, J46=""), 0, 1 - ((((XLOOKUP($A46, 'datos de inventario'!$A:$A, 'datos de inventario'!$D:$D, 0) * 'datos de inventario'!$K$2) + (XLOOKUP($A46, 'datos de inventario'!$A:$A, 'datos de inventario'!$F:$F, 0) * 'datos de inventario'!$K$3 * 'datos de inventario'!$K$4)) * 1.19 + (J46 * 0.15) + XLOOKUP(MAX($Z46, (XLOOKUP($A46, 'datos de inventario'!$A:$A, 'datos de inventario'!$F:$F, 0) * 1000000 / 4000)) + 0.1, Tarifas!$A$2:$A$33, IF(J46 <= 9989, Tarifas!$B$2:$B$33, IF(J46 <= 19989, Tarifas!$C$2:$C$33, Tarifas!$D$2:$D$33)), "Peso excedido", 1)) / J46))} -> 0.33659527 | L46: 8990 | M46: {=IF(OR(L46=0, L46=""), 0, 1 - ((((XLOOKUP($A46, 'datos de inventario'!$A:$A, 'datos de inventario'!$D:$D, 0) * 'datos de inventario'!$K$2) + (XLOOKUP($A46, 'datos de inventario'!$A:$A, 'datos de inventario'!$F:$F, 0) * 'datos de inventario'!$K$3 * 'datos de inventario'!$K$4)) * 1.19 + (L46 * 0.15) + XLOOKUP(MAX($Z46, (XLOOKUP($A46, 'datos de inventario'!$A:$A, 'datos de inventario'!$F:$F, 0) * 1000000 / 4000)) + 0.1, Tarifas!$A$2:$A$33, IF(L46 <= 9989, Tarifas!$B$2:$B$33, IF(L46 <= 19989, Tarifas!$C$2:$C$33, Tarifas!$D$2:$D$33)), "Peso excedido", 1)) / L46))} -> 0.30173379 | N46: Celulares y TelefoníaAccesorios para CelularesCables de DatosUgreen Cargador | P46: 2.3 | Q46: =(P46/7)*30 -> 9.8571429 | R46: 7 | S46: =(R46/7)*30 -> 30 | T46: 45992 | U46: =1-(J46/H46) -> 0.16680567 | V46: =1-(L46/J46) -> 0.1001001 | AB46: =W46*X46*Y46/1000000 -> 0
A47: CABLETRENZAUSBC2M | B47: Cable conexion USB A USB C 2 metros | C47: Cable Usb Tipo C To Usb 2 M Iphone Samsung Hosser Carga Rapi | D47: =LEN(C47) -> 60 | E47: Cable Usb Tipo C To Usb 2 metros Carga rapida Iphone Samsung 60 Watts Hosser Trenzado Negro | F47: Cable Usb Tipo C To Usb 2 M Iphone Samsung Hosser Carga Rapida | G47: =LEN(F47) -> 62 | H47: 9990 | I47: {=IF(OR(H47=0, H47=""), 0, 1 - ((((XLOOKUP($A47, 'datos de inventario'!$A:$A, 'datos de inventario'!$D:$D, 0) * 'datos de inventario'!$K$2) + (XLOOKUP($A47, 'datos de inventario'!$A:$A, 'datos de inventario'!$F:$F, 0) * 'datos de inventario'!$K$3 * 'datos de inventario'!$K$4)) * 1.19 + (H47 * 0.15) + XLOOKUP(MAX($Z47, (XLOOKUP($A47, 'datos de inventario'!$A:$A, 'datos de inventario'!$F:$F, 0) * 1000000 / 4000)) + 0.1, Tarifas!$A$2:$A$33, IF(H47 <= 9989, Tarifas!$B$2:$B$33, IF(H47 <= 19989, Tarifas!$C$2:$C$33, Tarifas!$D$2:$D$33)), "Peso excedido", 1)) / H47))} -> 0.5334962 | J47: 8990 | K47: {=IF(OR(J47=0, J47=""), 0, 1 - ((((XLOOKUP($A47, 'datos de inventario'!$A:$A, 'datos de inventario'!$D:$D, 0) * 'datos de inventario'!$K$2) + (XLOOKUP($A47, 'datos de inventario'!$A:$A, 'datos de inventario'!$F:$F, 0) * 'datos de inventario'!$K$3 * 'datos de inventario'!$K$4)) * 1.19 + (J47 * 0.15) + XLOOKUP(MAX($Z47, (XLOOKUP($A47, 'datos de inventario'!$A:$A, 'datos de inventario'!$F:$F, 0) * 1000000 / 4000)) + 0.1, Tarifas!$A$2:$A$33, IF(J47 <= 9989, Tarifas!$B$2:$B$33, IF(J47 <= 19989, Tarifas!$C$2:$C$33, Tarifas!$D$2:$D$33)), "Peso excedido", 1)) / J47))} -> 0.52053693 | L47: 7990 | M47: {=IF(OR(L47=0, L47=""), 0, 1 - ((((XLOOKUP($A47, 'datos de inventario'!$A:$A, 'datos de inventario'!$D:$D, 0) * 'datos de inventario'!$K$2) + (XLOOKUP($A47, 'datos de inventario'!$A:$A, 'datos de inventario'!$F:$F, 0) * 'datos de inventario'!$K$3 * 'datos de inventario'!$K$4)) * 1.19 + (L47 * 0.15) + XLOOKUP(MAX($Z47, (XLOOKUP($A47, 'datos de inventario'!$A:$A, 'datos de inventario'!$F:$F, 0) * 1000000 / 4000)) + 0.1, Tarifas!$A$2:$A$33, IF(L47 <= 9989, Tarifas!$B$2:$B$33, IF(L47 <= 19989, Tarifas!$C$2:$C$33, Tarifas!$D$2:$D$33)), "Peso excedido", 1)) / L47))} -> 0.4793025 | N47: Celulares y TelefoníaAccesorios para CelularesCables de DatosUgreen Cargador | P47: 2.3 | Q47: =(P47/7)*30 -> 9.8571429 | R47: 7 | S47: =(R47/7)*30 -> 30 | T47: 45992 | U47: =1-(J47/H47) -> 0.1001001 | V47: =1-(L47/J47) -> 0.11123471 | AB47: =W47*X47*Y47/1000000 -> 0
A48: BOTASCOMPRESION001 | B48: Masajeador de compresión de piernas bota inalámbrica | C48: Bota De Compresion Presoterapia Pierna Masajeador Howell | D48: =LEN(C48) -> 57 | E48: Bota De Compresion Equipo Presoterapia Para Pierna Masajeador Aire Inalambrico Howell Negro | F48: Bota Compresion Equipo Presoterapia Pierna Masajeador Aire Howell | G48: =LEN(F48) -> 66 | H48: 89990 | I48: {=IF(OR(H48=0, H48=""), 0, 1 - ((((XLOOKUP($A48, 'datos de inventario'!$A:$A, 'datos de inventario'!$D:$D, 0) * 'datos de inventario'!$K$2) + (XLOOKUP($A48, 'datos de inventario'!$A:$A, 'datos de inventario'!$F:$F, 0) * 'datos de inventario'!$K$3 * 'datos de inventario'!$K$4)) * 1.19 + (H48 * 0.15) + XLOOKUP(MAX($Z48, (XLOOKUP($A48, 'datos de inventario'!$A:$A, 'datos de inventario'!$F:$F, 0) * 1000000 / 4000)) + 0.1, Tarifas!$A$2:$A$33, IF(H48 <= 9989, Tarifas!$B$2:$B$33, IF(H48 <= 19989, Tarifas!$C$2:$C$33, Tarifas!$D$2:$D$33)), "Peso excedido", 1)) / H48))} -> 0.4546344 | J48: 79990 | K48: {=IF(OR(J48=0, J48=""), 0, 1 - ((((XLOOKUP($A48, 'datos de inventario'!$A:$A, 'datos de inventario'!$D:$D, 0) * 'datos de inventario'!$K$2) + (XLOOKUP($A48, 'datos de inventario'!$A:$A, 'datos de inventario'!$F:$F, 0) * 'datos de inventario'!$K$3 * 'datos de inventario'!$K$4)) * 1.19 + (J48 * 0.15) + XLOOKUP(MAX($Z48, (XLOOKUP($A48, 'datos de inventario'!$A:$A, 'datos de inventario'!$F:$F, 0) * 1000000 / 4000)) + 0.1, Tarifas!$A$2:$A$33, IF(J48 <= 9989, Tarifas!$B$2:$B$33, IF(J48 <= 19989, Tarifas!$C$2:$C$33, Tarifas!$D$2:$D$33)), "Peso excedido", 1)) / J48))} -> 0.40520752 | L48: 69990 | M48: {=IF(OR(L48=0, L48=""), 0, 1 - ((((XLOOKUP($A48, 'datos de inventario'!$A:$A, 'datos de inventario'!$D:$D, 0) * 'datos de inventario'!$K$2) + (XLOOKUP($A48, 'datos de inventario'!$A:$A, 'datos de inventario'!$F:$F, 0) * 'datos de inventario'!$K$3 * 'datos de inventario'!$K$4)) * 1.19 + (L48 * 0.15) + XLOOKUP(MAX($Z48, (XLOOKUP($A48, 'datos de inventario'!$A:$A, 'datos de inventario'!$F:$F, 0) * 1000000 / 4000)) + 0.1, Tarifas!$A$2:$A$33, IF(L48 <= 9989, Tarifas!$B$2:$B$33, IF(L48 <= 19989, Tarifas!$C$2:$C$33, Tarifas!$D$2:$D$33)), "Peso excedido", 1)) / L48))} -> 0.34165666 | N48: Belleza y Cuidado PersonalTratamientos de BellezaEquipos de Estética CorporalPresoterapia | P48: 0.5 | Q48: =(P48/7)*30 -> 2.1428571 | R48: 1.9 | S48: =(R48/7)*30 -> 8.1428571 | T48: 45992 | U48: =1-(J48/H48) -> 0.11112346 | V48: =1-(L48/J48) -> 0.12501563 | AB48: =W48*X48*Y48/1000000 -> 0
A49: CUCHI002 | B49: Cuchillo chef 7 pulgadas acero inoxidable | C49: Cuchillo Chef Profesional 18 Cm Fervora Cocina Acero Inox | D49: =LEN(C49) -> 57 | E49: Cuchillo Chef Profesional 18 Cm Fervora Cocina Acero Inoxidable Gris | F49: Cuchillo Chef Profesional 18 Cm Fervora Cocina Acero Inoxidable Gris | G49: =LEN(F49) -> 69 | H49: 23990 | I49: {=IF(OR(H49=0, H49=""), 0, 1 - ((((XLOOKUP($A49, 'datos de inventario'!$A:$A, 'datos de inventario'!$D:$D, 0) * 'datos de inventario'!$K$2) + (XLOOKUP($A49, 'datos de inventario'!$A:$A, 'datos de inventario'!$F:$F, 0) * 'datos de inventario'!$K$3 * 'datos de inventario'!$K$4)) * 1.19 + (H49 * 0.15) + XLOOKUP(MAX($Z49, (XLOOKUP($A49, 'datos de inventario'!$A:$A, 'datos de inventario'!$F:$F, 0) * 1000000 / 4000)) + 0.1, Tarifas!$A$2:$A$33, IF(H49 <= 9989, Tarifas!$B$2:$B$33, IF(H49 <= 19989, Tarifas!$C$2:$C$33, Tarifas!$D$2:$D$33)), "Peso excedido", 1)) / H49))} -> 0.52001886 | J49: 21990 | K49: {=IF(OR(J49=0, J49=""), 0, 1 - ((((XLOOKUP($A49, 'datos de inventario'!$A:$A, 'datos de inventario'!$D:$D, 0) * 'datos de inventario'!$K$2) + (XLOOKUP($A49, 'datos de inventario'!$A:$A, 'datos de inventario'!$F:$F, 0) * 'datos de inventario'!$K$3 * 'datos de inventario'!$K$4)) * 1.19 + (J49 * 0.15) + XLOOKUP(MAX($Z49, (XLOOKUP($A49, 'datos de inventario'!$A:$A, 'datos de inventario'!$F:$F, 0) * 1000000 / 4000)) + 0.1, Tarifas!$A$2:$A$33, IF(J49 <= 9989, Tarifas!$B$2:$B$33, IF(J49 <= 19989, Tarifas!$C$2:$C$33, Tarifas!$D$2:$D$33)), "Peso excedido", 1)) / J49))} -> 0.49000693 | L49: 19980 | M49: {=IF(OR(L49=0, L49=""), 0, 1 - ((((XLOOKUP($A49, 'datos de inventario'!$A:$A, 'datos de inventario'!$D:$D, 0) * 'datos de inventario'!$K$2) + (XLOOKUP($A49, 'datos de inventario'!$A:$A, 'datos de inventario'!$F:$F, 0) * 'datos de inventario'!$K$3 * 'datos de inventario'!$K$4)) * 1.19 + (L49 * 0.15) + XLOOKUP(MAX($Z49, (XLOOKUP($A49, 'datos de inventario'!$A:$A, 'datos de inventario'!$F:$F, 0) * 1000000 / 4000)) + 0.1, Tarifas!$A$2:$A$33, IF(L49 <= 9989, Tarifas!$B$2:$B$33, IF(L49 <= 19989, Tarifas!$C$2:$C$33, Tarifas!$D$2:$D$33)), "Peso excedido", 1)) / L49))} -> 0.56039802 | N49: Hogar y MueblesCocina y MenajeVajilla y Artículos de ServirCuchilleríaCuchillos de Cocina | P49: 1.9 | Q49: =(P49/7)*30 -> 8.1428571 | R49: 4.7 | S49: =(R49/7)*30 -> 20.142857 | T49: 45992 | U49: =1-(J49/H49) -> 0.08336807 | V49: =1-(L49/J49) -> 0.091405184 | AB49: =W49*X49*Y49/1000000 -> 0
A50: WIPESADULTO001X8 | B50: toallitas húmedas de adulto pack x 8 | C50: Toallas Humedas Adultos Hipoalergenicas 60U Howell Pack 8 | D50: =LEN(C50) -> 57 | E50: Toallas Humedas Adultos Tamaño XG Howell Caja Family Set 8x60 Unidades Hipoalergenicas Con Aloe Vera | F50: Toallas Humedas Adultos Hipoalergenicas 60 Unidades Howell Pack 8 | G50: =LEN(F50) -> 65 | H50: 19990 | I50: {=IF(OR(H50=0, H50=""), 0, 1 - ((((XLOOKUP($A50, 'datos de inventario'!$A:$A, 'datos de inventario'!$D:$D, 0) * 'datos de inventario'!$K$2) + (XLOOKUP($A50, 'datos de inventario'!$A:$A, 'datos de inventario'!$F:$F, 0) * 'datos de inventario'!$K$3 * 'datos de inventario'!$K$4)) * 1.19 + (H50 * 0.15) + XLOOKUP(MAX($Z50, (XLOOKUP($A50, 'datos de inventario'!$A:$A, 'datos de inventario'!$F:$F, 0) * 1000000 / 4000)) + 0.1, Tarifas!$A$2:$A$33, IF(H50 <= 9989, Tarifas!$B$2:$B$33, IF(H50 <= 19989, Tarifas!$C$2:$C$33, Tarifas!$D$2:$D$33)), "Peso excedido", 1)) / H50))} -> 0.34432336 | J50: 17990 | K50: {=IF(OR(J50=0, J50=""), 0, 1 - ((((XLOOKUP($A50, 'datos de inventario'!$A:$A, 'datos de inventario'!$D:$D, 0) * 'datos de inventario'!$K$2) + (XLOOKUP($A50, 'datos de inventario'!$A:$A, 'datos de inventario'!$F:$F, 0) * 'datos de inventario'!$K$3 * 'datos de inventario'!$K$4)) * 1.19 + (J50 * 0.15) + XLOOKUP(MAX($Z50, (XLOOKUP($A50, 'datos de inventario'!$A:$A, 'datos de inventario'!$F:$F, 0) * 1000000 / 4000)) + 0.1, Tarifas!$A$2:$A$33, IF(J50 <= 9989, Tarifas!$B$2:$B$33, IF(J50 <= 19989, Tarifas!$C$2:$C$33, Tarifas!$D$2:$D$33)), "Peso excedido", 1)) / J50))} -> 0.44652718 | L50: 15990 | M50: {=IF(OR(L50=0, L50=""), 0, 1 - ((((XLOOKUP($A50, 'datos de inventario'!$A:$A, 'datos de inventario'!$D:$D, 0) * 'datos de inventario'!$K$2) + (XLOOKUP($A50, 'datos de inventario'!$A:$A, 'datos de inventario'!$F:$F, 0) * 'datos de inventario'!$K$3 * 'datos de inventario'!$K$4)) * 1.19 + (L50 * 0.15) + XLOOKUP(MAX($Z50, (XLOOKUP($A50, 'datos de inventario'!$A:$A, 'datos de inventario'!$F:$F, 0) * 1000000 / 4000)) + 0.1, Tarifas!$A$2:$A$33, IF(L50 <= 9989, Tarifas!$B$2:$B$33, IF(L50 <= 19989, Tarifas!$C$2:$C$33, Tarifas!$D$2:$D$33)), "Peso excedido", 1)) / L50))} -> 0.39606153 | N50: Belleza y Cuidado PersonalHigiene PersonalToallas HúmedasToallas Humedas Adultos | P50: 11.6 | Q50: =(P50/7)*30 -> 49.714286 | R50: 35 | S50: =(R50/7)*30 -> 150 | T50: 45992 | U50: =1-(J50/H50) -> 0.10005003 | V50: =1-(L50/J50) -> 0.11117287 | AB50: =W50*X50*Y50/1000000 -> 0
A51: WIPESBEBE001X12 | B51: toallitas húmedas de bebe pack x12 | C51: Toallitas Humedas Wipes Caja 12x60U 99% Agua Bebe Mimoru | D51: =LEN(C51) -> 57 | E51: Toallitas Humedas Mimoru Bebe Caja 12 x 60 Unidades Wipes 99% Agua Hipoalergenica | F51: Toallitas Humedas Mimoru Bebe Caja 12 x 60 Unidades Wipes 99% Agua | G51: =LEN(F51) -> 67 | H51: 18990 | I51: {=IF(OR(H51=0, H51=""), 0, 1 - ((((XLOOKUP($A51, 'datos de inventario'!$A:$A, 'datos de inventario'!$D:$D, 0) * 'datos de inventario'!$K$2) + (XLOOKUP($A51, 'datos de inventario'!$A:$A, 'datos de inventario'!$F:$F, 0) * 'datos de inventario'!$K$3 * 'datos de inventario'!$K$4)) * 1.19 + (H51 * 0.15) + XLOOKUP(MAX($Z51, (XLOOKUP($A51, 'datos de inventario'!$A:$A, 'datos de inventario'!$F:$F, 0) * 1000000 / 4000)) + 0.1, Tarifas!$A$2:$A$33, IF(H51 <= 9989, Tarifas!$B$2:$B$33, IF(H51 <= 19989, Tarifas!$C$2:$C$33, Tarifas!$D$2:$D$33)), "Peso excedido", 1)) / H51))} -> 0.46338004 | J51: 16990 | K51: {=IF(OR(J51=0, J51=""), 0, 1 - ((((XLOOKUP($A51, 'datos de inventario'!$A:$A, 'datos de inventario'!$D:$D, 0) * 'datos de inventario'!$K$2) + (XLOOKUP($A51, 'datos de inventario'!$A:$A, 'datos de inventario'!$F:$F, 0) * 'datos de inventario'!$K$3 * 'datos de inventario'!$K$4)) * 1.19 + (J51 * 0.15) + XLOOKUP(MAX($Z51, (XLOOKUP($A51, 'datos de inventario'!$A:$A, 'datos de inventario'!$F:$F, 0) * 1000000 / 4000)) + 0.1, Tarifas!$A$2:$A$33, IF(J51 <= 9989, Tarifas!$B$2:$B$33, IF(J51 <= 19989, Tarifas!$C$2:$C$33, Tarifas!$D$2:$D$33)), "Peso excedido", 1)) / J51))} -> 0.41786857 | L51: 14990 | M51: {=IF(OR(L51=0, L51=""), 0, 1 - ((((XLOOKUP($A51, 'datos de inventario'!$A:$A, 'datos de inventario'!$D:$D, 0) * 'datos de inventario'!$K$2) + (XLOOKUP($A51, 'datos de inventario'!$A:$A, 'datos de inventario'!$F:$F, 0) * 'datos de inventario'!$K$3 * 'datos de inventario'!$K$4)) * 1.19 + (L51 * 0.15) + XLOOKUP(MAX($Z51, (XLOOKUP($A51, 'datos de inventario'!$A:$A, 'datos de inventario'!$F:$F, 0) * 1000000 / 4000)) + 0.1, Tarifas!$A$2:$A$33, IF(L51 <= 9989, Tarifas!$B$2:$B$33, IF(L51 <= 19989, Tarifas!$C$2:$C$33, Tarifas!$D$2:$D$33)), "Peso excedido", 1)) / L51))} -> 0.36021261 | N51: BebésHigiene y Cuidado del BebéToallitas Húmedas | P51: 15.3 | Q51: =(P51/7)*30 -> 65.571429 | R51: 46.7 | S51: =(R51/7)*30 -> 200.14286 | T51: 45992 | U51: =1-(J51/H51) -> 0.10531859 | V51: =1-(L51/J51) -> 0.1177163 | AB51: =W51*X51*Y51/1000000 -> 0
A52: WIPESADULTO001 | H52: 2990 | I52: {=IF(OR(H52=0, H52=""), 0, 1 - ((((XLOOKUP($A52, 'datos de inventario'!$A:$A, 'datos de inventario'!$D:$D, 0) * 'datos de inventario'!$K$2) + (XLOOKUP($A52, 'datos de inventario'!$A:$A, 'datos de inventario'!$F:$F, 0) * 'datos de inventario'!$K$3 * 'datos de inventario'!$K$4)) * 1.19 + (H52 * 0.15) + XLOOKUP(MAX($Z52, (XLOOKUP($A52, 'datos de inventario'!$A:$A, 'datos de inventario'!$F:$F, 0) * 1000000 / 4000)) + 0.1, Tarifas!$A$2:$A$33, IF(H52 <= 9989, Tarifas!$B$2:$B$33, IF(H52 <= 19989, Tarifas!$C$2:$C$33, Tarifas!$D$2:$D$33)), "Peso excedido", 1)) / H52))} -> 0.58244147 | J52: 2490 | K52: {=IF(OR(J52=0, J52=""), 0, 1 - ((((XLOOKUP($A52, 'datos de inventario'!$A:$A, 'datos de inventario'!$D:$D, 0) * 'datos de inventario'!$K$2) + (XLOOKUP($A52, 'datos de inventario'!$A:$A, 'datos de inventario'!$F:$F, 0) * 'datos de inventario'!$K$3 * 'datos de inventario'!$K$4)) * 1.19 + (J52 * 0.15) + XLOOKUP(MAX($Z52, (XLOOKUP($A52, 'datos de inventario'!$A:$A, 'datos de inventario'!$F:$F, 0) * 1000000 / 4000)) + 0.1, Tarifas!$A$2:$A$33, IF(J52 <= 9989, Tarifas!$B$2:$B$33, IF(J52 <= 19989, Tarifas!$C$2:$C$33, Tarifas!$D$2:$D$33)), "Peso excedido", 1)) / J52))} -> 0.52871486 | L52: 1990 | M52: {=IF(OR(L52=0, L52=""), 0, 1 - ((((XLOOKUP($A52, 'datos de inventario'!$A:$A, 'datos de inventario'!$D:$D, 0) * 'datos de inventario'!$K$2) + (XLOOKUP($A52, 'datos de inventario'!$A:$A, 'datos de inventario'!$F:$F, 0) * 'datos de inventario'!$K$3 * 'datos de inventario'!$K$4)) * 1.19 + (L52 * 0.15) + XLOOKUP(MAX($Z52, (XLOOKUP($A52, 'datos de inventario'!$A:$A, 'datos de inventario'!$F:$F, 0) * 1000000 / 4000)) + 0.1, Tarifas!$A$2:$A$33, IF(L52 <= 9989, Tarifas!$B$2:$B$33, IF(L52 <= 19989, Tarifas!$C$2:$C$33, Tarifas!$D$2:$D$33)), "Peso excedido", 1)) / L52))} -> 0.44798995 | AB52: =W52*X52*Y52/1000000 -> 0
A53: WIPESBEBE001 | H53: 2490 | I53: {=IF(OR(H53=0, H53=""), 0, 1 - ((((XLOOKUP($A53, 'datos de inventario'!$A:$A, 'datos de inventario'!$D:$D, 0) * 'datos de inventario'!$K$2) + (XLOOKUP($A53, 'datos de inventario'!$A:$A, 'datos de inventario'!$F:$F, 0) * 'datos de inventario'!$K$3 * 'datos de inventario'!$K$4)) * 1.19 + (H53 * 0.15) + XLOOKUP(MAX($Z53, (XLOOKUP($A53, 'datos de inventario'!$A:$A, 'datos de inventario'!$F:$F, 0) * 1000000 / 4000)) + 0.1, Tarifas!$A$2:$A$33, IF(H53 <= 9989, Tarifas!$B$2:$B$33, IF(H53 <= 19989, Tarifas!$C$2:$C$33, Tarifas!$D$2:$D$33)), "Peso excedido", 1)) / H53))} -> 0.52871486 | J53: 1990 | K53: {=IF(OR(J53=0, J53=""), 0, 1 - ((((XLOOKUP($A53, 'datos de inventario'!$A:$A, 'datos de inventario'!$D:$D, 0) * 'datos de inventario'!$K$2) + (XLOOKUP($A53, 'datos de inventario'!$A:$A, 'datos de inventario'!$F:$F, 0) * 'datos de inventario'!$K$3 * 'datos de inventario'!$K$4)) * 1.19 + (J53 * 0.15) + XLOOKUP(MAX($Z53, (XLOOKUP($A53, 'datos de inventario'!$A:$A, 'datos de inventario'!$F:$F, 0) * 1000000 / 4000)) + 0.1, Tarifas!$A$2:$A$33, IF(J53 <= 9989, Tarifas!$B$2:$B$33, IF(J53 <= 19989, Tarifas!$C$2:$C$33, Tarifas!$D$2:$D$33)), "Peso excedido", 1)) / J53))} -> 0.44798995 | L53: 1490 | M53: {=IF(OR(L53=0, L53=""), 0, 1 - ((((XLOOKUP($A53, 'datos de inventario'!$A:$A, 'datos de inventario'!$D:$D, 0) * 'datos de inventario'!$K$2) + (XLOOKUP($A53, 'datos de inventario'!$A:$A, 'datos de inventario'!$F:$F, 0) * 'datos de inventario'!$K$3 * 'datos de inventario'!$K$4)) * 1.19 + (L53 * 0.15) + XLOOKUP(MAX($Z53, (XLOOKUP($A53, 'datos de inventario'!$A:$A, 'datos de inventario'!$F:$F, 0) * 1000000 / 4000)) + 0.1, Tarifas!$A$2:$A$33, IF(L53 <= 9989, Tarifas!$B$2:$B$33, IF(L53 <= 19989, Tarifas!$C$2:$C$33, Tarifas!$D$2:$D$33)), "Peso excedido", 1)) / L53))} -> 0.31308725 | AB53: =W53*X53*Y53/1000000 -> 0
A54: PAPELOPALITEXTUR002 | B54: Papel opalina texturizado A4 50 unidades 230 gramos | C54: Papel Opalina Texturizada A4 230 Gramos Homely 50 Hojas | D54: =LEN(C54) -> 55 | E54: Papel Opalina Texturizada A4 230 Gramos Homely 50 Hojas | F54: Papel Opalina Texturizada A4 230 Gramos Homely 50 Hojas | G54: =LEN(F54) -> 55 | H54: 8990 | I54: {=IF(OR(H54=0, H54=""), 0, 1 - ((((XLOOKUP($A54, 'datos de inventario'!$A:$A, 'datos de inventario'!$D:$D, 0) * 'datos de inventario'!$K$2) + (XLOOKUP($A54, 'datos de inventario'!$A:$A, 'datos de inventario'!$F:$F, 0) * 'datos de inventario'!$K$3 * 'datos de inventario'!$K$4)) * 1.19 + (H54 * 0.15) + XLOOKUP(MAX($Z54, (XLOOKUP($A54, 'datos de inventario'!$A:$A, 'datos de inventario'!$F:$F, 0) * 1000000 / 4000)) + 0.1, Tarifas!$A$2:$A$33, IF(H54 <= 9989, Tarifas!$B$2:$B$33, IF(H54 <= 19989, Tarifas!$C$2:$C$33, Tarifas!$D$2:$D$33)), "Peso excedido", 1)) / H54))} -> 0.50644577 | J54: 7990 | K54: {=IF(OR(J54=0, J54=""), 0, 1 - ((((XLOOKUP($A54, 'datos de inventario'!$A:$A, 'datos de inventario'!$D:$D, 0) * 'datos de inventario'!$K$2) + (XLOOKUP($A54, 'datos de inventario'!$A:$A, 'datos de inventario'!$F:$F, 0) * 'datos de inventario'!$K$3 * 'datos de inventario'!$K$4)) * 1.19 + (J54 * 0.15) + XLOOKUP(MAX($Z54, (XLOOKUP($A54, 'datos de inventario'!$A:$A, 'datos de inventario'!$F:$F, 0) * 1000000 / 4000)) + 0.1, Tarifas!$A$2:$A$33, IF(J54 <= 9989, Tarifas!$B$2:$B$33, IF(J54 <= 19989, Tarifas!$C$2:$C$33, Tarifas!$D$2:$D$33)), "Peso excedido", 1)) / J54))} -> 0.46344775 | L54: 6990 | M54: {=IF(OR(L54=0, L54=""), 0, 1 - ((((XLOOKUP($A54, 'datos de inventario'!$A:$A, 'datos de inventario'!$D:$D, 0) * 'datos de inventario'!$K$2) + (XLOOKUP($A54, 'datos de inventario'!$A:$A, 'datos de inventario'!$F:$F, 0) * 'datos de inventario'!$K$3 * 'datos de inventario'!$K$4)) * 1.19 + (L54 * 0.15) + XLOOKUP(MAX($Z54, (XLOOKUP($A54, 'datos de inventario'!$A:$A, 'datos de inventario'!$F:$F, 0) * 1000000 / 4000)) + 0.1, Tarifas!$A$2:$A$33, IF(L54 <= 9989, Tarifas!$B$2:$B$33, IF(L54 <= 19989, Tarifas!$C$2:$C$33, Tarifas!$D$2:$D$33)), "Peso excedido", 1)) / L54))} -> 0.408147 | N54: Arte, Librería y Cordonería/Librería/Comercial y oficina/Papeles de impresion | P54: 9.3 | Q54: =(P54/7)*30 -> 39.857143 | R54: 28 | S54: =(R54/7)*30 -> 120 | T54: 45992 | U54: =1-(J54/H54) -> 0.11123471 | V54: =1-(L54/J54) -> 0.12515645 | AB54: =W54*X54*Y54/1000000 -> 0
A55: PAPELHOLOGRAFICODIS001 | B55: Papel laminado en frío holográfico diseños adhesivo mix A4 18 hojas | C55: Papel Laminado Frio Holografico Adhesivo A4 Homely 18 Hojas | D55: =LEN(C55) -> 59 | E55: Papel Laminado En Frio Holografico Adhesivo A4 Homely 18 Hojas | F55: Papel Laminado En Frio Holografico Adhesivo A4 Homely 18 Hojas | G55: =LEN(F55) -> 62 | H55: 6990 | I55: {=IF(OR(H55=0, H55=""), 0, 1 - ((((XLOOKUP($A55, 'datos de inventario'!$A:$A, 'datos de inventario'!$D:$D, 0) * 'datos de inventario'!$K$2) + (XLOOKUP($A55, 'datos de inventario'!$A:$A, 'datos de inventario'!$F:$F, 0) * 'datos de inventario'!$K$3 * 'datos de inventario'!$K$4)) * 1.19 + (H55 * 0.15) + XLOOKUP(MAX($Z55, (XLOOKUP($A55, 'datos de inventario'!$A:$A, 'datos de inventario'!$F:$F, 0) * 1000000 / 4000)) + 0.1, Tarifas!$A$2:$A$33, IF(H55 <= 9989, Tarifas!$B$2:$B$33, IF(H55 <= 19989, Tarifas!$C$2:$C$33, Tarifas!$D$2:$D$33)), "Peso excedido", 1)) / H55))} -> 0.51414099 | J55: 5990 | K55: {=IF(OR(J55=0, J55=""), 0, 1 - ((((XLOOKUP($A55, 'datos de inventario'!$A:$A, 'datos de inventario'!$D:$D, 0) * 'datos de inventario'!$K$2) + (XLOOKUP($A55, 'datos de inventario'!$A:$A, 'datos de inventario'!$F:$F, 0) * 'datos de inventario'!$K$3 * 'datos de inventario'!$K$4)) * 1.19 + (J55 * 0.15) + XLOOKUP(MAX($Z55, (XLOOKUP($A55, 'datos de inventario'!$A:$A, 'datos de inventario'!$F:$F, 0) * 1000000 / 4000)) + 0.1, Tarifas!$A$2:$A$33, IF(J55 <= 9989, Tarifas!$B$2:$B$33, IF(J55 <= 19989, Tarifas!$C$2:$C$33, Tarifas!$D$2:$D$33)), "Peso excedido", 1)) / J55))} -> 0.45807104 | L55: 4990 | M55: {=IF(OR(L55=0, L55=""), 0, 1 - ((((XLOOKUP($A55, 'datos de inventario'!$A:$A, 'datos de inventario'!$D:$D, 0) * 'datos de inventario'!$K$2) + (XLOOKUP($A55, 'datos de inventario'!$A:$A, 'datos de inventario'!$F:$F, 0) * 'datos de inventario'!$K$3 * 'datos de inventario'!$K$4)) * 1.19 + (L55 * 0.15) + XLOOKUP(MAX($Z55, (XLOOKUP($A55, 'datos de inventario'!$A:$A, 'datos de inventario'!$F:$F, 0) * 1000000 / 4000)) + 0.1, Tarifas!$A$2:$A$33, IF(L55 <= 9989, Tarifas!$B$2:$B$33, IF(L55 <= 19989, Tarifas!$C$2:$C$33, Tarifas!$D$2:$D$33)), "Peso excedido", 1)) / L55))} -> 0.37952816 | N55: Arte, Librería y Cordonería/Librería/Comercial y oficina/Papeles de impresion | P55: 5.3 | Q55: =(P55/7)*30 -> 22.714286 | R55: 16 | S55: =(R55/7)*30 -> 68.571429 | T55: 45992 | U55: =1-(J55/H55) -> 0.14306152 | V55: =1-(L55/J55) -> 0.16694491 | AB55: =W55*X55*Y55/1000000 -> 0
A56: PAPELVINILOHOLO001 | B56: Papel vinilo adhesivo holográfico liso A4 20 hojas 210 g | C56: Papel Vinilo Adhesivo Holografico A4 20 Hojas Homely 210G | D56: =LEN(C56) -> 57 | E56: Papel Vinilo Adhesivo Holografico Liso A4 20 Hojas Homely Imprimible 210 Gramos Tornasol | F56: Papel Vinilo Adhesivo Holografico Liso A4 20 Hojas Homely 210 Gramos | G56: =LEN(F56) -> 68 | H56: 8990 | I56: {=IF(OR(H56=0, H56=""), 0, 1 - ((((XLOOKUP($A56, 'datos de inventario'!$A:$A, 'datos de inventario'!$D:$D, 0) * 'datos de inventario'!$K$2) + (XLOOKUP($A56, 'datos de inventario'!$A:$A, 'datos de inventario'!$F:$F, 0) * 'datos de inventario'!$K$3 * 'datos de inventario'!$K$4)) * 1.19 + (H56 * 0.15) + XLOOKUP(MAX($Z56, (XLOOKUP($A56, 'datos de inventario'!$A:$A, 'datos de inventario'!$F:$F, 0) * 1000000 / 4000)) + 0.1, Tarifas!$A$2:$A$33, IF(H56 <= 9989, Tarifas!$B$2:$B$33, IF(H56 <= 19989, Tarifas!$C$2:$C$33, Tarifas!$D$2:$D$33)), "Peso excedido", 1)) / H56))} -> 0.50621126 | J56: 7990 | K56: {=IF(OR(J56=0, J56=""), 0, 1 - ((((XLOOKUP($A56, 'datos de inventario'!$A:$A, 'datos de inventario'!$D:$D, 0) * 'datos de inventario'!$K$2) + (XLOOKUP($A56, 'datos de inventario'!$A:$A, 'datos de inventario'!$F:$F, 0) * 'datos de inventario'!$K$3 * 'datos de inventario'!$K$4)) * 1.19 + (J56 * 0.15) + XLOOKUP(MAX($Z56, (XLOOKUP($A56, 'datos de inventario'!$A:$A, 'datos de inventario'!$F:$F, 0) * 1000000 / 4000)) + 0.1, Tarifas!$A$2:$A$33, IF(J56 <= 9989, Tarifas!$B$2:$B$33, IF(J56 <= 19989, Tarifas!$C$2:$C$33, Tarifas!$D$2:$D$33)), "Peso excedido", 1)) / J56))} -> 0.46318389 | L56: 6990 | M56: {=IF(OR(L56=0, L56=""), 0, 1 - ((((XLOOKUP($A56, 'datos de inventario'!$A:$A, 'datos de inventario'!$D:$D, 0) * 'datos de inventario'!$K$2) + (XLOOKUP($A56, 'datos de inventario'!$A:$A, 'datos de inventario'!$F:$F, 0) * 'datos de inventario'!$K$3 * 'datos de inventario'!$K$4)) * 1.19 + (L56 * 0.15) + XLOOKUP(MAX($Z56, (XLOOKUP($A56, 'datos de inventario'!$A:$A, 'datos de inventario'!$F:$F, 0) * 1000000 / 4000)) + 0.1, Tarifas!$A$2:$A$33, IF(L56 <= 9989, Tarifas!$B$2:$B$33, IF(L56 <= 19989, Tarifas!$C$2:$C$33, Tarifas!$D$2:$D$33)), "Peso excedido", 1)) / L56))} -> 0.40784539 | N56: Cámaras y Accesorios/Accesorios para Cámaras/Rollos/Para Cámaras Instantáneas | P56: 9.3 | Q56: =(P56/7)*30 -> 39.857143 | R56: 28 | S56: =(R56/7)*30 -> 120 | T56: 45992 | U56: =1-(J56/H56) -> 0.11123471 | V56: =1-(L56/J56) -> 0.12515645 | AB56: =W56*X56*Y56/1000000 -> 0
A57: PAPELVINILOTRANSPARENT001 | B57: Papel vinilo adhesivo transparente A4 20 hojas 90 g | C57: Papel Vinilo Adhesivo Transparente A4 20 Hojas Homely 90G | D57: =LEN(C57) -> 57 | E57: Papel Vinilo Adhesivo Transparente A4 20 Hojas Homely Imprimible Inkjet 90 Gramos | F57: Papel Vinilo Adhesivo Transparente A4 20 Hojas Homely Inkjet 90 Gramos | G57: =LEN(F57) -> 70 | H57: 8990 | I57: {=IF(OR(H57=0, H57=""), 0, 1 - ((((XLOOKUP($A57, 'datos de inventario'!$A:$A, 'datos de inventario'!$D:$D, 0) * 'datos de inventario'!$K$2) + (XLOOKUP($A57, 'datos de inventario'!$A:$A, 'datos de inventario'!$F:$F, 0) * 'datos de inventario'!$K$3 * 'datos de inventario'!$K$4)) * 1.19 + (H57 * 0.15) + XLOOKUP(MAX($Z57, (XLOOKUP($A57, 'datos de inventario'!$A:$A, 'datos de inventario'!$F:$F, 0) * 1000000 / 4000)) + 0.1, Tarifas!$A$2:$A$33, IF(H57 <= 9989, Tarifas!$B$2:$B$33, IF(H57 <= 19989, Tarifas!$C$2:$C$33, Tarifas!$D$2:$D$33)), "Peso excedido", 1)) / H57))} -> 0.52825075 | J57: 7990 | K57: {=IF(OR(J57=0, J57=""), 0, 1 - ((((XLOOKUP($A57, 'datos de inventario'!$A:$A, 'datos de inventario'!$D:$D, 0) * 'datos de inventario'!$K$2) + (XLOOKUP($A57, 'datos de inventario'!$A:$A, 'datos de inventario'!$F:$F, 0) * 'datos de inventario'!$K$3 * 'datos de inventario'!$K$4)) * 1.19 + (J57 * 0.15) + XLOOKUP(MAX($Z57, (XLOOKUP($A57, 'datos de inventario'!$A:$A, 'datos de inventario'!$F:$F, 0) * 1000000 / 4000)) + 0.1, Tarifas!$A$2:$A$33, IF(J57 <= 9989, Tarifas!$B$2:$B$33, IF(J57 <= 19989, Tarifas!$C$2:$C$33, Tarifas!$D$2:$D$33)), "Peso excedido", 1)) / J57))} -> 0.48798176 | L57: 6990 | M57: {=IF(OR(L57=0, L57=""), 0, 1 - ((((XLOOKUP($A57, 'datos de inventario'!$A:$A, 'datos de inventario'!$D:$D, 0) * 'datos de inventario'!$K$2) + (XLOOKUP($A57, 'datos de inventario'!$A:$A, 'datos de inventario'!$F:$F, 0) * 'datos de inventario'!$K$3 * 'datos de inventario'!$K$4)) * 1.19 + (L57 * 0.15) + XLOOKUP(MAX($Z57, (XLOOKUP($A57, 'datos de inventario'!$A:$A, 'datos de inventario'!$F:$F, 0) * 1000000 / 4000)) + 0.1, Tarifas!$A$2:$A$33, IF(L57 <= 9989, Tarifas!$B$2:$B$33, IF(L57 <= 19989, Tarifas!$C$2:$C$33, Tarifas!$D$2:$D$33)), "Peso excedido", 1)) / L57))} -> 0.43619088 | N57: Cámaras y Accesorios/Accesorios para Cámaras/Rollos/Para Cámaras Instantáneas | P57: 9.4 | Q57: =(P57/7)*30 -> 40.285714 | R57: 28 | S57: =(R57/7)*30 -> 120 | T57: 45992 | U57: =1-(J57/H57) -> 0.11123471 | V57: =1-(L57/J57) -> 0.12515645 | AB57: =W57*X57*Y57/1000000 -> 0
A58: PAPFOT005 | B58: Papel fotográfico doble faz brillante A4 100 hojas 180 g | C58: Papel Fotografico Doble Faz Glossy A4 180G Homely 100 Hojas | D58: =LEN(C58) -> 59 | E58: Papel Fotografico Doble Faz Glossy A4 100 Hojas Homely Imprimible 180 Gramos | F58: Papel Fotografico Doble Faz Glossy A4 100 Hojas Homely 180 Gramos | G58: =LEN(F58) -> 65 | H58: 8990 | I58: {=IF(OR(H58=0, H58=""), 0, 1 - ((((XLOOKUP($A58, 'datos de inventario'!$A:$A, 'datos de inventario'!$D:$D, 0) * 'datos de inventario'!$K$2) + (XLOOKUP($A58, 'datos de inventario'!$A:$A, 'datos de inventario'!$F:$F, 0) * 'datos de inventario'!$K$3 * 'datos de inventario'!$K$4)) * 1.19 + (H58 * 0.15) + XLOOKUP(MAX($Z58, (XLOOKUP($A58, 'datos de inventario'!$A:$A, 'datos de inventario'!$F:$F, 0) * 1000000 / 4000)) + 0.1, Tarifas!$A$2:$A$33, IF(H58 <= 9989, Tarifas!$B$2:$B$33, IF(H58 <= 19989, Tarifas!$C$2:$C$33, Tarifas!$D$2:$D$33)), "Peso excedido", 1)) / H58))} -> 0.40519694 | J58: 7990 | K58: {=IF(OR(J58=0, J58=""), 0, 1 - ((((XLOOKUP($A58, 'datos de inventario'!$A:$A, 'datos de inventario'!$D:$D, 0) * 'datos de inventario'!$K$2) + (XLOOKUP($A58, 'datos de inventario'!$A:$A, 'datos de inventario'!$F:$F, 0) * 'datos de inventario'!$K$3 * 'datos de inventario'!$K$4)) * 1.19 + (J58 * 0.15) + XLOOKUP(MAX($Z58, (XLOOKUP($A58, 'datos de inventario'!$A:$A, 'datos de inventario'!$F:$F, 0) * 1000000 / 4000)) + 0.1, Tarifas!$A$2:$A$33, IF(J58 <= 9989, Tarifas!$B$2:$B$33, IF(J58 <= 19989, Tarifas!$C$2:$C$33, Tarifas!$D$2:$D$33)), "Peso excedido", 1)) / J58))} -> 0.34952697 | L58: 6990 | M58: {=IF(OR(L58=0, L58=""), 0, 1 - ((((XLOOKUP($A58, 'datos de inventario'!$A:$A, 'datos de inventario'!$D:$D, 0) * 'datos de inventario'!$K$2) + (XLOOKUP($A58, 'datos de inventario'!$A:$A, 'datos de inventario'!$F:$F, 0) * 'datos de inventario'!$K$3 * 'datos de inventario'!$K$4)) * 1.19 + (L58 * 0.15) + XLOOKUP(MAX($Z58, (XLOOKUP($A58, 'datos de inventario'!$A:$A, 'datos de inventario'!$F:$F, 0) * 1000000 / 4000)) + 0.1, Tarifas!$A$2:$A$33, IF(L58 <= 9989, Tarifas!$B$2:$B$33, IF(L58 <= 19989, Tarifas!$C$2:$C$33, Tarifas!$D$2:$D$33)), "Peso excedido", 1)) / L58))} -> 0.27792854 | N58: Cámaras y Accesorios/Accesorios para Cámaras/Rollos/Para Cámaras Instantáneas | P58: 9.5 | Q58: =(P58/7)*30 -> 40.714286 | R58: 28 | S58: =(R58/7)*30 -> 120 | T58: 45992 | U58: =1-(J58/H58) -> 0.11123471 | V58: =1-(L58/J58) -> 0.12515645 | AB58: =W58*X58*Y58/1000000 -> 0
A59: PAPFOT006 | B59: Papel fotográfico doble faz brillante A4 100 hojas 220 g | C59: Papel Fotografico Doble Faz Glossy A4 220G Homely 100 Hojas | D59: =LEN(C59) -> 59 | E59: Papel Fotografico Doble Faz Glossy A4 100 Hojas Homely Imprimible 220 Gramos | F59: Papel Fotografico Doble Faz Glossy A4 100 Hojas Homely 220 Gramos | G59: =LEN(F59) -> 65 | H59: 9990 | I59: {=IF(OR(H59=0, H59=""), 0, 1 - ((((XLOOKUP($A59, 'datos de inventario'!$A:$A, 'datos de inventario'!$D:$D, 0) * 'datos de inventario'!$K$2) + (XLOOKUP($A59, 'datos de inventario'!$A:$A, 'datos de inventario'!$F:$F, 0) * 'datos de inventario'!$K$3 * 'datos de inventario'!$K$4)) * 1.19 + (H59 * 0.15) + XLOOKUP(MAX($Z59, (XLOOKUP($A59, 'datos de inventario'!$A:$A, 'datos de inventario'!$F:$F, 0) * 1000000 / 4000)) + 0.1, Tarifas!$A$2:$A$33, IF(H59 <= 9989, Tarifas!$B$2:$B$33, IF(H59 <= 19989, Tarifas!$C$2:$C$33, Tarifas!$D$2:$D$33)), "Peso excedido", 1)) / H59))} -> 0.37470068 | J59: 8990 | K59: {=IF(OR(J59=0, J59=""), 0, 1 - ((((XLOOKUP($A59, 'datos de inventario'!$A:$A, 'datos de inventario'!$D:$D, 0) * 'datos de inventario'!$K$2) + (XLOOKUP($A59, 'datos de inventario'!$A:$A, 'datos de inventario'!$F:$F, 0) * 'datos de inventario'!$K$3 * 'datos de inventario'!$K$4)) * 1.19 + (J59 * 0.15) + XLOOKUP(MAX($Z59, (XLOOKUP($A59, 'datos de inventario'!$A:$A, 'datos de inventario'!$F:$F, 0) * 1000000 / 4000)) + 0.1, Tarifas!$A$2:$A$33, IF(J59 <= 9989, Tarifas!$B$2:$B$33, IF(J59 <= 19989, Tarifas!$C$2:$C$33, Tarifas!$D$2:$D$33)), "Peso excedido", 1)) / J59))} -> 0.34519018 | L59: 7990 | M59: {=IF(OR(L59=0, L59=""), 0, 1 - ((((XLOOKUP($A59, 'datos de inventario'!$A:$A, 'datos de inventario'!$D:$D, 0) * 'datos de inventario'!$K$2) + (XLOOKUP($A59, 'datos de inventario'!$A:$A, 'datos de inventario'!$F:$F, 0) * 'datos de inventario'!$K$3 * 'datos de inventario'!$K$4)) * 1.19 + (L59 * 0.15) + XLOOKUP(MAX($Z59, (XLOOKUP($A59, 'datos de inventario'!$A:$A, 'datos de inventario'!$F:$F, 0) * 1000000 / 4000)) + 0.1, Tarifas!$A$2:$A$33, IF(L59 <= 9989, Tarifas!$B$2:$B$33, IF(L59 <= 19989, Tarifas!$C$2:$C$33, Tarifas!$D$2:$D$33)), "Peso excedido", 1)) / L59))} -> 0.28200998 | N59: Cámaras y Accesorios/Accesorios para Cámaras/Rollos/Para Cámaras Instantáneas | P59: 9.6 | Q59: =(P59/7)*30 -> 41.142857 | R59: 28 | S59: =(R59/7)*30 -> 120 | T59: 45992 | U59: =1-(J59/H59) -> 0.1001001 | V59: =1-(L59/J59) -> 0.11123471 | AB59: =W59*X59*Y59/1000000 -> 0
A60: PAPFOT4R001 | B60: Papel fotográfico glossy 4R 100 hojas 230 g | C60: Papel Fotografico Glossy 4R 230 Gramos Homely 100 Hojas | D60: =LEN(C60) -> 55 | E60: Papel Fotografico Glossy 4R 10x15 Cm 230 Gramos Homely 100 Hojas Blanco | F60: Papel Fotografico Glossy 4R 10x15 Cm 230 Gramos Homely 100 Hojas | G60: =LEN(F60) -> 65 | H60: 4990 | I60: {=IF(OR(H60=0, H60=""), 0, 1 - ((((XLOOKUP($A60, 'datos de inventario'!$A:$A, 'datos de inventario'!$D:$D, 0) * 'datos de inventario'!$K$2) + (XLOOKUP($A60, 'datos de inventario'!$A:$A, 'datos de inventario'!$F:$F, 0) * 'datos de inventario'!$K$3 * 'datos de inventario'!$K$4)) * 1.19 + (H60 * 0.15) + XLOOKUP(MAX($Z60, (XLOOKUP($A60, 'datos de inventario'!$A:$A, 'datos de inventario'!$F:$F, 0) * 1000000 / 4000)) + 0.1, Tarifas!$A$2:$A$33, IF(H60 <= 9989, Tarifas!$B$2:$B$33, IF(H60 <= 19989, Tarifas!$C$2:$C$33, Tarifas!$D$2:$D$33)), "Peso excedido", 1)) / H60))} -> 0.51497114 | J60: 3990 | K60: {=IF(OR(J60=0, J60=""), 0, 1 - ((((XLOOKUP($A60, 'datos de inventario'!$A:$A, 'datos de inventario'!$D:$D, 0) * 'datos de inventario'!$K$2) + (XLOOKUP($A60, 'datos de inventario'!$A:$A, 'datos de inventario'!$F:$F, 0) * 'datos de inventario'!$K$3 * 'datos de inventario'!$K$4)) * 1.19 + (J60 * 0.15) + XLOOKUP(MAX($Z60, (XLOOKUP($A60, 'datos de inventario'!$A:$A, 'datos de inventario'!$F:$F, 0) * 1000000 / 4000)) + 0.1, Tarifas!$A$2:$A$33, IF(J60 <= 9989, Tarifas!$B$2:$B$33, IF(J60 <= 19989, Tarifas!$C$2:$C$33, Tarifas!$D$2:$D$33)), "Peso excedido", 1)) / J60))} -> 0.43100401 | L60: 2990 | M60: {=IF(OR(L60=0, L60=""), 0, 1 - ((((XLOOKUP($A60, 'datos de inventario'!$A:$A, 'datos de inventario'!$D:$D, 0) * 'datos de inventario'!$K$2) + (XLOOKUP($A60, 'datos de inventario'!$A:$A, 'datos de inventario'!$F:$F, 0) * 'datos de inventario'!$K$3 * 'datos de inventario'!$K$4)) * 1.19 + (L60 * 0.15) + XLOOKUP(MAX($Z60, (XLOOKUP($A60, 'datos de inventario'!$A:$A, 'datos de inventario'!$F:$F, 0) * 1000000 / 4000)) + 0.1, Tarifas!$A$2:$A$33, IF(L60 <= 9989, Tarifas!$B$2:$B$33, IF(L60 <= 19989, Tarifas!$C$2:$C$33, Tarifas!$D$2:$D$33)), "Peso excedido", 1)) / L60))} -> 0.29087157 | N60: Cámaras y Accesorios/Accesorios para Cámaras/Rollos/Para Cámaras Instantáneas | P60: 7.7 | Q60: =(P60/7)*30 -> 33 | R60: 23 | S60: =(R60/7)*30 -> 98.571429 | T60: 45992 | U60: =1-(J60/H60) -> 0.2004008 | V60: =1-(L60/J60) -> 0.25062657 | AB60: =W60*X60*Y60/1000000 -> 0
A61: PAPELLAMINADOFRIO001 | B61: Papel laminado en frío adhesivo transparente A4 50 hojas | C61: Papel Laminado Frio Adhesivo Transparente A4 Homely 50 Hojas | D61: =LEN(C61) -> 60 | E61: Papel Laminado En Frio Adhesivo Transparente A4 Homely 50 Hojas | F61: Papel Laminado En Frio Adhesivo Transparente A4 Homely 50 Hojas | G61: =LEN(F61) -> 63 | H61: 9990 | I61: {=IF(OR(H61=0, H61=""), 0, 1 - ((((XLOOKUP($A61, 'datos de inventario'!$A:$A, 'datos de inventario'!$D:$D, 0) * 'datos de inventario'!$K$2) + (XLOOKUP($A61, 'datos de inventario'!$A:$A, 'datos de inventario'!$F:$F, 0) * 'datos de inventario'!$K$3 * 'datos de inventario'!$K$4)) * 1.19 + (H61 * 0.15) + XLOOKUP(MAX($Z61, (XLOOKUP($A61, 'datos de inventario'!$A:$A, 'datos de inventario'!$F:$F, 0) * 1000000 / 4000)) + 0.1, Tarifas!$A$2:$A$33, IF(H61 <= 9989, Tarifas!$B$2:$B$33, IF(H61 <= 19989, Tarifas!$C$2:$C$33, Tarifas!$D$2:$D$33)), "Peso excedido", 1)) / H61))} -> 0.40656286 | J61: 8990 | K61: {=IF(OR(J61=0, J61=""), 0, 1 - ((((XLOOKUP($A61, 'datos de inventario'!$A:$A, 'datos de inventario'!$D:$D, 0) * 'datos de inventario'!$K$2) + (XLOOKUP($A61, 'datos de inventario'!$A:$A, 'datos de inventario'!$F:$F, 0) * 'datos de inventario'!$K$3 * 'datos de inventario'!$K$4)) * 1.19 + (J61 * 0.15) + XLOOKUP(MAX($Z61, (XLOOKUP($A61, 'datos de inventario'!$A:$A, 'datos de inventario'!$F:$F, 0) * 1000000 / 4000)) + 0.1, Tarifas!$A$2:$A$33, IF(J61 <= 9989, Tarifas!$B$2:$B$33, IF(J61 <= 19989, Tarifas!$C$2:$C$33, Tarifas!$D$2:$D$33)), "Peso excedido", 1)) / J61))} -> 0.3794842 | L61: 7990 | M61: {=IF(OR(L61=0, L61=""), 0, 1 - ((((XLOOKUP($A61, 'datos de inventario'!$A:$A, 'datos de inventario'!$D:$D, 0) * 'datos de inventario'!$K$2) + (XLOOKUP($A61, 'datos de inventario'!$A:$A, 'datos de inventario'!$F:$F, 0) * 'datos de inventario'!$K$3 * 'datos de inventario'!$K$4)) * 1.19 + (L61 * 0.15) + XLOOKUP(MAX($Z61, (XLOOKUP($A61, 'datos de inventario'!$A:$A, 'datos de inventario'!$F:$F, 0) * 1000000 / 4000)) + 0.1, Tarifas!$A$2:$A$33, IF(L61 <= 9989, Tarifas!$B$2:$B$33, IF(L61 <= 19989, Tarifas!$C$2:$C$33, Tarifas!$D$2:$D$33)), "Peso excedido", 1)) / L61))} -> 0.32059612 | N61: Arte, Librería y Cordonería/Librería/Otros | P61: 10 | Q61: =(P61/7)*30 -> 42.857143 | R61: 30 | S61: =(R61/7)*30 -> 128.57143 | T61: 45992 | U61: =1-(J61/H61) -> 0.1001001 | V61: =1-(L61/J61) -> 0.11123471 | AB61: =W61*X61*Y61/1000000 -> 0
A62: PAPELMATTE001 | B62: Papel adhesivo matte A4 50 hojas 135 g | C62: Papel Fotografico Adhesivo Matte A4 135G Homely 50 Hojas | D62: =LEN(C62) -> 56 | E62: Papel Fotografico Adhesivo Matte A4 135 Gramos Homely 50 Hojas Blanco | F62: Papel Fotografico Adhesivo Matte A4 135 Gramos Homely 50 Hojas blanco | G62: =LEN(F62) -> 69 | H62: 6990 | I62: {=IF(OR(H62=0, H62=""), 0, 1 - ((((XLOOKUP($A62, 'datos de inventario'!$A:$A, 'datos de inventario'!$D:$D, 0) * 'datos de inventario'!$K$2) + (XLOOKUP($A62, 'datos de inventario'!$A:$A, 'datos de inventario'!$F:$F, 0) * 'datos de inventario'!$K$3 * 'datos de inventario'!$K$4)) * 1.19 + (H62 * 0.15) + XLOOKUP(MAX($Z62, (XLOOKUP($A62, 'datos de inventario'!$A:$A, 'datos de inventario'!$F:$F, 0) * 1000000 / 4000)) + 0.1, Tarifas!$A$2:$A$33, IF(H62 <= 9989, Tarifas!$B$2:$B$33, IF(H62 <= 19989, Tarifas!$C$2:$C$33, Tarifas!$D$2:$D$33)), "Peso excedido", 1)) / H62))} -> 0.47223931 | J62: 5990 | K62: {=IF(OR(J62=0, J62=""), 0, 1 - ((((XLOOKUP($A62, 'datos de inventario'!$A:$A, 'datos de inventario'!$D:$D, 0) * 'datos de inventario'!$K$2) + (XLOOKUP($A62, 'datos de inventario'!$A:$A, 'datos de inventario'!$F:$F, 0) * 'datos de inventario'!$K$3 * 'datos de inventario'!$K$4)) * 1.19 + (J62 * 0.15) + XLOOKUP(MAX($Z62, (XLOOKUP($A62, 'datos de inventario'!$A:$A, 'datos de inventario'!$F:$F, 0) * 1000000 / 4000)) + 0.1, Tarifas!$A$2:$A$33, IF(J62 <= 9989, Tarifas!$B$2:$B$33, IF(J62 <= 19989, Tarifas!$C$2:$C$33, Tarifas!$D$2:$D$33)), "Peso excedido", 1)) / J62))} -> 0.40917408 | L62: 4990 | M62: {=IF(OR(L62=0, L62=""), 0, 1 - ((((XLOOKUP($A62, 'datos de inventario'!$A:$A, 'datos de inventario'!$D:$D, 0) * 'datos de inventario'!$K$2) + (XLOOKUP($A62, 'datos de inventario'!$A:$A, 'datos de inventario'!$F:$F, 0) * 'datos de inventario'!$K$3 * 'datos de inventario'!$K$4)) * 1.19 + (L62 * 0.15) + XLOOKUP(MAX($Z62, (XLOOKUP($A62, 'datos de inventario'!$A:$A, 'datos de inventario'!$F:$F, 0) * 1000000 / 4000)) + 0.1, Tarifas!$A$2:$A$33, IF(L62 <= 9989, Tarifas!$B$2:$B$33, IF(L62 <= 19989, Tarifas!$C$2:$C$33, Tarifas!$D$2:$D$33)), "Peso excedido", 1)) / L62))} -> 0.32083221 | N62: Arte, Librería y Cordonería/Librería/Comercial y oficina/Papeles de impresion | P62: 9.6 | Q62: =(P62/7)*30 -> 41.142857 | R62: 28 | S62: =(R62/7)*30 -> 120 | T62: 45992 | U62: =1-(J62/H62) -> 0.14306152 | V62: =1-(L62/J62) -> 0.16694491 | AB62: =W62*X62*Y62/1000000 -> 0
A63: CAFETERAPREN002 | B63: Cafetera prensa francesa 600Ml + dosificador | C63: Cafetera Francesa 600Ml Atelier Prensa Vidrio Acero Portatil | D63: =LEN(C63) -> 60 | E63: Cafetera Francesa 600ml Atelier Prensa Vidrio Acero Inoxidable Portatil Con Dosificador | F63: Cafetera Francesa 600ml Atelier Prensa Vidrio Portatil Con Dosificador | G63: =LEN(F63) -> 70 | H63: 14990 | I63: {=IF(OR(H63=0, H63=""), 0, 1 - ((((XLOOKUP($A63, 'datos de inventario'!$A:$A, 'datos de inventario'!$D:$D, 0) * 'datos de inventario'!$K$2) + (XLOOKUP($A63, 'datos de inventario'!$A:$A, 'datos de inventario'!$F:$F, 0) * 'datos de inventario'!$K$3 * 'datos de inventario'!$K$4)) * 1.19 + (H63 * 0.15) + XLOOKUP(MAX($Z63, (XLOOKUP($A63, 'datos de inventario'!$A:$A, 'datos de inventario'!$F:$F, 0) * 1000000 / 4000)) + 0.1, Tarifas!$A$2:$A$33, IF(H63 <= 9989, Tarifas!$B$2:$B$33, IF(H63 <= 19989, Tarifas!$C$2:$C$33, Tarifas!$D$2:$D$33)), "Peso excedido", 1)) / H63))} -> 0.4106561 | J63: 13990 | K63: {=IF(OR(J63=0, J63=""), 0, 1 - ((((XLOOKUP($A63, 'datos de inventario'!$A:$A, 'datos de inventario'!$D:$D, 0) * 'datos de inventario'!$K$2) + (XLOOKUP($A63, 'datos de inventario'!$A:$A, 'datos de inventario'!$F:$F, 0) * 'datos de inventario'!$K$3 * 'datos de inventario'!$K$4)) * 1.19 + (J63 * 0.15) + XLOOKUP(MAX($Z63, (XLOOKUP($A63, 'datos de inventario'!$A:$A, 'datos de inventario'!$F:$F, 0) * 1000000 / 4000)) + 0.1, Tarifas!$A$2:$A$33, IF(J63 <= 9989, Tarifas!$B$2:$B$33, IF(J63 <= 19989, Tarifas!$C$2:$C$33, Tarifas!$D$2:$D$33)), "Peso excedido", 1)) / J63))} -> 0.37925197 | L63: 12990 | M63: {=IF(OR(L63=0, L63=""), 0, 1 - ((((XLOOKUP($A63, 'datos de inventario'!$A:$A, 'datos de inventario'!$D:$D, 0) * 'datos de inventario'!$K$2) + (XLOOKUP($A63, 'datos de inventario'!$A:$A, 'datos de inventario'!$F:$F, 0) * 'datos de inventario'!$K$3 * 'datos de inventario'!$K$4)) * 1.19 + (L63 * 0.15) + XLOOKUP(MAX($Z63, (XLOOKUP($A63, 'datos de inventario'!$A:$A, 'datos de inventario'!$F:$F, 0) * 1000000 / 4000)) + 0.1, Tarifas!$A$2:$A$33, IF(L63 <= 9989, Tarifas!$B$2:$B$33, IF(L63 <= 19989, Tarifas!$C$2:$C$33, Tarifas!$D$2:$D$33)), "Peso excedido", 1)) / L63))} -> 0.3430127 | N63: ElectrodomésticosPequeños ElectrodomésticosPara CocinaCafeteras | P63: 6.5 | Q63: =(P63/7)*30 -> 27.857143 | R63: 18 | S63: =(R63/7)*30 -> 77.142857 | T63: 46023 | U63: =1-(J63/H63) -> 0.066711141 | V63: =1-(L63/J63) -> 0.071479628 | AB63: =W63*X63*Y63/1000000 -> 0
A64: MANHEX25KG | B64: Mancuerna Hexagonal 2,5Kg Acero y Caucho Overfit | C64: Mancuerna Hexagonal 2.5kg Acero Y Caucho Overfit Negro | D64: =LEN(C64) -> 54 | E64: Mancuerna Hexagonal 2.5kg Acero Y Caucho Overfit Negro Pesas | F64: Mancuerna Hexagonal 2.5kg Acero Y Caucho Overfit Negro Pesas | G64: =LEN(F64) -> 61 | H64: 11990 | I64: {=IF(OR(H64=0, H64=""), 0, 1 - ((((XLOOKUP($A64, 'datos de inventario'!$A:$A, 'datos de inventario'!$D:$D, 0) * 'datos de inventario'!$K$2) + (XLOOKUP($A64, 'datos de inventario'!$A:$A, 'datos de inventario'!$F:$F, 0) * 'datos de inventario'!$K$3 * 'datos de inventario'!$K$4)) * 1.19 + (H64 * 0.15) + XLOOKUP(MAX($Z64, (XLOOKUP($A64, 'datos de inventario'!$A:$A, 'datos de inventario'!$F:$F, 0) * 1000000 / 4000)) + 0.1, Tarifas!$A$2:$A$33, IF(H64 <= 9989, Tarifas!$B$2:$B$33, IF(H64 <= 19989, Tarifas!$C$2:$C$33, Tarifas!$D$2:$D$33)), "Peso excedido", 1)) / H64))} -> 0.49886072 | J64: 9990 | K64: {=IF(OR(J64=0, J64=""), 0, 1 - ((((XLOOKUP($A64, 'datos de inventario'!$A:$A, 'datos de inventario'!$D:$D, 0) * 'datos de inventario'!$K$2) + (XLOOKUP($A64, 'datos de inventario'!$A:$A, 'datos de inventario'!$F:$F, 0) * 'datos de inventario'!$K$3 * 'datos de inventario'!$K$4)) * 1.19 + (J64 * 0.15) + XLOOKUP(MAX($Z64, (XLOOKUP($A64, 'datos de inventario'!$A:$A, 'datos de inventario'!$F:$F, 0) * 1000000 / 4000)) + 0.1, Tarifas!$A$2:$A$33, IF(J64 <= 9989, Tarifas!$B$2:$B$33, IF(J64 <= 19989, Tarifas!$C$2:$C$33, Tarifas!$D$2:$D$33)), "Peso excedido", 1)) / J64))} -> 0.42856256 | L64: 8990 | M64: {=IF(OR(L64=0, L64=""), 0, 1 - ((((XLOOKUP($A64, 'datos de inventario'!$A:$A, 'datos de inventario'!$D:$D, 0) * 'datos de inventario'!$K$2) + (XLOOKUP($A64, 'datos de inventario'!$A:$A, 'datos de inventario'!$F:$F, 0) * 'datos de inventario'!$K$3 * 'datos de inventario'!$K$4)) * 1.19 + (L64 * 0.15) + XLOOKUP(MAX($Z64, (XLOOKUP($A64, 'datos de inventario'!$A:$A, 'datos de inventario'!$F:$F, 0) * 1000000 / 4000)) + 0.1, Tarifas!$A$2:$A$33, IF(L64 <= 9989, Tarifas!$B$2:$B$33, IF(L64 <= 19989, Tarifas!$C$2:$C$33, Tarifas!$D$2:$D$33)), "Peso excedido", 1)) / L64))} -> 0.40504338 | N64: Deportes y FitnessFitness y MusculaciónPesas, Discos y BarrasMancuernas | P64: 6.5 | Q64: =(P64/7)*30 -> 27.857143 | R64: 18 | S64: =(R64/7)*30 -> 77.142857 | T64: 46023 | U64: =1-(J64/H64) -> 0.16680567 | V64: =1-(L64/J64) -> 0.1001001 | AB64: =W64*X64*Y64/1000000 -> 0
A65: TOPPERKING001 | B65: Cubre colchón topper acolchado tamaño king | C65: Topper Cubre Colchon King Homely Acolchado Premium Blanco | D65: =LEN(C65) -> 58 | E65: Topper Cubre Colchon King Homely Acolchado Hipoalergenico Eslastico Premium Blanco Protector Viscoelastico | F65: Topper Cubre Colchon King Homely Acolchado Premium Blanco Protector | G65: =LEN(F65) -> 67 | H65: 62990 | I65: {=IF(OR(H65=0, H65=""), 0, 1 - ((((XLOOKUP($A65, 'datos de inventario'!$A:$A, 'datos de inventario'!$D:$D, 0) * 'datos de inventario'!$K$2) + (XLOOKUP($A65, 'datos de inventario'!$A:$A, 'datos de inventario'!$F:$F, 0) * 'datos de inventario'!$K$3 * 'datos de inventario'!$K$4)) * 1.19 + (H65 * 0.15) + XLOOKUP(MAX($Z65, (XLOOKUP($A65, 'datos de inventario'!$A:$A, 'datos de inventario'!$F:$F, 0) * 1000000 / 4000)) + 0.1, Tarifas!$A$2:$A$33, IF(H65 <= 9989, Tarifas!$B$2:$B$33, IF(H65 <= 19989, Tarifas!$C$2:$C$33, Tarifas!$D$2:$D$33)), "Peso excedido", 1)) / H65))} -> 0.36592523 | J65: 59990 | K65: {=IF(OR(J65=0, J65=""), 0, 1 - ((((XLOOKUP($A65, 'datos de inventario'!$A:$A, 'datos de inventario'!$D:$D, 0) * 'datos de inventario'!$K$2) + (XLOOKUP($A65, 'datos de inventario'!$A:$A, 'datos de inventario'!$F:$F, 0) * 'datos de inventario'!$K$3 * 'datos de inventario'!$K$4)) * 1.19 + (J65 * 0.15) + XLOOKUP(MAX($Z65, (XLOOKUP($A65, 'datos de inventario'!$A:$A, 'datos de inventario'!$F:$F, 0) * 1000000 / 4000)) + 0.1, Tarifas!$A$2:$A$33, IF(J65 <= 9989, Tarifas!$B$2:$B$33, IF(J65 <= 19989, Tarifas!$C$2:$C$33, Tarifas!$D$2:$D$33)), "Peso excedido", 1)) / J65))} -> 0.34171745 | L65: 57990 | M65: {=IF(OR(L65=0, L65=""), 0, 1 - ((((XLOOKUP($A65, 'datos de inventario'!$A:$A, 'datos de inventario'!$D:$D, 0) * 'datos de inventario'!$K$2) + (XLOOKUP($A65, 'datos de inventario'!$A:$A, 'datos de inventario'!$F:$F, 0) * 'datos de inventario'!$K$3 * 'datos de inventario'!$K$4)) * 1.19 + (L65 * 0.15) + XLOOKUP(MAX($Z65, (XLOOKUP($A65, 'datos de inventario'!$A:$A, 'datos de inventario'!$F:$F, 0) * 1000000 / 4000)) + 0.1, Tarifas!$A$2:$A$33, IF(L65 <= 9989, Tarifas!$B$2:$B$33, IF(L65 <= 19989, Tarifas!$C$2:$C$33, Tarifas!$D$2:$D$33)), "Peso excedido", 1)) / L65))} -> 0.32418745 | N65: Hogar y MueblesTextiles de Hogar y DecoraciónRopa de CamaCubre Colchones | P65: 2 | Q65: =(P65/7)*30 -> 8.5714286 | R65: 5 | S65: =(R65/7)*30 -> 21.428571 | T65: 46023 | U65: =1-(J65/H65) -> 0.047626607 | V65: =1-(L65/J65) -> 0.03333889 | AB65: =W65*X65*Y65/1000000 -> 0
A66: FUNDALAPTOP14001NEG | B66: Funda protectora de laptop 14" Hosser | C66: Funda Notebook 13 - 14 Pulgadas Hosser Portatil 14" Negro | D66: =LEN(C66) -> 58 | E66: Funda Notebook 13 - 14 Pulgadas Hosser Bolsa Protectora Laptop Portatil Negro | F66: Funda Notebook 13-14 Pulgadas Hosser Protectora Laptop Portatil Negro | G66: =LEN(F66) -> 70 | H66: 11990 | I66: {=IF(OR(H66=0, H66=""), 0, 1 - ((((XLOOKUP($A66, 'datos de inventario'!$A:$A, 'datos de inventario'!$D:$D, 0) * 'datos de inventario'!$K$2) + (XLOOKUP($A66, 'datos de inventario'!$A:$A, 'datos de inventario'!$F:$F, 0) * 'datos de inventario'!$K$3 * 'datos de inventario'!$K$4)) * 1.19 + (H66 * 0.15) + XLOOKUP(MAX($Z66, (XLOOKUP($A66, 'datos de inventario'!$A:$A, 'datos de inventario'!$F:$F, 0) * 1000000 / 4000)) + 0.1, Tarifas!$A$2:$A$33, IF(H66 <= 9989, Tarifas!$B$2:$B$33, IF(H66 <= 19989, Tarifas!$C$2:$C$33, Tarifas!$D$2:$D$33)), "Peso excedido", 1)) / H66))} -> 0.52548436 | J66: 9990 | K66: {=IF(OR(J66=0, J66=""), 0, 1 - ((((XLOOKUP($A66, 'datos de inventario'!$A:$A, 'datos de inventario'!$D:$D, 0) * 'datos de inventario'!$K$2) + (XLOOKUP($A66, 'datos de inventario'!$A:$A, 'datos de inventario'!$F:$F, 0) * 'datos de inventario'!$K$3 * 'datos de inventario'!$K$4)) * 1.19 + (J66 * 0.15) + XLOOKUP(MAX($Z66, (XLOOKUP($A66, 'datos de inventario'!$A:$A, 'datos de inventario'!$F:$F, 0) * 1000000 / 4000)) + 0.1, Tarifas!$A$2:$A$33, IF(J66 <= 9989, Tarifas!$B$2:$B$33, IF(J66 <= 19989, Tarifas!$C$2:$C$33, Tarifas!$D$2:$D$33)), "Peso excedido", 1)) / J66))} -> 0.46051627 | L66: 8990 | M66: {=IF(OR(L66=0, L66=""), 0, 1 - ((((XLOOKUP($A66, 'datos de inventario'!$A:$A, 'datos de inventario'!$D:$D, 0) * 'datos de inventario'!$K$2) + (XLOOKUP($A66, 'datos de inventario'!$A:$A, 'datos de inventario'!$F:$F, 0) * 'datos de inventario'!$K$3 * 'datos de inventario'!$K$4)) * 1.19 + (L66 * 0.15) + XLOOKUP(MAX($Z66, (XLOOKUP($A66, 'datos de inventario'!$A:$A, 'datos de inventario'!$F:$F, 0) * 1000000 / 4000)) + 0.1, Tarifas!$A$2:$A$33, IF(L66 <= 9989, Tarifas!$B$2:$B$33, IF(L66 <= 19989, Tarifas!$C$2:$C$33, Tarifas!$D$2:$D$33)), "Peso excedido", 1)) / L66))} -> 0.44055145 | N66: ComputaciónNotebooks y AccesoriosAccesorios para NotebooksMochilas, Maletines y FundasMaletines y Bolsos | P66: 4 | Q66: =(P66/7)*30 -> 17.142857 | R66: 11.6 | S66: =(R66/7)*30 -> 49.714286 | T66: 46023 | U66: =1-(J66/H66) -> 0.16680567 | V66: =1-(L66/J66) -> 0.1001001 | AB66: =W66*X66*Y66/1000000 -> 0
A67: TOALLAUTO001GRI | B67: Toalla De Microfibra Secado Auto 1200 Gsm | C67: Paño Microfibra Para Autos Galanta Toalla Secado 1200 GSM | D67: =LEN(C67) -> 58 | E67: Paño De Microfibra Para Autos Galanta Toalla Secado 1200 GSM Limpieza Profesional Ultra Absorbente | F67: Paño De Microfibra Para Autos Galanta Toalla Secado 1200 GSM Limpieza | G67: =LEN(F67) -> 69 | H67: 15990 | I67: {=IF(OR(H67=0, H67=""), 0, 1 - ((((XLOOKUP($A67, 'datos de inventario'!$A:$A, 'datos de inventario'!$D:$D, 0) * 'datos de inventario'!$K$2) + (XLOOKUP($A67, 'datos de inventario'!$A:$A, 'datos de inventario'!$F:$F, 0) * 'datos de inventario'!$K$3 * 'datos de inventario'!$K$4)) * 1.19 + (H67 * 0.15) + XLOOKUP(MAX($Z67, (XLOOKUP($A67, 'datos de inventario'!$A:$A, 'datos de inventario'!$F:$F, 0) * 1000000 / 4000)) + 0.1, Tarifas!$A$2:$A$33, IF(H67 <= 9989, Tarifas!$B$2:$B$33, IF(H67 <= 19989, Tarifas!$C$2:$C$33, Tarifas!$D$2:$D$33)), "Peso excedido", 1)) / H67))} -> 0.51842292 | J67: 14990 | K67: {=IF(OR(J67=0, J67=""), 0, 1 - ((((XLOOKUP($A67, 'datos de inventario'!$A:$A, 'datos de inventario'!$D:$D, 0) * 'datos de inventario'!$K$2) + (XLOOKUP($A67, 'datos de inventario'!$A:$A, 'datos de inventario'!$F:$F, 0) * 'datos de inventario'!$K$3 * 'datos de inventario'!$K$4)) * 1.19 + (J67 * 0.15) + XLOOKUP(MAX($Z67, (XLOOKUP($A67, 'datos de inventario'!$A:$A, 'datos de inventario'!$F:$F, 0) * 1000000 / 4000)) + 0.1, Tarifas!$A$2:$A$33, IF(J67 <= 9989, Tarifas!$B$2:$B$33, IF(J67 <= 19989, Tarifas!$C$2:$C$33, Tarifas!$D$2:$D$33)), "Peso excedido", 1)) / J67))} -> 0.49630304 | L67: 12990 | M67: {=IF(OR(L67=0, L67=""), 0, 1 - ((((XLOOKUP($A67, 'datos de inventario'!$A:$A, 'datos de inventario'!$D:$D, 0) * 'datos de inventario'!$K$2) + (XLOOKUP($A67, 'datos de inventario'!$A:$A, 'datos de inventario'!$F:$F, 0) * 'datos de inventario'!$K$3 * 'datos de inventario'!$K$4)) * 1.19 + (L67 * 0.15) + XLOOKUP(MAX($Z67, (XLOOKUP($A67, 'datos de inventario'!$A:$A, 'datos de inventario'!$F:$F, 0) * 1000000 / 4000)) + 0.1, Tarifas!$A$2:$A$33, IF(L67 <= 9989, Tarifas!$B$2:$B$33, IF(L67 <= 19989, Tarifas!$C$2:$C$33, Tarifas!$D$2:$D$33)), "Peso excedido", 1)) / L67))} -> 0.44184623 | N67: Accesorios para VehículosLimpieza de VehículosPaños/super mercado | P67: 8.3 | Q67: =P67*4.3 -> 35.69 | R67: 25 | S67: =R67*4.3 -> 107.5 | T67: 46023 | U67: =1-(J67/H67) -> 0.062539087 | V67: =1-(L67/J67) -> 0.13342228 | AB67: =W67*X67*Y67/1000000 -> 0
A68: MICA002CARTA | B68: Láminas Termolaminadora Carta 125 micrones 100 Micas | C68: Laminas Termolaminadora Carta 100 Micas 125 Micrones Homely | D68: =LEN(C68) -> 60 | E68: Laminas Para Termolaminadora Tamaño Carta 100 Micas 125 Micrones Homely Plastificadora | F68: Laminas Termolaminadora Carta 100 Micas 125 Micrones Homely | G68: =LEN(F68) -> 60 | H68: 11990 | I68: {=IF(OR(H68=0, H68=""), 0, 1 - ((((XLOOKUP($A68, 'datos de inventario'!$A:$A, 'datos de inventario'!$D:$D, 0) * 'datos de inventario'!$K$2) + (XLOOKUP($A68, 'datos de inventario'!$A:$A, 'datos de inventario'!$F:$F, 0) * 'datos de inventario'!$K$3 * 'datos de inventario'!$K$4)) * 1.19 + (H68 * 0.15) + XLOOKUP(MAX($Z68, (XLOOKUP($A68, 'datos de inventario'!$A:$A, 'datos de inventario'!$F:$F, 0) * 1000000 / 4000)) + 0.1, Tarifas!$A$2:$A$33, IF(H68 <= 9989, Tarifas!$B$2:$B$33, IF(H68 <= 19989, Tarifas!$C$2:$C$33, Tarifas!$D$2:$D$33)), "Peso excedido", 1)) / H68))} -> 0.38134946 | J68: 10990 | K68: {=IF(OR(J68=0, J68=""), 0, 1 - ((((XLOOKUP($A68, 'datos de inventario'!$A:$A, 'datos de inventario'!$D:$D, 0) * 'datos de inventario'!$K$2) + (XLOOKUP($A68, 'datos de inventario'!$A:$A, 'datos de inventario'!$F:$F, 0) * 'datos de inventario'!$K$3 * 'datos de inventario'!$K$4)) * 1.19 + (J68 * 0.15) + XLOOKUP(MAX($Z68, (XLOOKUP($A68, 'datos de inventario'!$A:$A, 'datos de inventario'!$F:$F, 0) * 1000000 / 4000)) + 0.1, Tarifas!$A$2:$A$33, IF(J68 <= 9989, Tarifas!$B$2:$B$33, IF(J68 <= 19989, Tarifas!$C$2:$C$33, Tarifas!$D$2:$D$33)), "Peso excedido", 1)) / J68))} -> 0.3387061 | L68: 9980 | M68: {=IF(OR(L68=0, L68=""), 0, 1 - ((((XLOOKUP($A68, 'datos de inventario'!$A:$A, 'datos de inventario'!$D:$D, 0) * 'datos de inventario'!$K$2) + (XLOOKUP($A68, 'datos de inventario'!$A:$A, 'datos de inventario'!$F:$F, 0) * 'datos de inventario'!$K$3 * 'datos de inventario'!$K$4)) * 1.19 + (L68 * 0.15) + XLOOKUP(MAX($Z68, (XLOOKUP($A68, 'datos de inventario'!$A:$A, 'datos de inventario'!$F:$F, 0) * 1000000 / 4000)) + 0.1, Tarifas!$A$2:$A$33, IF(L68 <= 9989, Tarifas!$B$2:$B$33, IF(L68 <= 19989, Tarifas!$C$2:$C$33, Tarifas!$D$2:$D$33)), "Peso excedido", 1)) / L68))} -> 0.30800401 | N68: Industrias y OficinasGráfica e ImpresiónPlastificadoPlastificadoras | P68: 16 | Q68: =P68*4.3 -> 68.8 | R68: 50 | S68: =R68*4.3 -> 215 | T68: 46023 | U68: =1-(J68/H68) -> 0.083402836 | V68: =1-(L68/J68) -> 0.091901729 | AB68: =W68*X68*Y68/1000000 -> 0
A69: COJLAC002 | B69: Cojin Almohada Lactancia Maternal con funda herradura | C69: Cojin Maternal Lactancia Embarazada Mimoru Almohada U Dormir | D69: =LEN(C69) -> 60 | E69: Cojin Maternal De Lactancia Embarazada Mimoru Almohada U Funda Extra Suave Para Dormir Antimolestia Gris | F69: Cojin Maternal De Lactancia Embarazada Mimoru Almohada U Extra Suave | G69: =LEN(F69) -> 68 | H69: 34990 | I69: {=IF(OR(H69=0, H69=""), 0, 1 - ((((XLOOKUP($A69, 'datos de inventario'!$A:$A, 'datos de inventario'!$D:$D, 0) * 'datos de inventario'!$K$2) + (XLOOKUP($A69, 'datos de inventario'!$A:$A, 'datos de inventario'!$F:$F, 0) * 'datos de inventario'!$K$3 * 'datos de inventario'!$K$4)) * 1.19 + (H69 * 0.15) + XLOOKUP(MAX($Z69, (XLOOKUP($A69, 'datos de inventario'!$A:$A, 'datos de inventario'!$F:$F, 0) * 1000000 / 4000)) + 0.1, Tarifas!$A$2:$A$33, IF(H69 <= 9989, Tarifas!$B$2:$B$33, IF(H69 <= 19989, Tarifas!$C$2:$C$33, Tarifas!$D$2:$D$33)), "Peso excedido", 1)) / H69))} -> 0.41267255 | J69: 31990 | K69: {=IF(OR(J69=0, J69=""), 0, 1 - ((((XLOOKUP($A69, 'datos de inventario'!$A:$A, 'datos de inventario'!$D:$D, 0) * 'datos de inventario'!$K$2) + (XLOOKUP($A69, 'datos de inventario'!$A:$A, 'datos de inventario'!$F:$F, 0) * 'datos de inventario'!$K$3 * 'datos de inventario'!$K$4)) * 1.19 + (J69 * 0.15) + XLOOKUP(MAX($Z69, (XLOOKUP($A69, 'datos de inventario'!$A:$A, 'datos de inventario'!$F:$F, 0) * 1000000 / 4000)) + 0.1, Tarifas!$A$2:$A$33, IF(J69 <= 9989, Tarifas!$B$2:$B$33, IF(J69 <= 19989, Tarifas!$C$2:$C$33, Tarifas!$D$2:$D$33)), "Peso excedido", 1)) / J69))} -> 0.37166028 | L69: 28990 | M69: {=IF(OR(L69=0, L69=""), 0, 1 - ((((XLOOKUP($A69, 'datos de inventario'!$A:$A, 'datos de inventario'!$D:$D, 0) * 'datos de inventario'!$K$2) + (XLOOKUP($A69, 'datos de inventario'!$A:$A, 'datos de inventario'!$F:$F, 0) * 'datos de inventario'!$K$3 * 'datos de inventario'!$K$4)) * 1.19 + (L69 * 0.15) + XLOOKUP(MAX($Z69, (XLOOKUP($A69, 'datos de inventario'!$A:$A, 'datos de inventario'!$F:$F, 0) * 1000000 / 4000)) + 0.1, Tarifas!$A$2:$A$33, IF(L69 <= 9989, Tarifas!$B$2:$B$33, IF(L69 <= 19989, Tarifas!$C$2:$C$33, Tarifas!$D$2:$D$33)), "Peso excedido", 1)) / L69))} -> 0.3221598 | N69: BebésArticulos de MaternidadCojines de LactanciaCojin Maternal | P69: 8.3 | Q69: =P69*4.3 -> 35.69 | R69: 25 | S69: =R69*4.3 -> 107.5 | T69: 46023 | U69: =1-(J69/H69) -> 0.085738783 | V69: =1-(L69/J69) -> 0.093779306 | AB69: =W69*X69*Y69/1000000 -> 0
A70: COJLAC003 | B70: Cojin Almohada Lactancia Maternal con funda luna | C70: Cojin Maternal Lactancia Embarazada Mimoru Almohada 102x71Cm | D70: =LEN(C70) -> 60 | E70: Cojin Maternal De Lactancia Embarazada Mimoru Almohada 102x71 Cm Funda Extra Suave Para Dormir Antimolestia Gris | F70: Cojin Maternal De Lactancia Embarazada Mimoru Almohada 102x71 Cm | G70: =LEN(F70) -> 65 | H70: 19980 | I70: {=IF(OR(H70=0, H70=""), 0, 1 - ((((XLOOKUP($A70, 'datos de inventario'!$A:$A, 'datos de inventario'!$D:$D, 0) * 'datos de inventario'!$K$2) + (XLOOKUP($A70, 'datos de inventario'!$A:$A, 'datos de inventario'!$F:$F, 0) * 'datos de inventario'!$K$3 * 'datos de inventario'!$K$4)) * 1.19 + (H70 * 0.15) + XLOOKUP(MAX($Z70, (XLOOKUP($A70, 'datos de inventario'!$A:$A, 'datos de inventario'!$F:$F, 0) * 1000000 / 4000)) + 0.1, Tarifas!$A$2:$A$33, IF(H70 <= 9989, Tarifas!$B$2:$B$33, IF(H70 <= 19989, Tarifas!$C$2:$C$33, Tarifas!$D$2:$D$33)), "Peso excedido", 1)) / H70))} -> 0.38136485 | J70: 18990 | K70: {=IF(OR(J70=0, J70=""), 0, 1 - ((((XLOOKUP($A70, 'datos de inventario'!$A:$A, 'datos de inventario'!$D:$D, 0) * 'datos de inventario'!$K$2) + (XLOOKUP($A70, 'datos de inventario'!$A:$A, 'datos de inventario'!$F:$F, 0) * 'datos de inventario'!$K$3 * 'datos de inventario'!$K$4)) * 1.19 + (J70 * 0.15) + XLOOKUP(MAX($Z70, (XLOOKUP($A70, 'datos de inventario'!$A:$A, 'datos de inventario'!$F:$F, 0) * 1000000 / 4000)) + 0.1, Tarifas!$A$2:$A$33, IF(J70 <= 9989, Tarifas!$B$2:$B$33, IF(J70 <= 19989, Tarifas!$C$2:$C$33, Tarifas!$D$2:$D$33)), "Peso excedido", 1)) / J70))} -> 0.35693364 | L70: 17990 | M70: {=IF(OR(L70=0, L70=""), 0, 1 - ((((XLOOKUP($A70, 'datos de inventario'!$A:$A, 'datos de inventario'!$D:$D, 0) * 'datos de inventario'!$K$2) + (XLOOKUP($A70, 'datos de inventario'!$A:$A, 'datos de inventario'!$F:$F, 0) * 'datos de inventario'!$K$3 * 'datos de inventario'!$K$4)) * 1.19 + (L70 * 0.15) + XLOOKUP(MAX($Z70, (XLOOKUP($A70, 'datos de inventario'!$A:$A, 'datos de inventario'!$F:$F, 0) * 1000000 / 4000)) + 0.1, Tarifas!$A$2:$A$33, IF(L70 <= 9989, Tarifas!$B$2:$B$33, IF(L70 <= 19989, Tarifas!$C$2:$C$33, Tarifas!$D$2:$D$33)), "Peso excedido", 1)) / L70))} -> 0.32952583 | N70: BebésArticulos de MaternidadCojines de LactanciaCojin Maternal | P70: 8.3 | Q70: =P70*4.3 -> 35.69 | R70: 25 | S70: =R70*4.3 -> 107.5 | T70: 46054 | U70: =1-(J70/H70) -> 0.04954955 | V70: =1-(L70/J70) -> 0.052659294 | AB70: =W70*X70*Y70/1000000 -> 0
A71: BAJOACUSTIC001NEG | B71: Bajo electroacústico 43 pulgadas negro Ibrah music | C71: Bajo Electroacustico Ibrah Music 43" Negro + Pack Accesorios | D71: =LEN(C71) -> 60 | E71: Bajo Electroacustico Ibrah Music 43" Negro Con Funda De Transporte Y Pack Accesesorios | F71: Bajo Electroacustico Ibrah Music 43" Negro Con Funda De Transporte | G71: =LEN(F71) -> 67 | H71: 144990 | I71: {=IF(OR(H71=0, H71=""), 0, 1 - ((((XLOOKUP($A71, 'datos de inventario'!$A:$A, 'datos de inventario'!$D:$D, 0) * 'datos de inventario'!$K$2) + (XLOOKUP($A71, 'datos de inventario'!$A:$A, 'datos de inventario'!$F:$F, 0) * 'datos de inventario'!$K$3 * 'datos de inventario'!$K$4)) * 1.19 + (H71 * 0.15) + XLOOKUP(MAX($Z71, (XLOOKUP($A71, 'datos de inventario'!$A:$A, 'datos de inventario'!$F:$F, 0) * 1000000 / 4000)) + 0.1, Tarifas!$A$2:$A$33, IF(H71 <= 9989, Tarifas!$B$2:$B$33, IF(H71 <= 19989, Tarifas!$C$2:$C$33, Tarifas!$D$2:$D$33)), "Peso excedido", 1)) / H71))} -> 0.46409602 | J71: 139990 | K71: {=IF(OR(J71=0, J71=""), 0, 1 - ((((XLOOKUP($A71, 'datos de inventario'!$A:$A, 'datos de inventario'!$D:$D, 0) * 'datos de inventario'!$K$2) + (XLOOKUP($A71, 'datos de inventario'!$A:$A, 'datos de inventario'!$F:$F, 0) * 'datos de inventario'!$K$3 * 'datos de inventario'!$K$4)) * 1.19 + (J71 * 0.15) + XLOOKUP(MAX($Z71, (XLOOKUP($A71, 'datos de inventario'!$A:$A, 'datos de inventario'!$F:$F, 0) * 1000000 / 4000)) + 0.1, Tarifas!$A$2:$A$33, IF(J71 <= 9989, Tarifas!$B$2:$B$33, IF(J71 <= 19989, Tarifas!$C$2:$C$33, Tarifas!$D$2:$D$33)), "Peso excedido", 1)) / J71))} -> 0.45031275 | L71: 129990 | M71: {=IF(OR(L71=0, L71=""), 0, 1 - ((((XLOOKUP($A71, 'datos de inventario'!$A:$A, 'datos de inventario'!$D:$D, 0) * 'datos de inventario'!$K$2) + (XLOOKUP($A71, 'datos de inventario'!$A:$A, 'datos de inventario'!$F:$F, 0) * 'datos de inventario'!$K$3 * 'datos de inventario'!$K$4)) * 1.19 + (L71 * 0.15) + XLOOKUP(MAX($Z71, (XLOOKUP($A71, 'datos de inventario'!$A:$A, 'datos de inventario'!$F:$F, 0) * 1000000 / 4000)) + 0.1, Tarifas!$A$2:$A$33, IF(L71 <= 9989, Tarifas!$B$2:$B$33, IF(L71 <= 19989, Tarifas!$C$2:$C$33, Tarifas!$D$2:$D$33)), "Peso excedido", 1)) / L71))} -> 0.41956522 | N71: Instrumentos MusicalesInstrumentos de CuerdaBajos | P71: 0.6 | Q71: =P71*4.3 -> 2.58 | R71: 2 | S71: =R71*4.3 -> 8.6 | T71: 46054 | U71: =1-(J71/H71) -> 0.034485137 | V71: =1-(L71/J71) -> 0.071433674 | AB71: =W71*X71*Y71/1000000 -> 0
A72: GUIELECTROACUS002NEG | B72: Guitarra electroacústica 41 pulgadas 12 cuerdas negra Ibrah music | C72: Guitarra Electroacustica De 12 Cuerdas Ibrah Music 41" Negra | D72: =LEN(C72) -> 60 | E72: Guitarra Electroacustica De 12 Cuerdas Ibrah Music 41" Color Negra Con Funda De Transporte Y Pack Accesesorios | F72: Guitarra Electroacustica Ibrah Music 41" De 12 Cuerdas Color Negra | G72: =LEN(F72) -> 66 | H72: 149990 | I72: {=IF(OR(H72=0, H72=""), 0, 1 - ((((XLOOKUP($A72, 'datos de inventario'!$A:$A, 'datos de inventario'!$D:$D, 0) * 'datos de inventario'!$K$2) + (XLOOKUP($A72, 'datos de inventario'!$A:$A, 'datos de inventario'!$F:$F, 0) * 'datos de inventario'!$K$3 * 'datos de inventario'!$K$4)) * 1.19 + (H72 * 0.15) + XLOOKUP(MAX($Z72, (XLOOKUP($A72, 'datos de inventario'!$A:$A, 'datos de inventario'!$F:$F, 0) * 1000000 / 4000)) + 0.1, Tarifas!$A$2:$A$33, IF(H72 <= 9989, Tarifas!$B$2:$B$33, IF(H72 <= 19989, Tarifas!$C$2:$C$33, Tarifas!$D$2:$D$33)), "Peso excedido", 1)) / H72))} -> 0.44596116 | J72: 139990 | K72: {=IF(OR(J72=0, J72=""), 0, 1 - ((((XLOOKUP($A72, 'datos de inventario'!$A:$A, 'datos de inventario'!$D:$D, 0) * 'datos de inventario'!$K$2) + (XLOOKUP($A72, 'datos de inventario'!$A:$A, 'datos de inventario'!$F:$F, 0) * 'datos de inventario'!$K$3 * 'datos de inventario'!$K$4)) * 1.19 + (J72 * 0.15) + XLOOKUP(MAX($Z72, (XLOOKUP($A72, 'datos de inventario'!$A:$A, 'datos de inventario'!$F:$F, 0) * 1000000 / 4000)) + 0.1, Tarifas!$A$2:$A$33, IF(J72 <= 9989, Tarifas!$B$2:$B$33, IF(J72 <= 19989, Tarifas!$C$2:$C$33, Tarifas!$D$2:$D$33)), "Peso excedido", 1)) / J72))} -> 0.41709918 | L72: 129990 | M72: {=IF(OR(L72=0, L72=""), 0, 1 - ((((XLOOKUP($A72, 'datos de inventario'!$A:$A, 'datos de inventario'!$D:$D, 0) * 'datos de inventario'!$K$2) + (XLOOKUP($A72, 'datos de inventario'!$A:$A, 'datos de inventario'!$F:$F, 0) * 'datos de inventario'!$K$3 * 'datos de inventario'!$K$4)) * 1.19 + (L72 * 0.15) + XLOOKUP(MAX($Z72, (XLOOKUP($A72, 'datos de inventario'!$A:$A, 'datos de inventario'!$F:$F, 0) * 1000000 / 4000)) + 0.1, Tarifas!$A$2:$A$33, IF(L72 <= 9989, Tarifas!$B$2:$B$33, IF(L72 <= 19989, Tarifas!$C$2:$C$33, Tarifas!$D$2:$D$33)), "Peso excedido", 1)) / L72))} -> 0.38379656 | N72: Instrumentos MusicalesInstrumentos de CuerdaGuitarrasAcústicasGuitarra Acustica | P72: 1.5 | Q72: =P72*4.3 -> 6.45 | R72: 6 | S72: =R72*4.3 -> 25.8 | T72: 46054 | U72: =1-(J72/H72) -> 0.066671111 | V72: =1-(L72/J72) -> 0.071433674 | AB72: =W72*X72*Y72/1000000 -> 0
A73: ELEVADORTALONES001 | B73: Elevador De Talones De Caucho cuña 70 cm largo | C73: Cuña Talonera Sentadillas Plataforma Inclinada 20° Overfit | D73: =LEN(C73) -> 58 | E73: Cuña Talonera De Goma Para Sentadillas Plataforma Inclinada 20 Grados Overfit Gym Elevaciones Pantorrilla | F73: Talonera De Goma Bloque De Cuña Inclinada 20 Grados Para Gym Overfit | G73: =LEN(F73) -> 68 | H73: 39990 | I73: {=IF(OR(H73=0, H73=""), 0, 1 - ((((XLOOKUP($A73, 'datos de inventario'!$A:$A, 'datos de inventario'!$D:$D, 0) * 'datos de inventario'!$K$2) + (XLOOKUP($A73, 'datos de inventario'!$A:$A, 'datos de inventario'!$F:$F, 0) * 'datos de inventario'!$K$3 * 'datos de inventario'!$K$4)) * 1.19 + (H73 * 0.15) + XLOOKUP(MAX($Z73, (XLOOKUP($A73, 'datos de inventario'!$A:$A, 'datos de inventario'!$F:$F, 0) * 1000000 / 4000)) + 0.1, Tarifas!$A$2:$A$33, IF(H73 <= 9989, Tarifas!$B$2:$B$33, IF(H73 <= 19989, Tarifas!$C$2:$C$33, Tarifas!$D$2:$D$33)), "Peso excedido", 1)) / H73))} -> 0.37412416 | J73: 37990 | K73: {=IF(OR(J73=0, J73=""), 0, 1 - ((((XLOOKUP($A73, 'datos de inventario'!$A:$A, 'datos de inventario'!$D:$D, 0) * 'datos de inventario'!$K$2) + (XLOOKUP($A73, 'datos de inventario'!$A:$A, 'datos de inventario'!$F:$F, 0) * 'datos de inventario'!$K$3 * 'datos de inventario'!$K$4)) * 1.19 + (J73 * 0.15) + XLOOKUP(MAX($Z73, (XLOOKUP($A73, 'datos de inventario'!$A:$A, 'datos de inventario'!$F:$F, 0) * 1000000 / 4000)) + 0.1, Tarifas!$A$2:$A$33, IF(J73 <= 9989, Tarifas!$B$2:$B$33, IF(J73 <= 19989, Tarifas!$C$2:$C$33, Tarifas!$D$2:$D$33)), "Peso excedido", 1)) / J73))} -> 0.34907147 | L73: 35990 | M73: {=IF(OR(L73=0, L73=""), 0, 1 - ((((XLOOKUP($A73, 'datos de inventario'!$A:$A, 'datos de inventario'!$D:$D, 0) * 'datos de inventario'!$K$2) + (XLOOKUP($A73, 'datos de inventario'!$A:$A, 'datos de inventario'!$F:$F, 0) * 'datos de inventario'!$K$3 * 'datos de inventario'!$K$4)) * 1.19 + (L73 * 0.15) + XLOOKUP(MAX($Z73, (XLOOKUP($A73, 'datos de inventario'!$A:$A, 'datos de inventario'!$F:$F, 0) * 1000000 / 4000)) + 0.1, Tarifas!$A$2:$A$33, IF(L73 <= 9989, Tarifas!$B$2:$B$33, IF(L73 <= 19989, Tarifas!$C$2:$C$33, Tarifas!$D$2:$D$33)), "Peso excedido", 1)) / L73))} -> 0.32123437 | N73: Deportes y FitnessFitness y MusculaciónFuncional, Pilates y YogaSteps | P73: 1.25 | Q73: =P73*4.3 -> 5.375 | R73: 5 | S73: =R73*4.3 -> 21.5 | T73: 46054 | U73: =1-(J73/H73) -> 0.050012503 | V73: =1-(L73/J73) -> 0.052645433 | AB73: =W73*X73*Y73/1000000 -> 0
A74: SET3ELEVADORTALONES001 | B74: Elevadores de talones set 3 niveles ajustables | C74: Cuña Sentadilla Talonera Bloque 3 Niveles Gym Overfit Rampa | D74: =LEN(C74) -> 59 | E74: Cuña Para Sentadilla Talonera Bloque De 3 Niveles Gym Overfit Rampa Soporte Ajustable Mejora de postura Elevaciones | F74: Talonera Bloque De Cuña Sentadilla Overfit 3 Niveles Ajustable Gym | G74: =LEN(F74) -> 67 | H74: 18990 | I74: {=IF(OR(H74=0, H74=""), 0, 1 - ((((XLOOKUP($A74, 'datos de inventario'!$A:$A, 'datos de inventario'!$D:$D, 0) * 'datos de inventario'!$K$2) + (XLOOKUP($A74, 'datos de inventario'!$A:$A, 'datos de inventario'!$F:$F, 0) * 'datos de inventario'!$K$3 * 'datos de inventario'!$K$4)) * 1.19 + (H74 * 0.15) + XLOOKUP(MAX($Z74, (XLOOKUP($A74, 'datos de inventario'!$A:$A, 'datos de inventario'!$F:$F, 0) * 1000000 / 4000)) + 0.1, Tarifas!$A$2:$A$33, IF(H74 <= 9989, Tarifas!$B$2:$B$33, IF(H74 <= 19989, Tarifas!$C$2:$C$33, Tarifas!$D$2:$D$33)), "Peso excedido", 1)) / H74))} -> 0.57622399 | J74: 14990 | K74: {=IF(OR(J74=0, J74=""), 0, 1 - ((((XLOOKUP($A74, 'datos de inventario'!$A:$A, 'datos de inventario'!$D:$D, 0) * 'datos de inventario'!$K$2) + (XLOOKUP($A74, 'datos de inventario'!$A:$A, 'datos de inventario'!$F:$F, 0) * 'datos de inventario'!$K$3 * 'datos de inventario'!$K$4)) * 1.19 + (J74 * 0.15) + XLOOKUP(MAX($Z74, (XLOOKUP($A74, 'datos de inventario'!$A:$A, 'datos de inventario'!$F:$F, 0) * 1000000 / 4000)) + 0.1, Tarifas!$A$2:$A$33, IF(J74 <= 9989, Tarifas!$B$2:$B$33, IF(J74 <= 19989, Tarifas!$C$2:$C$33, Tarifas!$D$2:$D$33)), "Peso excedido", 1)) / J74))} -> 0.50316835 | L74: 12990 | M74: {=IF(OR(L74=0, L74=""), 0, 1 - ((((XLOOKUP($A74, 'datos de inventario'!$A:$A, 'datos de inventario'!$D:$D, 0) * 'datos de inventario'!$K$2) + (XLOOKUP($A74, 'datos de inventario'!$A:$A, 'datos de inventario'!$F:$F, 0) * 'datos de inventario'!$K$3 * 'datos de inventario'!$K$4)) * 1.19 + (L74 * 0.15) + XLOOKUP(MAX($Z74, (XLOOKUP($A74, 'datos de inventario'!$A:$A, 'datos de inventario'!$F:$F, 0) * 1000000 / 4000)) + 0.1, Tarifas!$A$2:$A$33, IF(L74 <= 9989, Tarifas!$B$2:$B$33, IF(L74 <= 19989, Tarifas!$C$2:$C$33, Tarifas!$D$2:$D$33)), "Peso excedido", 1)) / L74))} -> 0.44976855 | N74: Deportes y FitnessFitness y MusculaciónFuncional, Pilates y YogaSteps | P74: 1.25 | Q74: =P74*4.3 -> 5.375 | R74: 5 | S74: =R74*4.3 -> 21.5 | T74: 46054 | U74: =1-(J74/H74) -> 0.21063718 | V74: =1-(L74/J74) -> 0.13342228 | AB74: =W74*X74*Y74/1000000 -> 0
A75: MUDADORBEBE001GRIS | B75: Mudador cambiador de bebé portatil plegable impermeable | C75: Mudador Portatil Bebe Impermeable Mimoru Cambiador Plegable | D75: =LEN(C75) -> 59 | E75: Mudador Portatil Bebe Impermeable Mimoru Para Cambiar Pañales Plegable | F75: Mudador Portatil Bebe Impermeable Mimoru Para Cambiar Pañales Plegable | G75: =LEN(F75) -> 70 | H75: 14990 | I75: {=IF(OR(H75=0, H75=""), 0, 1 - ((((XLOOKUP($A75, 'datos de inventario'!$A:$A, 'datos de inventario'!$D:$D, 0) * 'datos de inventario'!$K$2) + (XLOOKUP($A75, 'datos de inventario'!$A:$A, 'datos de inventario'!$F:$F, 0) * 'datos de inventario'!$K$3 * 'datos de inventario'!$K$4)) * 1.19 + (H75 * 0.15) + XLOOKUP(MAX($Z75, (XLOOKUP($A75, 'datos de inventario'!$A:$A, 'datos de inventario'!$F:$F, 0) * 1000000 / 4000)) + 0.1, Tarifas!$A$2:$A$33, IF(H75 <= 9989, Tarifas!$B$2:$B$33, IF(H75 <= 19989, Tarifas!$C$2:$C$33, Tarifas!$D$2:$D$33)), "Peso excedido", 1)) / H75))} -> 0.4606025 | J75: 11990 | K75: {=IF(OR(J75=0, J75=""), 0, 1 - ((((XLOOKUP($A75, 'datos de inventario'!$A:$A, 'datos de inventario'!$D:$D, 0) * 'datos de inventario'!$K$2) + (XLOOKUP($A75, 'datos de inventario'!$A:$A, 'datos de inventario'!$F:$F, 0) * 'datos de inventario'!$K$3 * 'datos de inventario'!$K$4)) * 1.19 + (J75 * 0.15) + XLOOKUP(MAX($Z75, (XLOOKUP($A75, 'datos de inventario'!$A:$A, 'datos de inventario'!$F:$F, 0) * 1000000 / 4000)) + 0.1, Tarifas!$A$2:$A$33, IF(J75 <= 9989, Tarifas!$B$2:$B$33, IF(J75 <= 19989, Tarifas!$C$2:$C$33, Tarifas!$D$2:$D$33)), "Peso excedido", 1)) / J75))} -> 0.36317193 | L75: 9980 | M75: {=IF(OR(L75=0, L75=""), 0, 1 - ((((XLOOKUP($A75, 'datos de inventario'!$A:$A, 'datos de inventario'!$D:$D, 0) * 'datos de inventario'!$K$2) + (XLOOKUP($A75, 'datos de inventario'!$A:$A, 'datos de inventario'!$F:$F, 0) * 'datos de inventario'!$K$3 * 'datos de inventario'!$K$4)) * 1.19 + (L75 * 0.15) + XLOOKUP(MAX($Z75, (XLOOKUP($A75, 'datos de inventario'!$A:$A, 'datos de inventario'!$F:$F, 0) * 1000000 / 4000)) + 0.1, Tarifas!$A$2:$A$33, IF(L75 <= 9989, Tarifas!$B$2:$B$33, IF(L75 <= 19989, Tarifas!$C$2:$C$33, Tarifas!$D$2:$D$33)), "Peso excedido", 1)) / L75))} -> 0.28616548 | N75: BebésArticulos de MaternidadCambiadores PortátilesMudador Plegable | P75: =Q75/30*7 -> 1.4 | Q75: 6 | R75: =S75/30*7 -> 4.2 | S75: 18 | T75: 46054 | U75: =1-(J75/H75) -> 0.20013342 | V75: =1-(L75/J75) -> 0.1676397 | AB75: =W75*X75*Y75/1000000 -> 0
A76: MUDADORBEBE002 | B76: Mudador bebé colchoneta impermeable anatómico portatil | C76: Mudador Bebe Anatomico Horizontal Mimoru Ergonomico Blanco | D76: =LEN(C76) -> 59 | E76: Mudador De Bebe Anatomico Horizontal Mimoru Ergonomico Impermeable Color Blanco | F76: Mudador De Bebe Anatomico Horizontal Mimoru Ergonomico Impermeable | G76: =LEN(F76) -> 66 | H76: 18990 | I76: {=IF(OR(H76=0, H76=""), 0, 1 - ((((XLOOKUP($A76, 'datos de inventario'!$A:$A, 'datos de inventario'!$D:$D, 0) * 'datos de inventario'!$K$2) + (XLOOKUP($A76, 'datos de inventario'!$A:$A, 'datos de inventario'!$F:$F, 0) * 'datos de inventario'!$K$3 * 'datos de inventario'!$K$4)) * 1.19 + (H76 * 0.15) + XLOOKUP(MAX($Z76, (XLOOKUP($A76, 'datos de inventario'!$A:$A, 'datos de inventario'!$F:$F, 0) * 1000000 / 4000)) + 0.1, Tarifas!$A$2:$A$33, IF(H76 <= 9989, Tarifas!$B$2:$B$33, IF(H76 <= 19989, Tarifas!$C$2:$C$33, Tarifas!$D$2:$D$33)), "Peso excedido", 1)) / H76))} -> 0.37844837 | J76: 16990 | K76: {=IF(OR(J76=0, J76=""), 0, 1 - ((((XLOOKUP($A76, 'datos de inventario'!$A:$A, 'datos de inventario'!$D:$D, 0) * 'datos de inventario'!$K$2) + (XLOOKUP($A76, 'datos de inventario'!$A:$A, 'datos de inventario'!$F:$F, 0) * 'datos de inventario'!$K$3 * 'datos de inventario'!$K$4)) * 1.19 + (J76 * 0.15) + XLOOKUP(MAX($Z76, (XLOOKUP($A76, 'datos de inventario'!$A:$A, 'datos de inventario'!$F:$F, 0) * 1000000 / 4000)) + 0.1, Tarifas!$A$2:$A$33, IF(J76 <= 9989, Tarifas!$B$2:$B$33, IF(J76 <= 19989, Tarifas!$C$2:$C$33, Tarifas!$D$2:$D$33)), "Peso excedido", 1)) / J76))} -> 0.32293905 | L76: 14990 | M76: {=IF(OR(L76=0, L76=""), 0, 1 - ((((XLOOKUP($A76, 'datos de inventario'!$A:$A, 'datos de inventario'!$D:$D, 0) * 'datos de inventario'!$K$2) + (XLOOKUP($A76, 'datos de inventario'!$A:$A, 'datos de inventario'!$F:$F, 0) * 'datos de inventario'!$K$3 * 'datos de inventario'!$K$4)) * 1.19 + (L76 * 0.15) + XLOOKUP(MAX($Z76, (XLOOKUP($A76, 'datos de inventario'!$A:$A, 'datos de inventario'!$F:$F, 0) * 1000000 / 4000)) + 0.1, Tarifas!$A$2:$A$33, IF(L76 <= 9989, Tarifas!$B$2:$B$33, IF(L76 <= 19989, Tarifas!$C$2:$C$33, Tarifas!$D$2:$D$33)), "Peso excedido", 1)) / L76))} -> 0.25261738 | N76: BebésArticulos de MaternidadCambiadores PortátilesColchoneta Mudador | P76: =Q76/30*7 -> 2.3333333 | Q76: 10 | R76: =S76/30*7 -> 7 | S76: 30 | T76: 46054 | U76: =1-(J76/H76) -> 0.10531859 | V76: =1-(L76/J76) -> 0.1177163 | AB76: =W76*X76*Y76/1000000 -> 0
A77: CAJAORGA005 | B77: Carrito organizadores bajo cama 48 litros unidad | C77: Cajas Organizadoras Bajo Cama Homely Carrito Ruedas 48Litros | D77: =LEN(C77) -> 60 | E77: Bolsas Organizadoras Almacenamiento Bajo Cama Cajas Plasticas Homely Carrito De Metal Con Ruedas 78 X 43 X 17 Cm 48 Litros Gris | F77: Bolsas Organizadoras Almacenamiento Bajo Cama Homely 48 Litros Gris | G77: =LEN(F77) -> 67 | H77: 18990 | I77: {=IF(OR(H77=0, H77=""), 0, 1 - ((((XLOOKUP($A77, 'datos de inventario'!$A:$A, 'datos de inventario'!$D:$D, 0) * 'datos de inventario'!$K$2) + (XLOOKUP($A77, 'datos de inventario'!$A:$A, 'datos de inventario'!$F:$F, 0) * 'datos de inventario'!$K$3 * 'datos de inventario'!$K$4)) * 1.19 + (H77 * 0.15) + XLOOKUP(MAX($Z77, (XLOOKUP($A77, 'datos de inventario'!$A:$A, 'datos de inventario'!$F:$F, 0) * 1000000 / 4000)) + 0.1, Tarifas!$A$2:$A$33, IF(H77 <= 9989, Tarifas!$B$2:$B$33, IF(H77 <= 19989, Tarifas!$C$2:$C$33, Tarifas!$D$2:$D$33)), "Peso excedido", 1)) / H77))} -> 0.41548782 | J77: 16990 | K77: {=IF(OR(J77=0, J77=""), 0, 1 - ((((XLOOKUP($A77, 'datos de inventario'!$A:$A, 'datos de inventario'!$D:$D, 0) * 'datos de inventario'!$K$2) + (XLOOKUP($A77, 'datos de inventario'!$A:$A, 'datos de inventario'!$F:$F, 0) * 'datos de inventario'!$K$3 * 'datos de inventario'!$K$4)) * 1.19 + (J77 * 0.15) + XLOOKUP(MAX($Z77, (XLOOKUP($A77, 'datos de inventario'!$A:$A, 'datos de inventario'!$F:$F, 0) * 1000000 / 4000)) + 0.1, Tarifas!$A$2:$A$33, IF(J77 <= 9989, Tarifas!$B$2:$B$33, IF(J77 <= 19989, Tarifas!$C$2:$C$33, Tarifas!$D$2:$D$33)), "Peso excedido", 1)) / J77))} -> 0.36433866 | L77: 14990 | M77: {=IF(OR(L77=0, L77=""), 0, 1 - ((((XLOOKUP($A77, 'datos de inventario'!$A:$A, 'datos de inventario'!$D:$D, 0) * 'datos de inventario'!$K$2) + (XLOOKUP($A77, 'datos de inventario'!$A:$A, 'datos de inventario'!$F:$F, 0) * 'datos de inventario'!$K$3 * 'datos de inventario'!$K$4)) * 1.19 + (L77 * 0.15) + XLOOKUP(MAX($Z77, (XLOOKUP($A77, 'datos de inventario'!$A:$A, 'datos de inventario'!$F:$F, 0) * 1000000 / 4000)) + 0.1, Tarifas!$A$2:$A$33, IF(L77 <= 9989, Tarifas!$B$2:$B$33, IF(L77 <= 19989, Tarifas!$C$2:$C$33, Tarifas!$D$2:$D$33)), "Peso excedido", 1)) / L77))} -> 0.29954061 | N77: Hogar y MueblesOrganización para el HogarCajas | P77: =Q77/30*7 -> 2.3333333 | Q77: 10 | R77: =S77/30*7 -> 7 | S77: 30 | T77: 46054 | U77: =1-(J77/H77) -> 0.10531859 | V77: =1-(L77/J77) -> 0.1177163 | AB77: =W77*X77*Y77/1000000 -> 0
A78: COJLAC004 | B78: Almohadilla cojin de lactancia para bebe diseño estrellas | C78: Cojin Maternal De Lactancia Bebe Almuhada Embarazada Mimoru | D78: =LEN(C78) -> 59 | E78: Cojin Maternal De Lactancia Para Bebe Almuhada Embarazada Mimoru Multifuncional | F78: Cojin Maternal De Lactancia Para Bebe Almuhada Embarazada Mimoru | G78: =LEN(F78) -> 64 | H78: 16990 | I78: {=IF(OR(H78=0, H78=""), 0, 1 - ((((XLOOKUP($A78, 'datos de inventario'!$A:$A, 'datos de inventario'!$D:$D, 0) * 'datos de inventario'!$K$2) + (XLOOKUP($A78, 'datos de inventario'!$A:$A, 'datos de inventario'!$F:$F, 0) * 'datos de inventario'!$K$3 * 'datos de inventario'!$K$4)) * 1.19 + (H78 * 0.15) + XLOOKUP(MAX($Z78, (XLOOKUP($A78, 'datos de inventario'!$A:$A, 'datos de inventario'!$F:$F, 0) * 1000000 / 4000)) + 0.1, Tarifas!$A$2:$A$33, IF(H78 <= 9989, Tarifas!$B$2:$B$33, IF(H78 <= 19989, Tarifas!$C$2:$C$33, Tarifas!$D$2:$D$33)), "Peso excedido", 1)) / H78))} -> 0.5214608 | J78: 14990 | K78: {=IF(OR(J78=0, J78=""), 0, 1 - ((((XLOOKUP($A78, 'datos de inventario'!$A:$A, 'datos de inventario'!$D:$D, 0) * 'datos de inventario'!$K$2) + (XLOOKUP($A78, 'datos de inventario'!$A:$A, 'datos de inventario'!$F:$F, 0) * 'datos de inventario'!$K$3 * 'datos de inventario'!$K$4)) * 1.19 + (J78 * 0.15) + XLOOKUP(MAX($Z78, (XLOOKUP($A78, 'datos de inventario'!$A:$A, 'datos de inventario'!$F:$F, 0) * 1000000 / 4000)) + 0.1, Tarifas!$A$2:$A$33, IF(J78 <= 9989, Tarifas!$B$2:$B$33, IF(J78 <= 19989, Tarifas!$C$2:$C$33, Tarifas!$D$2:$D$33)), "Peso excedido", 1)) / J78))} -> 0.47762635 | L78: 12990 | M78: {=IF(OR(L78=0, L78=""), 0, 1 - ((((XLOOKUP($A78, 'datos de inventario'!$A:$A, 'datos de inventario'!$D:$D, 0) * 'datos de inventario'!$K$2) + (XLOOKUP($A78, 'datos de inventario'!$A:$A, 'datos de inventario'!$F:$F, 0) * 'datos de inventario'!$K$3 * 'datos de inventario'!$K$4)) * 1.19 + (L78 * 0.15) + XLOOKUP(MAX($Z78, (XLOOKUP($A78, 'datos de inventario'!$A:$A, 'datos de inventario'!$F:$F, 0) * 1000000 / 4000)) + 0.1, Tarifas!$A$2:$A$33, IF(L78 <= 9989, Tarifas!$B$2:$B$33, IF(L78 <= 19989, Tarifas!$C$2:$C$33, Tarifas!$D$2:$D$33)), "Peso excedido", 1)) / L78))} -> 0.420294 | N78: BebésArticulos de MaternidadCojines de Lactancia | P78: =Q78/30*7 -> 2.8 | Q78: 12 | R78: =S78/30*7 -> 8.1666667 | S78: 35 | T78: 46054 | U78: =1-(J78/H78) -> 0.1177163 | V78: =1-(L78/J78) -> 0.13342228 | AB78: =W78*X78*Y78/1000000 -> 0
A79: CAJAORGA006 | B79: Set x 2 bolsas organizadoras malla transparente bajo cama | C79: Bolsas Organizadoras Bajo Cama Homely trasnparente 52L Set 2 | D79: =LEN(C79) -> 60 | E79: Bolsas Organizadoras Almacenamiento Bajo Cama Homely Cajas Plasticas Contenedor 52 Litros Set X2 Transparante | F79: Bolsas Organizadoras Almacenamiento Homely 52L Set X2 Transparante | G79: =LEN(F79) -> 66 | H79: 11990 | I79: {=IF(OR(H79=0, H79=""), 0, 1 - ((((XLOOKUP($A79, 'datos de inventario'!$A:$A, 'datos de inventario'!$D:$D, 0) * 'datos de inventario'!$K$2) + (XLOOKUP($A79, 'datos de inventario'!$A:$A, 'datos de inventario'!$F:$F, 0) * 'datos de inventario'!$K$3 * 'datos de inventario'!$K$4)) * 1.19 + (H79 * 0.15) + XLOOKUP(MAX($Z79, (XLOOKUP($A79, 'datos de inventario'!$A:$A, 'datos de inventario'!$F:$F, 0) * 1000000 / 4000)) + 0.1, Tarifas!$A$2:$A$33, IF(H79 <= 9989, Tarifas!$B$2:$B$33, IF(H79 <= 19989, Tarifas!$C$2:$C$33, Tarifas!$D$2:$D$33)), "Peso excedido", 1)) / H79))} -> 0.45084635 | J79: 9980 | K79: {=IF(OR(J79=0, J79=""), 0, 1 - ((((XLOOKUP($A79, 'datos de inventario'!$A:$A, 'datos de inventario'!$D:$D, 0) * 'datos de inventario'!$K$2) + (XLOOKUP($A79, 'datos de inventario'!$A:$A, 'datos de inventario'!$F:$F, 0) * 'datos de inventario'!$K$3 * 'datos de inventario'!$K$4)) * 1.19 + (J79 * 0.15) + XLOOKUP(MAX($Z79, (XLOOKUP($A79, 'datos de inventario'!$A:$A, 'datos de inventario'!$F:$F, 0) * 1000000 / 4000)) + 0.1, Tarifas!$A$2:$A$33, IF(J79 <= 9989, Tarifas!$B$2:$B$33, IF(J79 <= 19989, Tarifas!$C$2:$C$33, Tarifas!$D$2:$D$33)), "Peso excedido", 1)) / J79))} -> 0.39149777 | L79: 7990 | M79: {=IF(OR(L79=0, L79=""), 0, 1 - ((((XLOOKUP($A79, 'datos de inventario'!$A:$A, 'datos de inventario'!$D:$D, 0) * 'datos de inventario'!$K$2) + (XLOOKUP($A79, 'datos de inventario'!$A:$A, 'datos de inventario'!$F:$F, 0) * 'datos de inventario'!$K$3 * 'datos de inventario'!$K$4)) * 1.19 + (L79 * 0.15) + XLOOKUP(MAX($Z79, (XLOOKUP($A79, 'datos de inventario'!$A:$A, 'datos de inventario'!$F:$F, 0) * 1000000 / 4000)) + 0.1, Tarifas!$A$2:$A$33, IF(L79 <= 9989, Tarifas!$B$2:$B$33, IF(L79 <= 19989, Tarifas!$C$2:$C$33, Tarifas!$D$2:$D$33)), "Peso excedido", 1)) / L79))} -> 0.2773026 | N79: Hogar y MueblesOrganización para el HogarCajas | P79: =Q79/30*7 -> 2.3333333 | Q79: 10 | R79: =S79/30*7 -> 7 | S79: 30 | T79: 46054 | U79: =1-(J79/H79) -> 0.1676397 | V79: =1-(L79/J79) -> 0.1993988 | AB79: =W79*X79*Y79/1000000 -> 0
A80: BOLSASMUDANZA001 | B80: Set x 2 bolsas mudanza gris 90 Litros | C80: Bolsas Mudanzas Almacenamiento Grande Homely 90L Gris Set 2 | D80: =LEN(C80) -> 59 | E80: Bolsas Mudanzas Almacenamiento Extra Grande Homely 90 Litros Color Gris Set x2 | F80: Bolsas Mudanzas Almacenamiento Extra Grande Homely 85L Gris Set x2 | G80: =LEN(F80) -> 66 | H80: 13990 | I80: {=IF(OR(H80=0, H80=""), 0, 1 - ((((XLOOKUP($A80, 'datos de inventario'!$A:$A, 'datos de inventario'!$D:$D, 0) * 'datos de inventario'!$K$2) + (XLOOKUP($A80, 'datos de inventario'!$A:$A, 'datos de inventario'!$F:$F, 0) * 'datos de inventario'!$K$3 * 'datos de inventario'!$K$4)) * 1.19 + (H80 * 0.15) + XLOOKUP(MAX($Z80, (XLOOKUP($A80, 'datos de inventario'!$A:$A, 'datos de inventario'!$F:$F, 0) * 1000000 / 4000)) + 0.1, Tarifas!$A$2:$A$33, IF(H80 <= 9989, Tarifas!$B$2:$B$33, IF(H80 <= 19989, Tarifas!$C$2:$C$33, Tarifas!$D$2:$D$33)), "Peso excedido", 1)) / H80))} -> 0.46809637 | J80: 11990 | K80: {=IF(OR(J80=0, J80=""), 0, 1 - ((((XLOOKUP($A80, 'datos de inventario'!$A:$A, 'datos de inventario'!$D:$D, 0) * 'datos de inventario'!$K$2) + (XLOOKUP($A80, 'datos de inventario'!$A:$A, 'datos de inventario'!$F:$F, 0) * 'datos de inventario'!$K$3 * 'datos de inventario'!$K$4)) * 1.19 + (J80 * 0.15) + XLOOKUP(MAX($Z80, (XLOOKUP($A80, 'datos de inventario'!$A:$A, 'datos de inventario'!$F:$F, 0) * 1000000 / 4000)) + 0.1, Tarifas!$A$2:$A$33, IF(J80 <= 9989, Tarifas!$B$2:$B$33, IF(J80 <= 19989, Tarifas!$C$2:$C$33, Tarifas!$D$2:$D$33)), "Peso excedido", 1)) / J80))} -> 0.40439268 | L80: 9980 | M80: {=IF(OR(L80=0, L80=""), 0, 1 - ((((XLOOKUP($A80, 'datos de inventario'!$A:$A, 'datos de inventario'!$D:$D, 0) * 'datos de inventario'!$K$2) + (XLOOKUP($A80, 'datos de inventario'!$A:$A, 'datos de inventario'!$F:$F, 0) * 'datos de inventario'!$K$3 * 'datos de inventario'!$K$4)) * 1.19 + (L80 * 0.15) + XLOOKUP(MAX($Z80, (XLOOKUP($A80, 'datos de inventario'!$A:$A, 'datos de inventario'!$F:$F, 0) * 1000000 / 4000)) + 0.1, Tarifas!$A$2:$A$33, IF(L80 <= 9989, Tarifas!$B$2:$B$33, IF(L80 <= 19989, Tarifas!$C$2:$C$33, Tarifas!$D$2:$D$33)), "Peso excedido", 1)) / L80))} -> 0.3356882 | N80: Hogar y MueblesOrganización para el HogarCajas / tambien vende mucho en Vestuario y CalzadoBolsos, Carteras y MochilasEquipaje y Accesorios de ViajeBolsos de Viaje | P80: 3 | Q80: =P80*4.3 -> 12.9 | R80: 8 | S80: =R80*4.3 -> 34.4 | T80: 46082 | U80: =1-(J80/H80) -> 0.14295926 | V80: =1-(L80/J80) -> 0.1676397 | AB80: =W80*X80*Y80/1000000 -> 0
A81: CAJAORGA007 | B81: Set x 6 Cajas Cubo Organizadoras Closet Ropa Accesorios Plegables Beige | C81: Cajas Organizadoras Cubo Plegable Homely Beige Ropa Pack 6 | D81: =LEN(C81) -> 58 | E81: Cajas Organizadoras Cubo Plegable Homely Color Beige Closet Ropa Accesorios Pack 6 | F81: Cajas Organizadoras Cubo Plegable Homely Beige Ropa Accesorios Pack 6 | G81: =LEN(F81) -> 69 | H81: 17990 | I81: {=IF(OR(H81=0, H81=""), 0, 1 - ((((XLOOKUP($A81, 'datos de inventario'!$A:$A, 'datos de inventario'!$D:$D, 0) * 'datos de inventario'!$K$2) + (XLOOKUP($A81, 'datos de inventario'!$A:$A, 'datos de inventario'!$F:$F, 0) * 'datos de inventario'!$K$3 * 'datos de inventario'!$K$4)) * 1.19 + (H81 * 0.15) + XLOOKUP(MAX($Z81, (XLOOKUP($A81, 'datos de inventario'!$A:$A, 'datos de inventario'!$F:$F, 0) * 1000000 / 4000)) + 0.1, Tarifas!$A$2:$A$33, IF(H81 <= 9989, Tarifas!$B$2:$B$33, IF(H81 <= 19989, Tarifas!$C$2:$C$33, Tarifas!$D$2:$D$33)), "Peso excedido", 1)) / H81))} -> 0.41354564 | J81: 15990 | K81: {=IF(OR(J81=0, J81=""), 0, 1 - ((((XLOOKUP($A81, 'datos de inventario'!$A:$A, 'datos de inventario'!$D:$D, 0) * 'datos de inventario'!$K$2) + (XLOOKUP($A81, 'datos de inventario'!$A:$A, 'datos de inventario'!$F:$F, 0) * 'datos de inventario'!$K$3 * 'datos de inventario'!$K$4)) * 1.19 + (J81 * 0.15) + XLOOKUP(MAX($Z81, (XLOOKUP($A81, 'datos de inventario'!$A:$A, 'datos de inventario'!$F:$F, 0) * 1000000 / 4000)) + 0.1, Tarifas!$A$2:$A$33, IF(J81 <= 9989, Tarifas!$B$2:$B$33, IF(J81 <= 19989, Tarifas!$C$2:$C$33, Tarifas!$D$2:$D$33)), "Peso excedido", 1)) / J81))} -> 0.35895472 | L81: 13990 | M81: {=IF(OR(L81=0, L81=""), 0, 1 - ((((XLOOKUP($A81, 'datos de inventario'!$A:$A, 'datos de inventario'!$D:$D, 0) * 'datos de inventario'!$K$2) + (XLOOKUP($A81, 'datos de inventario'!$A:$A, 'datos de inventario'!$F:$F, 0) * 'datos de inventario'!$K$3 * 'datos de inventario'!$K$4)) * 1.19 + (L81 * 0.15) + XLOOKUP(MAX($Z81, (XLOOKUP($A81, 'datos de inventario'!$A:$A, 'datos de inventario'!$F:$F, 0) * 1000000 / 4000)) + 0.1, Tarifas!$A$2:$A$33, IF(L81 <= 9989, Tarifas!$B$2:$B$33, IF(L81 <= 19989, Tarifas!$C$2:$C$33, Tarifas!$D$2:$D$33)), "Peso excedido", 1)) / L81))} -> 0.28875525 | N81: Hogar y MueblesOrganización para el HogarCajas | P81: 3.33 | Q81: =P81*4.3 -> 14.319 | R81: 10 | S81: =R81*4.3 -> 43 | T81: 46082 | U81: =1-(J81/H81) -> 0.11117287 | V81: =1-(L81/J81) -> 0.12507817 | AB81: =W81*X81*Y81/1000000 -> 0
A82: CAJAORGA008 | B82: Set x 4 Bolsas Organizadoras Ropa Plegable Asa Almacenamiento | C82: Cajas Organizadoras Plegable Homely Almacenamiento Asa Set 4 | D82: =LEN(C82) -> 60 | E82: Cajas Organizadoras Plegable Homely Almacenamiento Closet Ropa Accesorios Asa Set 4 | F82: Cajas Organizadoras Plegable Homely Almacenamiento Asa Set 4 | G82: =LEN(F82) -> 60 | H82: 10990 | I82: {=IF(OR(H82=0, H82=""), 0, 1 - ((((XLOOKUP($A82, 'datos de inventario'!$A:$A, 'datos de inventario'!$D:$D, 0) * 'datos de inventario'!$K$2) + (XLOOKUP($A82, 'datos de inventario'!$A:$A, 'datos de inventario'!$F:$F, 0) * 'datos de inventario'!$K$3 * 'datos de inventario'!$K$4)) * 1.19 + (H82 * 0.15) + XLOOKUP(MAX($Z82, (XLOOKUP($A82, 'datos de inventario'!$A:$A, 'datos de inventario'!$F:$F, 0) * 1000000 / 4000)) + 0.1, Tarifas!$A$2:$A$33, IF(H82 <= 9989, Tarifas!$B$2:$B$33, IF(H82 <= 19989, Tarifas!$C$2:$C$33, Tarifas!$D$2:$D$33)), "Peso excedido", 1)) / H82))} -> 0.58199288 | J82: 9980 | K82: {=IF(OR(J82=0, J82=""), 0, 1 - ((((XLOOKUP($A82, 'datos de inventario'!$A:$A, 'datos de inventario'!$D:$D, 0) * 'datos de inventario'!$K$2) + (XLOOKUP($A82, 'datos de inventario'!$A:$A, 'datos de inventario'!$F:$F, 0) * 'datos de inventario'!$K$3 * 'datos de inventario'!$K$4)) * 1.19 + (J82 * 0.15) + XLOOKUP(MAX($Z82, (XLOOKUP($A82, 'datos de inventario'!$A:$A, 'datos de inventario'!$F:$F, 0) * 1000000 / 4000)) + 0.1, Tarifas!$A$2:$A$33, IF(J82 <= 9989, Tarifas!$B$2:$B$33, IF(J82 <= 19989, Tarifas!$C$2:$C$33, Tarifas!$D$2:$D$33)), "Peso excedido", 1)) / J82))} -> 0.575912 | L82: 8990 | M82: {=IF(OR(L82=0, L82=""), 0, 1 - ((((XLOOKUP($A82, 'datos de inventario'!$A:$A, 'datos de inventario'!$D:$D, 0) * 'datos de inventario'!$K$2) + (XLOOKUP($A82, 'datos de inventario'!$A:$A, 'datos de inventario'!$F:$F, 0) * 'datos de inventario'!$K$3 * 'datos de inventario'!$K$4)) * 1.19 + (L82 * 0.15) + XLOOKUP(MAX($Z82, (XLOOKUP($A82, 'datos de inventario'!$A:$A, 'datos de inventario'!$F:$F, 0) * 1000000 / 4000)) + 0.1, Tarifas!$A$2:$A$33, IF(L82 <= 9989, Tarifas!$B$2:$B$33, IF(L82 <= 19989, Tarifas!$C$2:$C$33, Tarifas!$D$2:$D$33)), "Peso excedido", 1)) / L82))} -> 0.54572878 | N82: Hogar y MueblesOrganización para el HogarCajas | P82: 2.4 | Q82: =P82*4.3 -> 10.32 | R82: 7 | S82: =R82*4.3 -> 30.1 | T82: 46082 | U82: =1-(J82/H82) -> 0.091901729 | V82: =1-(L82/J82) -> 0.099198397 | AB82: =W82*X82*Y82/1000000 -> 0
A83: CAJAORGA009 | B83: Set x 2 Bolsas Organizadoras Almacenamiento Bajo Cama 90 litros negro | C83: Bolsas Organizadoras Bajo Cama Homely Negro 90 Litros Set 2 | D83: =LEN(C83) -> 60 | E83: Bolsas Organizadoras Plegable Almacenamiento Bajo Cama Homely Color Negro 90 Litros Set x2 | F83: Bolsas Organizadoras Plegable Bajo Cama Homely Negro 90 Litros Set x2 | G83: =LEN(F83) -> 69 | H83: 10990 | I83: {=IF(OR(H83=0, H83=""), 0, 1 - ((((XLOOKUP($A83, 'datos de inventario'!$A:$A, 'datos de inventario'!$D:$D, 0) * 'datos de inventario'!$K$2) + (XLOOKUP($A83, 'datos de inventario'!$A:$A, 'datos de inventario'!$F:$F, 0) * 'datos de inventario'!$K$3 * 'datos de inventario'!$K$4)) * 1.19 + (H83 * 0.15) + XLOOKUP(MAX($Z83, (XLOOKUP($A83, 'datos de inventario'!$A:$A, 'datos de inventario'!$F:$F, 0) * 1000000 / 4000)) + 0.1, Tarifas!$A$2:$A$33, IF(H83 <= 9989, Tarifas!$B$2:$B$33, IF(H83 <= 19989, Tarifas!$C$2:$C$33, Tarifas!$D$2:$D$33)), "Peso excedido", 1)) / H83))} -> 0.43385737 | J83: 9990 | K83: {=IF(OR(J83=0, J83=""), 0, 1 - ((((XLOOKUP($A83, 'datos de inventario'!$A:$A, 'datos de inventario'!$D:$D, 0) * 'datos de inventario'!$K$2) + (XLOOKUP($A83, 'datos de inventario'!$A:$A, 'datos de inventario'!$F:$F, 0) * 'datos de inventario'!$K$3 * 'datos de inventario'!$K$4)) * 1.19 + (J83 * 0.15) + XLOOKUP(MAX($Z83, (XLOOKUP($A83, 'datos de inventario'!$A:$A, 'datos de inventario'!$F:$F, 0) * 1000000 / 4000)) + 0.1, Tarifas!$A$2:$A$33, IF(J83 <= 9989, Tarifas!$B$2:$B$33, IF(J83 <= 19989, Tarifas!$C$2:$C$33, Tarifas!$D$2:$D$33)), "Peso excedido", 1)) / J83))} -> 0.39220145 | L83: 8990 | M83: {=IF(OR(L83=0, L83=""), 0, 1 - ((((XLOOKUP($A83, 'datos de inventario'!$A:$A, 'datos de inventario'!$D:$D, 0) * 'datos de inventario'!$K$2) + (XLOOKUP($A83, 'datos de inventario'!$A:$A, 'datos de inventario'!$F:$F, 0) * 'datos de inventario'!$K$3 * 'datos de inventario'!$K$4)) * 1.19 + (L83 * 0.15) + XLOOKUP(MAX($Z83, (XLOOKUP($A83, 'datos de inventario'!$A:$A, 'datos de inventario'!$F:$F, 0) * 1000000 / 4000)) + 0.1, Tarifas!$A$2:$A$33, IF(L83 <= 9989, Tarifas!$B$2:$B$33, IF(L83 <= 19989, Tarifas!$C$2:$C$33, Tarifas!$D$2:$D$33)), "Peso excedido", 1)) / L83))} -> 0.36463765 | N83: Hogar y MueblesOrganización para el HogarCajas | P83: 6.6 | Q83: =P83*4.3 -> 28.38 | R83: 20 | S83: =R83*4.3 -> 86 | T83: 46082 | U83: =1-(J83/H83) -> 0.090991811 | V83: =1-(L83/J83) -> 0.1001001 | AB83: =W83*X83*Y83/1000000 -> 0
A84: PISOCAUCHO002 | B84: Pack x2 piso de caucho gym 50x50x2cm | C84: Pack x2 Piso de Caucho Gym Overfit 50x50x2 Cm Alta Densidad | D84: =LEN(C84) -> 59 | E84: Pack x2 Piso de Caucho Para Gimnasio 50x50x2 Cm Overfit Gym De Alta Densidad Y Intensidad | F84: Pack x2 Piso de Caucho Gimnasio 50x50x2 Cm Overfit De Alta Densidad | G84: =LEN(F84) -> 67 | H84: 19980 | I84: {=IF(OR(H84=0, H84=""), 0, 1 - ((((XLOOKUP($A84, 'datos de inventario'!$A:$A, 'datos de inventario'!$D:$D, 0) * 'datos de inventario'!$K$2) + (XLOOKUP($A84, 'datos de inventario'!$A:$A, 'datos de inventario'!$F:$F, 0) * 'datos de inventario'!$K$3 * 'datos de inventario'!$K$4)) * 1.19 + (H84 * 0.15) + XLOOKUP(MAX($Z84, (XLOOKUP($A84, 'datos de inventario'!$A:$A, 'datos de inventario'!$F:$F, 0) * 1000000 / 4000)) + 0.1, Tarifas!$A$2:$A$33, IF(H84 <= 9989, Tarifas!$B$2:$B$33, IF(H84 <= 19989, Tarifas!$C$2:$C$33, Tarifas!$D$2:$D$33)), "Peso excedido", 1)) / H84))} -> 0.4241718 | J84: 18980 | K84: {=IF(OR(J84=0, J84=""), 0, 1 - ((((XLOOKUP($A84, 'datos de inventario'!$A:$A, 'datos de inventario'!$D:$D, 0) * 'datos de inventario'!$K$2) + (XLOOKUP($A84, 'datos de inventario'!$A:$A, 'datos de inventario'!$F:$F, 0) * 'datos de inventario'!$K$3 * 'datos de inventario'!$K$4)) * 1.19 + (J84 * 0.15) + XLOOKUP(MAX($Z84, (XLOOKUP($A84, 'datos de inventario'!$A:$A, 'datos de inventario'!$F:$F, 0) * 1000000 / 4000)) + 0.1, Tarifas!$A$2:$A$33, IF(J84 <= 9989, Tarifas!$B$2:$B$33, IF(J84 <= 19989, Tarifas!$C$2:$C$33, Tarifas!$D$2:$D$33)), "Peso excedido", 1)) / J84))} -> 0.40173617 | L84: 17980 | M84: {=IF(OR(L84=0, L84=""), 0, 1 - ((((XLOOKUP($A84, 'datos de inventario'!$A:$A, 'datos de inventario'!$D:$D, 0) * 'datos de inventario'!$K$2) + (XLOOKUP($A84, 'datos de inventario'!$A:$A, 'datos de inventario'!$F:$F, 0) * 'datos de inventario'!$K$3 * 'datos de inventario'!$K$4)) * 1.19 + (L84 * 0.15) + XLOOKUP(MAX($Z84, (XLOOKUP($A84, 'datos de inventario'!$A:$A, 'datos de inventario'!$F:$F, 0) * 1000000 / 4000)) + 0.1, Tarifas!$A$2:$A$33, IF(L84 <= 9989, Tarifas!$B$2:$B$33, IF(L84 <= 19989, Tarifas!$C$2:$C$33, Tarifas!$D$2:$D$33)), "Peso excedido", 1)) / L84))} -> 0.37680492 | N84: Deportes y FitnessFitness y MusculaciónOtros | P84: 3.33 | Q84: =P84*4.3 -> 14.319 | R84: 10 | S84: =R84*4.3 -> 43 | T84: 46082 | U84: =1-(J84/H84) -> 0.05005005 | V84: =1-(L84/J84) -> 0.052687039 | AB84: =W84*X84*Y84/1000000 -> 0
A85: CINTURONPESAS001 | B85: Cinturon levantamiento de pesas gym overfit | C85: Cinturon Levantamiento Pesas Gym Overfit Lumbar Crossfit | D85: =LEN(C85) -> 56 | E85: Cinturon Levantamiento De Pesas Gym Overfit Lumbar Crossfit Ajustable Negro | F85: Cinturon Levantamiento De Pesas Gym Overfit Lumbar Crossfit Ajustable Negro | G85: =LEN(F85) -> 75 | H85: 19980 | I85: {=IF(OR(H85=0, H85=""), 0, 1 - ((((XLOOKUP($A85, 'datos de inventario'!$A:$A, 'datos de inventario'!$D:$D, 0) * 'datos de inventario'!$K$2) + (XLOOKUP($A85, 'datos de inventario'!$A:$A, 'datos de inventario'!$F:$F, 0) * 'datos de inventario'!$K$3 * 'datos de inventario'!$K$4)) * 1.19 + (H85 * 0.15) + XLOOKUP(MAX($Z85, (XLOOKUP($A85, 'datos de inventario'!$A:$A, 'datos de inventario'!$F:$F, 0) * 1000000 / 4000)) + 0.1, Tarifas!$A$2:$A$33, IF(H85 <= 9989, Tarifas!$B$2:$B$33, IF(H85 <= 19989, Tarifas!$C$2:$C$33, Tarifas!$D$2:$D$33)), "Peso excedido", 1)) / H85))} -> 0.62220258 | J85: 14990 | K85: {=IF(OR(J85=0, J85=""), 0, 1 - ((((XLOOKUP($A85, 'datos de inventario'!$A:$A, 'datos de inventario'!$D:$D, 0) * 'datos de inventario'!$K$2) + (XLOOKUP($A85, 'datos de inventario'!$A:$A, 'datos de inventario'!$F:$F, 0) * 'datos de inventario'!$K$3 * 'datos de inventario'!$K$4)) * 1.19 + (J85 * 0.15) + XLOOKUP(MAX($Z85, (XLOOKUP($A85, 'datos de inventario'!$A:$A, 'datos de inventario'!$F:$F, 0) * 1000000 / 4000)) + 0.1, Tarifas!$A$2:$A$33, IF(J85 <= 9989, Tarifas!$B$2:$B$33, IF(J85 <= 19989, Tarifas!$C$2:$C$33, Tarifas!$D$2:$D$33)), "Peso excedido", 1)) / J85))} -> 0.54637141 | L85: 9990 | M85: {=IF(OR(L85=0, L85=""), 0, 1 - ((((XLOOKUP($A85, 'datos de inventario'!$A:$A, 'datos de inventario'!$D:$D, 0) * 'datos de inventario'!$K$2) + (XLOOKUP($A85, 'datos de inventario'!$A:$A, 'datos de inventario'!$F:$F, 0) * 'datos de inventario'!$K$3 * 'datos de inventario'!$K$4)) * 1.19 + (L85 * 0.15) + XLOOKUP(MAX($Z85, (XLOOKUP($A85, 'datos de inventario'!$A:$A, 'datos de inventario'!$F:$F, 0) * 1000000 / 4000)) + 0.1, Tarifas!$A$2:$A$33, IF(L85 <= 9989, Tarifas!$B$2:$B$33, IF(L85 <= 19989, Tarifas!$C$2:$C$33, Tarifas!$D$2:$D$33)), "Peso excedido", 1)) / L85))} -> 0.39440516 | N85: Deportes y FitnessFitness y MusculaciónFuncional, otros | P85: 6 | Q85: =P85*4.3 -> 25.8 | R85: 18 | S85: =R85*4.3 -> 77.4 | T85: 46082 | U85: =1-(J85/H85) -> 0.24974975 | V85: =1-(L85/J85) -> 0.3335557 | AB85: =W85*X85*Y85/1000000 -> 0
A86: PESARUSAKET12KG | B86: Pesa Rusa Kettlebell 12 kg PVC cemento | C86: Pesa Rusa Kettlebell 12kg Overfit Entrenamiento PVC Cemento | D86: =LEN(C86) -> 59 | E86: Pesa Rusa Kettlebell 12 kg Overfit Entrenamiento Gym Crossfit PVC Cemento | F86: Pesa Rusa Kettlebell 12 kg Overfit Entrenamiento Gym PVC Cemento | G86: =LEN(F86) -> 65 | H86: 16990 | I86: {=IF(OR(H86=0, H86=""), 0, 1 - ((((XLOOKUP($A86, 'datos de inventario'!$A:$A, 'datos de inventario'!$D:$D, 0) * 'datos de inventario'!$K$2) + (XLOOKUP($A86, 'datos de inventario'!$A:$A, 'datos de inventario'!$F:$F, 0) * 'datos de inventario'!$K$3 * 'datos de inventario'!$K$4)) * 1.19 + (H86 * 0.15) + XLOOKUP(MAX($Z86, (XLOOKUP($A86, 'datos de inventario'!$A:$A, 'datos de inventario'!$F:$F, 0) * 1000000 / 4000)) + 0.1, Tarifas!$A$2:$A$33, IF(H86 <= 9989, Tarifas!$B$2:$B$33, IF(H86 <= 19989, Tarifas!$C$2:$C$33, Tarifas!$D$2:$D$33)), "Peso excedido", 1)) / H86))} -> 0.44757515 | J86: 14990 | K86: {=IF(OR(J86=0, J86=""), 0, 1 - ((((XLOOKUP($A86, 'datos de inventario'!$A:$A, 'datos de inventario'!$D:$D, 0) * 'datos de inventario'!$K$2) + (XLOOKUP($A86, 'datos de inventario'!$A:$A, 'datos de inventario'!$F:$F, 0) * 'datos de inventario'!$K$3 * 'datos de inventario'!$K$4)) * 1.19 + (J86 * 0.15) + XLOOKUP(MAX($Z86, (XLOOKUP($A86, 'datos de inventario'!$A:$A, 'datos de inventario'!$F:$F, 0) * 1000000 / 4000)) + 0.1, Tarifas!$A$2:$A$33, IF(J86 <= 9989, Tarifas!$B$2:$B$33, IF(J86 <= 19989, Tarifas!$C$2:$C$33, Tarifas!$D$2:$D$33)), "Peso excedido", 1)) / J86))} -> 0.39388271 | L86: 12990 | M86: {=IF(OR(L86=0, L86=""), 0, 1 - ((((XLOOKUP($A86, 'datos de inventario'!$A:$A, 'datos de inventario'!$D:$D, 0) * 'datos de inventario'!$K$2) + (XLOOKUP($A86, 'datos de inventario'!$A:$A, 'datos de inventario'!$F:$F, 0) * 'datos de inventario'!$K$3 * 'datos de inventario'!$K$4)) * 1.19 + (L86 * 0.15) + XLOOKUP(MAX($Z86, (XLOOKUP($A86, 'datos de inventario'!$A:$A, 'datos de inventario'!$F:$F, 0) * 1000000 / 4000)) + 0.1, Tarifas!$A$2:$A$33, IF(L86 <= 9989, Tarifas!$B$2:$B$33, IF(L86 <= 19989, Tarifas!$C$2:$C$33, Tarifas!$D$2:$D$33)), "Peso excedido", 1)) / L86))} -> 0.32365679 | N86: Deportes y FitnessFitness y MusculaciónFuncional, pesas discos y barras,pesas rusas | P86: 5 | Q86: =P86*4.3 -> 21.5 | R86: 16 | S86: =R86*4.3 -> 68.8 | T86: 46082 | U86: =1-(J86/H86) -> 0.1177163 | V86: =1-(L86/J86) -> 0.13342228 | Z86: 12 | AB86: =W86*X86*Y86/1000000 -> 0
A87: PESARUSAKET20KG | B87: Pesa Rusa Kettlebell 20 kg PVC cemento | C87: Pesa Rusa Kettlebell 20kg Overfit Entrenamiento PVC Cemento | D87: =LEN(C87) -> 59 | E87: Pesa Rusa Kettlebell 20 kg Overfit Entrenamiento Gym Crossfit PVC Cemento | F87: Pesa Rusa Kettlebell 20 kg Overfit Entrenamiento Gym PVC Cemento | G87: =LEN(F87) -> 65 | H87: 32990 | I87: {=IF(OR(H87=0, H87=""), 0, 1 - ((((XLOOKUP($A87, 'datos de inventario'!$A:$A, 'datos de inventario'!$D:$D, 0) * 'datos de inventario'!$K$2) + (XLOOKUP($A87, 'datos de inventario'!$A:$A, 'datos de inventario'!$F:$F, 0) * 'datos de inventario'!$K$3 * 'datos de inventario'!$K$4)) * 1.19 + (H87 * 0.15) + XLOOKUP(MAX($Z87, (XLOOKUP($A87, 'datos de inventario'!$A:$A, 'datos de inventario'!$F:$F, 0) * 1000000 / 4000)) + 0.1, Tarifas!$A$2:$A$33, IF(H87 <= 9989, Tarifas!$B$2:$B$33, IF(H87 <= 19989, Tarifas!$C$2:$C$33, Tarifas!$D$2:$D$33)), "Peso excedido", 1)) / H87))} -> 0.31081218 | J87: 19980 | K87: {=IF(OR(J87=0, J87=""), 0, 1 - ((((XLOOKUP($A87, 'datos de inventario'!$A:$A, 'datos de inventario'!$D:$D, 0) * 'datos de inventario'!$K$2) + (XLOOKUP($A87, 'datos de inventario'!$A:$A, 'datos de inventario'!$F:$F, 0) * 'datos de inventario'!$K$3 * 'datos de inventario'!$K$4)) * 1.19 + (J87 * 0.15) + XLOOKUP(MAX($Z87, (XLOOKUP($A87, 'datos de inventario'!$A:$A, 'datos de inventario'!$F:$F, 0) * 1000000 / 4000)) + 0.1, Tarifas!$A$2:$A$33, IF(J87 <= 9989, Tarifas!$B$2:$B$33, IF(J87 <= 19989, Tarifas!$C$2:$C$33, Tarifas!$D$2:$D$33)), "Peso excedido", 1)) / J87))} -> 0.31557526 | L87: 18990 | M87: {=IF(OR(L87=0, L87=""), 0, 1 - ((((XLOOKUP($A87, 'datos de inventario'!$A:$A, 'datos de inventario'!$D:$D, 0) * 'datos de inventario'!$K$2) + (XLOOKUP($A87, 'datos de inventario'!$A:$A, 'datos de inventario'!$F:$F, 0) * 'datos de inventario'!$K$3 * 'datos de inventario'!$K$4)) * 1.19 + (L87 * 0.15) + XLOOKUP(MAX($Z87, (XLOOKUP($A87, 'datos de inventario'!$A:$A, 'datos de inventario'!$F:$F, 0) * 1000000 / 4000)) + 0.1, Tarifas!$A$2:$A$33, IF(L87 <= 9989, Tarifas!$B$2:$B$33, IF(L87 <= 19989, Tarifas!$C$2:$C$33, Tarifas!$D$2:$D$33)), "Peso excedido", 1)) / L87))} -> 0.28771426 | N87: Deportes y FitnessFitness y MusculaciónFuncional, pesas discos y barras,pesas rusas | P87: 4 | Q87: =P87*4.3 -> 17.2 | R87: 10 | S87: =R87*4.3 -> 43 | T87: 46082 | U87: =1-(J87/H87) -> 0.39436193 | V87: =1-(L87/J87) -> 0.04954955 | Z87: 20 | AB87: =W87*X87*Y87/1000000 -> 0
A88: TUPPERACERO004 | B88: Tupper individual acero inoxidable tapa cuerpo 850 ml | C88: Tupper Frasco 850ml Atelier Acero Inoxidable Individual | D88: =LEN(C88) -> 55 | E88: Tupper Frasco 850ml Atelier De Acero Inoxidable Individual Con Tapa Acero Inoxidable Hermetico Plateado | F88: Tupper Frasco 850ml Atelier De Acero Inoxidable Individual | G88: =LEN(F88) -> 60 | H88: 12990 | I88: {=IF(OR(H88=0, H88=""), 0, 1 - ((((XLOOKUP($A88, 'datos de inventario'!$A:$A, 'datos de inventario'!$D:$D, 0) * 'datos de inventario'!$K$2) + (XLOOKUP($A88, 'datos de inventario'!$A:$A, 'datos de inventario'!$F:$F, 0) * 'datos de inventario'!$K$3 * 'datos de inventario'!$K$4)) * 1.19 + (H88 * 0.15) + XLOOKUP(MAX($Z88, (XLOOKUP($A88, 'datos de inventario'!$A:$A, 'datos de inventario'!$F:$F, 0) * 1000000 / 4000)) + 0.1, Tarifas!$A$2:$A$33, IF(H88 <= 9989, Tarifas!$B$2:$B$33, IF(H88 <= 19989, Tarifas!$C$2:$C$33, Tarifas!$D$2:$D$33)), "Peso excedido", 1)) / H88))} -> 0.52302548 | J88: 9980 | K88: {=IF(OR(J88=0, J88=""), 0, 1 - ((((XLOOKUP($A88, 'datos de inventario'!$A:$A, 'datos de inventario'!$D:$D, 0) * 'datos de inventario'!$K$2) + (XLOOKUP($A88, 'datos de inventario'!$A:$A, 'datos de inventario'!$F:$F, 0) * 'datos de inventario'!$K$3 * 'datos de inventario'!$K$4)) * 1.19 + (J88 * 0.15) + XLOOKUP(MAX($Z88, (XLOOKUP($A88, 'datos de inventario'!$A:$A, 'datos de inventario'!$F:$F, 0) * 1000000 / 4000)) + 0.1, Tarifas!$A$2:$A$33, IF(J88 <= 9989, Tarifas!$B$2:$B$33, IF(J88 <= 19989, Tarifas!$C$2:$C$33, Tarifas!$D$2:$D$33)), "Peso excedido", 1)) / J88))} -> 0.445451 | L88: 7990 | M88: {=IF(OR(L88=0, L88=""), 0, 1 - ((((XLOOKUP($A88, 'datos de inventario'!$A:$A, 'datos de inventario'!$D:$D, 0) * 'datos de inventario'!$K$2) + (XLOOKUP($A88, 'datos de inventario'!$A:$A, 'datos de inventario'!$F:$F, 0) * 'datos de inventario'!$K$3 * 'datos de inventario'!$K$4)) * 1.19 + (L88 * 0.15) + XLOOKUP(MAX($Z88, (XLOOKUP($A88, 'datos de inventario'!$A:$A, 'datos de inventario'!$F:$F, 0) * 1000000 / 4000)) + 0.1, Tarifas!$A$2:$A$33, IF(L88 <= 9989, Tarifas!$B$2:$B$33, IF(L88 <= 19989, Tarifas!$C$2:$C$33, Tarifas!$D$2:$D$33)), "Peso excedido", 1)) / L88))} -> 0.34469349 | N88: Hogar y MueblesCocina y MenajeAlmacenamiento y OrganizaciónFrascos y Contenedores | P88: 8 | Q88: =P88*4.3 -> 34.4 | R88: 25 | S88: =R88*4.3 -> 107.5 | T88: 46082 | U88: =1-(J88/H88) -> 0.23171671 | V88: =1-(L88/J88) -> 0.1993988 | AB88: =W88*X88*Y88/1000000 -> 0
A89: TUPPERACERO005 | B89: Tupper individual acero inoxidable tapa plastico 1350 ml | C89: Tupper Frasco 1350ml Atelier Acero Inoxidable Individual | D89: =LEN(C89) -> 56 | E89: Tupper Frasco 1350ml Atelier Acero Inoxidable Individual Con tapa De Plastico Hermetico Plateado | F89: Tupper Frasco 1350ml Atelier Acero Inoxidable Individual | G89: =LEN(F89) -> 57 | H89: 14990 | I89: {=IF(OR(H89=0, H89=""), 0, 1 - ((((XLOOKUP($A89, 'datos de inventario'!$A:$A, 'datos de inventario'!$D:$D, 0) * 'datos de inventario'!$K$2) + (XLOOKUP($A89, 'datos de inventario'!$A:$A, 'datos de inventario'!$F:$F, 0) * 'datos de inventario'!$K$3 * 'datos de inventario'!$K$4)) * 1.19 + (H89 * 0.15) + XLOOKUP(MAX($Z89, (XLOOKUP($A89, 'datos de inventario'!$A:$A, 'datos de inventario'!$F:$F, 0) * 1000000 / 4000)) + 0.1, Tarifas!$A$2:$A$33, IF(H89 <= 9989, Tarifas!$B$2:$B$33, IF(H89 <= 19989, Tarifas!$C$2:$C$33, Tarifas!$D$2:$D$33)), "Peso excedido", 1)) / H89))} -> 0.5263244 | J89: 11990 | K89: {=IF(OR(J89=0, J89=""), 0, 1 - ((((XLOOKUP($A89, 'datos de inventario'!$A:$A, 'datos de inventario'!$D:$D, 0) * 'datos de inventario'!$K$2) + (XLOOKUP($A89, 'datos de inventario'!$A:$A, 'datos de inventario'!$F:$F, 0) * 'datos de inventario'!$K$3 * 'datos de inventario'!$K$4)) * 1.19 + (J89 * 0.15) + XLOOKUP(MAX($Z89, (XLOOKUP($A89, 'datos de inventario'!$A:$A, 'datos de inventario'!$F:$F, 0) * 1000000 / 4000)) + 0.1, Tarifas!$A$2:$A$33, IF(J89 <= 9989, Tarifas!$B$2:$B$33, IF(J89 <= 19989, Tarifas!$C$2:$C$33, Tarifas!$D$2:$D$33)), "Peso excedido", 1)) / J89))} -> 0.44533801 | L89: 9980 | M89: {=IF(OR(L89=0, L89=""), 0, 1 - ((((XLOOKUP($A89, 'datos de inventario'!$A:$A, 'datos de inventario'!$D:$D, 0) * 'datos de inventario'!$K$2) + (XLOOKUP($A89, 'datos de inventario'!$A:$A, 'datos de inventario'!$F:$F, 0) * 'datos de inventario'!$K$3 * 'datos de inventario'!$K$4)) * 1.19 + (L89 * 0.15) + XLOOKUP(MAX($Z89, (XLOOKUP($A89, 'datos de inventario'!$A:$A, 'datos de inventario'!$F:$F, 0) * 1000000 / 4000)) + 0.1, Tarifas!$A$2:$A$33, IF(L89 <= 9989, Tarifas!$B$2:$B$33, IF(L89 <= 19989, Tarifas!$C$2:$C$33, Tarifas!$D$2:$D$33)), "Peso excedido", 1)) / L89))} -> 0.38488004 | N89: Hogar y MueblesCocina y MenajeAlmacenamiento y OrganizaciónFrascos y Contenedores | P89: 8 | Q89: =P89*4.3 -> 34.4 | R89: 25 | S89: =R89*4.3 -> 107.5 | T89: 46082 | U89: =1-(J89/H89) -> 0.20013342 | V89: =1-(L89/J89) -> 0.1676397 | AB89: =W89*X89*Y89/1000000 -> 0
A90: AREGAT004LIM | B90: Arena Para Gato 20 Kilos Duke Bentonita Aglutinante Aroma Limon | C90: Arena Para Gato 20 Kg Duke Bentonita Aglutinante Aroma Limon | D90: =LEN(C90) -> 60 | E90: Arena Para Gato 20 Kilos Duke Bentonita Arena Sanitaria 20kg Aglutinante Absorbente Aroma Limon | F90: Arena Gato 20Kg Duke Bentonita Arena Sanitaria Aglutinante Aroma Limon | G90: =LEN(F90) -> 70 | H90: 18990 | I90: {=IF(OR(H90=0, H90=""), 0, 1 - ((((XLOOKUP($A90, 'datos de inventario'!$A:$A, 'datos de inventario'!$D:$D, 0) * 'datos de inventario'!$K$2) + (XLOOKUP($A90, 'datos de inventario'!$A:$A, 'datos de inventario'!$F:$F, 0) * 'datos de inventario'!$K$3 * 'datos de inventario'!$K$4)) * 1.19 + (H90 * 0.15) + XLOOKUP(MAX($Z90, (XLOOKUP($A90, 'datos de inventario'!$A:$A, 'datos de inventario'!$F:$F, 0) * 1000000 / 4000)) + 0.1, Tarifas!$A$2:$A$33, IF(H90 <= 9989, Tarifas!$B$2:$B$33, IF(H90 <= 19989, Tarifas!$C$2:$C$33, Tarifas!$D$2:$D$33)), "Peso excedido", 1)) / H90))} -> 0.37625777 | J90: 15990 | K90: {=IF(OR(J90=0, J90=""), 0, 1 - ((((XLOOKUP($A90, 'datos de inventario'!$A:$A, 'datos de inventario'!$D:$D, 0) * 'datos de inventario'!$K$2) + (XLOOKUP($A90, 'datos de inventario'!$A:$A, 'datos de inventario'!$F:$F, 0) * 'datos de inventario'!$K$3 * 'datos de inventario'!$K$4)) * 1.19 + (J90 * 0.15) + XLOOKUP(MAX($Z90, (XLOOKUP($A90, 'datos de inventario'!$A:$A, 'datos de inventario'!$F:$F, 0) * 1000000 / 4000)) + 0.1, Tarifas!$A$2:$A$33, IF(J90 <= 9989, Tarifas!$B$2:$B$33, IF(J90 <= 19989, Tarifas!$C$2:$C$33, Tarifas!$D$2:$D$33)), "Peso excedido", 1)) / J90))} -> 0.28737555 | L90: 13990 | M90: {=IF(OR(L90=0, L90=""), 0, 1 - ((((XLOOKUP($A90, 'datos de inventario'!$A:$A, 'datos de inventario'!$D:$D, 0) * 'datos de inventario'!$K$2) + (XLOOKUP($A90, 'datos de inventario'!$A:$A, 'datos de inventario'!$F:$F, 0) * 'datos de inventario'!$K$3 * 'datos de inventario'!$K$4)) * 1.19 + (L90 * 0.15) + XLOOKUP(MAX($Z90, (XLOOKUP($A90, 'datos de inventario'!$A:$A, 'datos de inventario'!$F:$F, 0) * 1000000 / 4000)) + 0.1, Tarifas!$A$2:$A$33, IF(L90 <= 9989, Tarifas!$B$2:$B$33, IF(L90 <= 19989, Tarifas!$C$2:$C$33, Tarifas!$D$2:$D$33)), "Peso excedido", 1)) / L90))} -> 0.20694317 | N90: MascotasGatosEstética y CuidadoArtículos SanitariosArena SanitariaArena Gatos | P90: 40 | Q90: =P90*4.3 -> 172 | R90: 120 | S90: =R90*4.3 -> 516 | T90: 46082 | U90: =1-(J90/H90) -> 0.15797788 | V90: =1-(L90/J90) -> 0.12507817 | Z90: 19.8 | AB90: =W90*X90*Y90/1000000 -> 0
A91: AREGATCRIS001 | B91: Arena de gato de cristal 1,6 kg Duke Lavanda | C91: Arena Para Gato Cristal Duke Sanitaria 1.6 Kg Aroma Lavanda | D91: =LEN(C91) -> 60 | E91: Arena Para Gato Cristales Sanitarios Duke 1.6 Kg Aroma Lavanda | F91: Arena Para Gato Cristales Sanitarios Duke 1.6 Kg Aroma Lavanda | G91: =LEN(F91) -> 64 | H91: 9980 | I91: {=IF(OR(H91=0, H91=""), 0, 1 - ((((XLOOKUP($A91, 'datos de inventario'!$A:$A, 'datos de inventario'!$D:$D, 0) * 'datos de inventario'!$K$2) + (XLOOKUP($A91, 'datos de inventario'!$A:$A, 'datos de inventario'!$F:$F, 0) * 'datos de inventario'!$K$3 * 'datos de inventario'!$K$4)) * 1.19 + (H91 * 0.15) + XLOOKUP(MAX($Z91, (XLOOKUP($A91, 'datos de inventario'!$A:$A, 'datos de inventario'!$F:$F, 0) * 1000000 / 4000)) + 0.1, Tarifas!$A$2:$A$33, IF(H91 <= 9989, Tarifas!$B$2:$B$33, IF(H91 <= 19989, Tarifas!$C$2:$C$33, Tarifas!$D$2:$D$33)), "Peso excedido", 1)) / H91))} -> 0.37248955 | J91: 7490 | K91: {=IF(OR(J91=0, J91=""), 0, 1 - ((((XLOOKUP($A91, 'datos de inventario'!$A:$A, 'datos de inventario'!$D:$D, 0) * 'datos de inventario'!$K$2) + (XLOOKUP($A91, 'datos de inventario'!$A:$A, 'datos de inventario'!$F:$F, 0) * 'datos de inventario'!$K$3 * 'datos de inventario'!$K$4)) * 1.19 + (J91 * 0.15) + XLOOKUP(MAX($Z90, (XLOOKUP($A91, 'datos de inventario'!$A:$A, 'datos de inventario'!$F:$F, 0) * 1000000 / 4000)) + 0.1, Tarifas!$A$2:$A$33, IF(J91 <= 9989, Tarifas!$B$2:$B$33, IF(J91 <= 19989, Tarifas!$C$2:$C$33, Tarifas!$D$2:$D$33)), "Peso excedido", 1)) / J91))} -> 0.07756285 | L91: 5990 | M91: {=IF(OR(L91=0, L91=""), 0, 1 - ((((XLOOKUP($A91, 'datos de inventario'!$A:$A, 'datos de inventario'!$D:$D, 0) * 'datos de inventario'!$K$2) + (XLOOKUP($A91, 'datos de inventario'!$A:$A, 'datos de inventario'!$F:$F, 0) * 'datos de inventario'!$K$3 * 'datos de inventario'!$K$4)) * 1.19 + (L91 * 0.15) + XLOOKUP(MAX($Z90, (XLOOKUP($A91, 'datos de inventario'!$A:$A, 'datos de inventario'!$F:$F, 0) * 1000000 / 4000)) + 0.1, Tarifas!$A$2:$A$33, IF(L91 <= 9989, Tarifas!$B$2:$B$33, IF(L91 <= 19989, Tarifas!$C$2:$C$33, Tarifas!$D$2:$D$33)), "Peso excedido", 1)) / L91))} -> -0.11586882 | N91: MascotasGatosEstética y CuidadoArtículos SanitariosArena SanitariaArena Gatos | P91: 13.3 | Q91: =P91*4.3 -> 57.19 | R91: 40 | S91: =R91*4.3 -> 172 | T91: 46082 | U91: =1-(J91/H91) -> 0.249499 | V91: =1-(L91/J91) -> 0.20026702 | Z91: 1.6 | AB91: =W91*X91*Y91/1000000 -> 0
A92: SABPERRO006PACK30 | B92: Sabanillas Para Perro 60x60 Duke Pack bolsa 30 Unidades | C92: Sabanillas Para Perros 60 x 60 Duke Training Pad pack 30 U | D92: =LEN(C92) -> 58 | E92: Sabanillas Para Perros 60 x 60 Duke Training Pad pack 30 Unidades Aroma Lavanda | H92: 9980 | I92: {=IF(OR(H92=0, H92=""), 0, 1 - ((((XLOOKUP($A92, 'datos de inventario'!$A:$A, 'datos de inventario'!$D:$D, 0) * 'datos de inventario'!$K$2) + (XLOOKUP($A92, 'datos de inventario'!$A:$A, 'datos de inventario'!$F:$F, 0) * 'datos de inventario'!$K$3 * 'datos de inventario'!$K$4)) * 1.19 + (H92 * 0.15) + XLOOKUP(MAX($Z92, (XLOOKUP($A92, 'datos de inventario'!$A:$A, 'datos de inventario'!$F:$F, 0) * 1000000 / 4000)) + 0.1, Tarifas!$A$2:$A$33, IF(H92 <= 9989, Tarifas!$B$2:$B$33, IF(H92 <= 19989, Tarifas!$C$2:$C$33, Tarifas!$D$2:$D$33)), "Peso excedido", 1)) / H92))} -> 0.54521245 | J92: 6990 | K92: {=IF(OR(J92=0, J92=""), 0, 1 - ((((XLOOKUP($A92, 'datos de inventario'!$A:$A, 'datos de inventario'!$D:$D, 0) * 'datos de inventario'!$K$2) + (XLOOKUP($A92, 'datos de inventario'!$A:$A, 'datos de inventario'!$F:$F, 0) * 'datos de inventario'!$K$3 * 'datos de inventario'!$K$4)) * 1.19 + (J92 * 0.15) + XLOOKUP(MAX($Z91, (XLOOKUP($A92, 'datos de inventario'!$A:$A, 'datos de inventario'!$F:$F, 0) * 1000000 / 4000)) + 0.1, Tarifas!$A$2:$A$33, IF(J92 <= 9989, Tarifas!$B$2:$B$33, IF(J92 <= 19989, Tarifas!$C$2:$C$33, Tarifas!$D$2:$D$33)), "Peso excedido", 1)) / J92))} -> 0.41483838 | L92: 4990 | M92: {=IF(OR(L92=0, L92=""), 0, 1 - ((((XLOOKUP($A92, 'datos de inventario'!$A:$A, 'datos de inventario'!$D:$D, 0) * 'datos de inventario'!$K$2) + (XLOOKUP($A92, 'datos de inventario'!$A:$A, 'datos de inventario'!$F:$F, 0) * 'datos de inventario'!$K$3 * 'datos de inventario'!$K$4)) * 1.19 + (L92 * 0.15) + XLOOKUP(MAX($Z91, (XLOOKUP($A92, 'datos de inventario'!$A:$A, 'datos de inventario'!$F:$F, 0) * 1000000 / 4000)) + 0.1, Tarifas!$A$2:$A$33, IF(L92 <= 9989, Tarifas!$B$2:$B$33, IF(L92 <= 19989, Tarifas!$C$2:$C$33, Tarifas!$D$2:$D$33)), "Peso excedido", 1)) / L92))} -> 0.2404249 | N92: MascotasPerrosAdiestramientoBaños Sanitarios | P92: 25 | Q92: =P92*4.3 -> 107.5 | R92: 100 | S92: =R92*4.3 -> 430 | T92: 46082 | U92: =1-(J92/H92) -> 0.2995992 | V92: =1-(L92/J92) -> 0.28612303 | AB92: =W92*X92*Y92/1000000 -> 0
A93: SABPERRO007PACK30 | B93: Sabanillas Para Perro 60x90 Duke Pack bolsa 30 Unidades | C93: Sabanillas Para Perros 90 x 60 Duke Training Pad pack 30 U | D93: =LEN(C93) -> 58 | E93: Sabanillas Para Perros 90 x 60 Duke Training Pad pack 30 Unidades Aroma Lavanda | H93: 12990 | I93: {=IF(OR(H93=0, H93=""), 0, 1 - ((((XLOOKUP($A93, 'datos de inventario'!$A:$A, 'datos de inventario'!$D:$D, 0) * 'datos de inventario'!$K$2) + (XLOOKUP($A93, 'datos de inventario'!$A:$A, 'datos de inventario'!$F:$F, 0) * 'datos de inventario'!$K$3 * 'datos de inventario'!$K$4)) * 1.19 + (H93 * 0.15) + XLOOKUP(MAX($Z93, (XLOOKUP($A93, 'datos de inventario'!$A:$A, 'datos de inventario'!$F:$F, 0) * 1000000 / 4000)) + 0.1, Tarifas!$A$2:$A$33, IF(H93 <= 9989, Tarifas!$B$2:$B$33, IF(H93 <= 19989, Tarifas!$C$2:$C$33, Tarifas!$D$2:$D$33)), "Peso excedido", 1)) / H93))} -> 0.53228926 | J93: 7990 | K93: {=IF(OR(J93=0, J93=""), 0, 1 - ((((XLOOKUP($A93, 'datos de inventario'!$A:$A, 'datos de inventario'!$D:$D, 0) * 'datos de inventario'!$K$2) + (XLOOKUP($A93, 'datos de inventario'!$A:$A, 'datos de inventario'!$F:$F, 0) * 'datos de inventario'!$K$3 * 'datos de inventario'!$K$4)) * 1.19 + (J93 * 0.15) + XLOOKUP(MAX($Z92, (XLOOKUP($A93, 'datos de inventario'!$A:$A, 'datos de inventario'!$F:$F, 0) * 1000000 / 4000)) + 0.1, Tarifas!$A$2:$A$33, IF(J93 <= 9989, Tarifas!$B$2:$B$33, IF(J93 <= 19989, Tarifas!$C$2:$C$33, Tarifas!$D$2:$D$33)), "Peso excedido", 1)) / J93))} -> 0.35850282 | L93: 5990 | M93: {=IF(OR(L93=0, L93=""), 0, 1 - ((((XLOOKUP($A93, 'datos de inventario'!$A:$A, 'datos de inventario'!$D:$D, 0) * 'datos de inventario'!$K$2) + (XLOOKUP($A93, 'datos de inventario'!$A:$A, 'datos de inventario'!$F:$F, 0) * 'datos de inventario'!$K$3 * 'datos de inventario'!$K$4)) * 1.19 + (L93 * 0.15) + XLOOKUP(MAX($Z92, (XLOOKUP($A93, 'datos de inventario'!$A:$A, 'datos de inventario'!$F:$F, 0) * 1000000 / 4000)) + 0.1, Tarifas!$A$2:$A$33, IF(L93 <= 9989, Tarifas!$B$2:$B$33, IF(L93 <= 19989, Tarifas!$C$2:$C$33, Tarifas!$D$2:$D$33)), "Peso excedido", 1)) / L93))} -> 0.19439691 | N93: MascotasPerrosAdiestramientoBaños Sanitarios | P93: 17.5 | Q93: =P93*4.3 -> 75.25 | R93: 70 | S93: =R93*4.3 -> 301 | T93: 46082 | U93: =1-(J93/H93) -> 0.38491147 | V93: =1-(L93/J93) -> 0.25031289 | AB93: =W93*X93*Y93/1000000 -> 0
A94: TETERA2500ML001 | B94: Tetera 2.5 Litros Acero Inoxidable granito | C94: Tetera Acero Inoxidable 2.5 Litros Te Atelier Color Granito | D94: =LEN(C94) -> 60 | E94: Tetera Acero Inoxidable 2.5 Litros Para Te Infuciones Atelier Color Granito | J94: 18990 | K94: {=IF(OR(J94=0, J94=""), 0, 1 - ((((XLOOKUP($A94, 'datos de inventario'!$A:$A, 'datos de inventario'!$D:$D, 0) * 'datos de inventario'!$K$2) + (XLOOKUP($A94, 'datos de inventario'!$A:$A, 'datos de inventario'!$F:$F, 0) * 'datos de inventario'!$K$3 * 'datos de inventario'!$K$4)) * 1.19 + (J94 * 0.15) + XLOOKUP(MAX($Z93, (XLOOKUP($A94, 'datos de inventario'!$A:$A, 'datos de inventario'!$F:$F, 0) * 1000000 / 4000)) + 0.1, Tarifas!$A$2:$A$33, IF(J94 <= 9989, Tarifas!$B$2:$B$33, IF(J94 <= 19989, Tarifas!$C$2:$C$33, Tarifas!$D$2:$D$33)), "Peso excedido", 1)) / J94))} -> 0.40973949 | T94: 46113 | U94: =1-(J94/H94) -> #DIV/0! | V94: =1-(L94/J94) -> 1 | W94: 19 | X94: 19 | Y94: 21.5 | Z94: 0.59 | AB94: =W94*X94*Y94/1000000 -> 0.0077615
A95: CAFETERAITA001 | B95: Cafetera italiana 4 tazas 300 ml color crema | C95: Cafetera italiana Espresso Atelier 300ml Acero Inoxidable | D95: =LEN(C95) -> 57 | E95: Cafetera italiana Espresso Atelier 300ml De Acero Inoxidable Color Crema | T95: 46113 | U95: =1-(J95/H95) -> #DIV/0! | V95: =1-(L95/J95) -> #DIV/0! | AB95: =W95*X95*Y95/1000000 -> 0
A96: GUIELELP002NARAN | B96: Guitarra Eléctrica LP Ibrah + Amplif + Accesorios Naranja Sunburst | T96: 46113 | U96: =1-(J96/H96) -> #DIV/0! | V96: =1-(L96/J96) -> #DIV/0! | AB96: =W96*X96*Y96/1000000 -> 0
A97: GUIELECTROACUS002CAFE | B97: Guitarra Electroacustica Ibrah 41 Pulgadas Cafe + accesorios | T97: 46113 | U97: =1-(J97/H97) -> #DIV/0! | V97: =1-(L97/J97) -> #DIV/0! | AB97: =W97*X97*Y97/1000000 -> 0
A98: GUIELECNIN002NEG | B98: Guitarra Eléctrica Niño 30 pulgadas Negro Blanco + accesorios | T98: 46113 | U98: =1-(J98/H98) -> #DIV/0! | V98: =1-(L98/J98) -> #DIV/0! | AB98: =W98*X98*Y98/1000000 -> 0
A99: CAMZEKSOL001 | B99: Camara de seguridad panel Solar wifi 2.4G Zeker 4MP | U99: =1-(J99/H99) -> #DIV/0! | V99: =1-(L99/J99) -> #DIV/0! | AB99: =W99*X99*Y99/1000000 -> 0
U100: =1-(J100/H100) -> #DIV/0! | V100: =1-(L100/J100) -> #DIV/0! | AB100: =W100*X100*Y100/1000000 -> 0
U101: =1-(J101/H101) -> #DIV/0! | V101: =1-(L101/J101) -> #DIV/0! | AB101: =W101*X101*Y101/1000000 -> 0
...

Sheet Revisión velocidades
A1: SKU | B1: Producto | C1: Margen Marzo | D1: Gasto publicidad mes actual Acos | E1: Precio de venta calculado | F1: Velocidad inicial semanal | G1: Velocidad madura semanal | H1: Fehca de llegada | I1: Días de rotación | J1: =VLOOKUP($A$1,'Cruce APP Velocidad ultimas 5 s'!$A$1:$L$1,6,0) -> W13 | K1: =VLOOKUP($A$1,'Cruce APP Velocidad ultimas 5 s'!$A$1:$L$1,7,0) -> W14 | L1: =VLOOKUP($A$1,'Cruce APP Velocidad ultimas 5 s'!$A$1:$L$1,8,0) -> W15 | M1: =VLOOKUP($A$1,'Cruce APP Velocidad ultimas 5 s'!$A$1:$L$1,9,0) -> W16 | N1: =VLOOKUP($A$1,'Cruce APP Velocidad ultimas 5 s'!$A$1:$L$1,10,0) -> W17 | O1: stock | P1: Nota | Q1: Palancas | R1: Palancas | S1: Palancas | T1: Palancas
A2: TROTAELEC002 | B2: =VLOOKUP(A2,'Cruce APP Velocidad ultimas 5 s'!A:B,2,0) -> Trotadora 2 Hp Overfit Caminadora Electrica Plegable 12 Km/h | C2: =VLOOKUP(A2,'App dashboard año actual'!A:I,9,0) -> 33,7 | D2: =VLOOKUP(A2,'App dashboard año actual'!A:K,11,0)/VLOOKUP(A2,'App dashboard año actual'!A:N,3,0) -> 0.049486849 | E2: =IFERROR(VLOOKUP(A2,'App dashboard año actual'!A:E,3,0)/VLOOKUP(A2,'App dashboard año actual'!A:E,5,0),"Sin ventas") -> 200887.12 | F2: 1.2 | G2: 4.7 | H2: 46065 | I2: =TODAY()-H2 -> 68 | J2: =VLOOKUP(A2,'Cruce APP Velocidad ultimas 5 s'!A:H,6,0) -> 0 | K2: =VLOOKUP(A2,'Cruce APP Velocidad ultimas 5 s'!A:H,7,0) -> 0 | L2: =VLOOKUP(A2,'Cruce APP Velocidad ultimas 5 s'!A:H,8,0) -> 0 | M2: =VLOOKUP(A2,'Cruce APP Velocidad ultimas 5 s'!A:I,9,0) -> 0 | N2: =VLOOKUP(A2,'Cruce APP Velocidad ultimas 5 s'!A:J,10,0) -> 0 | P2: Listo
A3: TROTAELEC003 | B3: =VLOOKUP(A3,'Cruce APP Velocidad ultimas 5 s'!A:B,2,0) -> Trotadora 1.5 Hp Overfit Caminadora Electrica Plegable 8km/h | C3: =VLOOKUP(A3,'App dashboard año actual'!A:I,9,0) -> 31,84 | D3: =VLOOKUP(A3,'App dashboard año actual'!A:K,11,0)/VLOOKUP(A3,'App dashboard año actual'!A:N,3,0) -> 0.051539011 | E3: =IFERROR(VLOOKUP(A3,'App dashboard año actual'!A:E,3,0)/VLOOKUP(A3,'App dashboard año actual'!A:E,5,0),"Sin ventas") -> 152721.42 | F3: 1.2 | G3: 4.7 | H3: 46065 | I3: =TODAY()-H3 -> 68 | J3: =VLOOKUP(A3,'Cruce APP Velocidad ultimas 5 s'!A:H,6,0) -> 4 | K3: =VLOOKUP(A3,'Cruce APP Velocidad ultimas 5 s'!A:H,7,0) -> 10 | L3: =VLOOKUP(A3,'Cruce APP Velocidad ultimas 5 s'!A:H,8,0) -> 3 | M3: =VLOOKUP(A3,'Cruce APP Velocidad ultimas 5 s'!A:I,9,0) -> 4 | N3: =VLOOKUP(A3,'Cruce APP Velocidad ultimas 5 s'!A:J,10,0) -> 0 | P3: Listo
A4: FUNGUI002 | B4: =VLOOKUP(A4,'Cruce APP Velocidad ultimas 5 s'!A:B,2,0) -> Funda Para Guitarra 41 Pulgadas Ibrah Bolso De Transporte | C4: =VLOOKUP(A4,'App dashboard año actual'!A:I,9,0) -> 33,17 | D4: =VLOOKUP(A4,'App dashboard año actual'!A:K,11,0)/VLOOKUP(A4,'App dashboard año actual'!A:N,3,0) -> 0.048755039 | E4: =IFERROR(VLOOKUP(A4,'App dashboard año actual'!A:E,3,0)/VLOOKUP(A4,'App dashboard año actual'!A:E,5,0),"Sin ventas") -> 19952.766 | F4: 1.2 | G4: 4.7 | H4: 46071 | I4: =TODAY()-H4 -> 62 | J4: =VLOOKUP(A4,'Cruce APP Velocidad ultimas 5 s'!A:H,6,0) -> 18 | K4: =VLOOKUP(A4,'Cruce APP Velocidad ultimas 5 s'!A:H,7,0) -> 18 | L4: =VLOOKUP(A4,'Cruce APP Velocidad ultimas 5 s'!A:H,8,0) -> 38 | M4: =VLOOKUP(A4,'Cruce APP Velocidad ultimas 5 s'!A:I,9,0) -> 31 | N4: =VLOOKUP(A4,'Cruce APP Velocidad ultimas 5 s'!A:J,10,0) -> 2 | P4: Listo
A5: BANCOGYM001 | B5: =VLOOKUP(A5,'Cruce APP Velocidad ultimas 5 s'!A:B,2,0) -> Banco Reclinable Gym Multifuncional Overfit Press Ajustable | C5: =VLOOKUP(A5,'App dashboard año actual'!A:I,9,0) -> 45,36 | D5: =VLOOKUP(A5,'App dashboard año actual'!A:K,11,0)/VLOOKUP(A5,'App dashboard año actual'!A:N,3,0) -> 0.041474249 | E5: =IFERROR(VLOOKUP(A5,'App dashboard año actual'!A:E,3,0)/VLOOKUP(A5,'App dashboard año actual'!A:E,5,0),"Sin ventas") -> 94850.787 | F5: 1.2 | G5: 4.7 | H5: 46071 | I5: =TODAY()-H5 -> 62 | J5: =VLOOKUP(A5,'Cruce APP Velocidad ultimas 5 s'!A:H,6,0) -> 1 | K5: =VLOOKUP(A5,'Cruce APP Velocidad ultimas 5 s'!A:H,7,0) -> 15 | L5: =VLOOKUP(A5,'Cruce APP Velocidad ultimas 5 s'!A:H,8,0) -> 0 | M5: =VLOOKUP(A5,'Cruce APP Velocidad ultimas 5 s'!A:I,9,0) -> 3 | N5: =VLOOKUP(A5,'Cruce APP Velocidad ultimas 5 s'!A:J,10,0) -> 1 | P5: Listo
A6: GUIACU003 | B6: =VLOOKUP(A6,'Cruce APP Velocidad ultimas 5 s'!A:B,2,0) -> Guitarra Acustica Cutaway Ibrah Music 38 plgds + accesorios | C6: =VLOOKUP(A6,'App dashboard año actual'!A:I,9,0) -> 38,2 | D6: =VLOOKUP(A6,'App dashboard año actual'!A:K,11,0)/VLOOKUP(A6,'App dashboard año actual'!A:N,3,0) -> 0.057097127 | E6: =IFERROR(VLOOKUP(A6,'App dashboard año actual'!A:E,3,0)/VLOOKUP(A6,'App dashboard año actual'!A:E,5,0),"Sin ventas") -> 61012.202 | F6: 1.2 | G6: 4.7 | H6: 46071 | I6: =TODAY()-H6 -> 62 | J6: =VLOOKUP(A6,'Cruce APP Velocidad ultimas 5 s'!A:H,6,0) -> 31 | K6: =VLOOKUP(A6,'Cruce APP Velocidad ultimas 5 s'!A:H,7,0) -> 57 | L6: =VLOOKUP(A6,'Cruce APP Velocidad ultimas 5 s'!A:H,8,0) -> 45 | M6: =VLOOKUP(A6,'Cruce APP Velocidad ultimas 5 s'!A:I,9,0) -> 27 | N6: =VLOOKUP(A6,'Cruce APP Velocidad ultimas 5 s'!A:J,10,0) -> 1 | P6: Listo
A7: MONCURGAMER27 | B7: =VLOOKUP(A7,'Cruce APP Velocidad ultimas 5 s'!A:B,2,0) -> Monitor Gamer Curvo 27" Hosser Fhd 165Hz Gaming Freesync 1ms | C7: =VLOOKUP(A7,'App dashboard año actual'!A:I,9,0) -> 29,97 | D7: =VLOOKUP(A7,'App dashboard año actual'!A:K,11,0)/VLOOKUP(A7,'App dashboard año actual'!A:N,3,0) -> 0.031482226 | E7: =IFERROR(VLOOKUP(A7,'App dashboard año actual'!A:E,3,0)/VLOOKUP(A7,'App dashboard año actual'!A:E,5,0),"Sin ventas") -> 138104.79 | F7: 1.2 | G7: 4.7 | H7: 46071 | I7: =TODAY()-H7 -> 62 | J7: =VLOOKUP(A7,'Cruce APP Velocidad ultimas 5 s'!A:H,6,0) -> 4 | K7: =VLOOKUP(A7,'Cruce APP Velocidad ultimas 5 s'!A:H,7,0) -> 35 | L7: =VLOOKUP(A7,'Cruce APP Velocidad ultimas 5 s'!A:H,8,0) -> 7 | M7: =VLOOKUP(A7,'Cruce APP Velocidad ultimas 5 s'!A:I,9,0) -> 3 | N7: =VLOOKUP(A7,'Cruce APP Velocidad ultimas 5 s'!A:J,10,0) -> 0 | P7: Listo
A8: MONCURGAMER34 | B8: =VLOOKUP(A8,'Cruce APP Velocidad ultimas 5 s'!A:B,2,0) -> Monitor PC Gamer Curvo 34" Hosser FHD 165 Hz Gaming 1 ms | C8: =VLOOKUP(A8,'App dashboard año actual'!A:I,9,0) -> 37,02 | D8: =VLOOKUP(A8,'App dashboard año actual'!A:K,11,0)/VLOOKUP(A8,'App dashboard año actual'!A:N,3,0) -> 0.031977702 | E8: =IFERROR(VLOOKUP(A8,'App dashboard año actual'!A:E,3,0)/VLOOKUP(A8,'App dashboard año actual'!A:E,5,0),"Sin ventas") -> 277019.42 | F8: 1.2 | G8: 4.7 | H8: 46071 | I8: =TODAY()-H8 -> 62 | J8: =VLOOKUP(A8,'Cruce APP Velocidad ultimas 5 s'!A:H,6,0) -> 7 | K8: =VLOOKUP(A8,'Cruce APP Velocidad ultimas 5 s'!A:H,7,0) -> 7 | L8: =VLOOKUP(A8,'Cruce APP Velocidad ultimas 5 s'!A:H,8,0) -> 5 | M8: =VLOOKUP(A8,'Cruce APP Velocidad ultimas 5 s'!A:I,9,0) -> 0 | N8: =VLOOKUP(A8,'Cruce APP Velocidad ultimas 5 s'!A:J,10,0) -> 0 | P8: Listo
A9: BATERIAELE001 | B9: =VLOOKUP(A9,'Cruce APP Velocidad ultimas 5 s'!A:B,2,0) -> Bateria Electrica Ibrah Music | C9: =VLOOKUP(A9,'App dashboard año actual'!A:I,9,0) -> 40,36 | D9: =VLOOKUP(A9,'App dashboard año actual'!A:K,11,0)/VLOOKUP(A9,'App dashboard año actual'!A:N,3,0) -> 0.03232644 | E9: =IFERROR(VLOOKUP(A9,'App dashboard año actual'!A:E,3,0)/VLOOKUP(A9,'App dashboard año actual'!A:E,5,0),"Sin ventas") -> 391412.51 | F9: 1.2 | G9: 4.7 | H9: 46072 | I9: =TODAY()-H9 -> 61 | J9: =VLOOKUP(A9,'Cruce APP Velocidad ultimas 5 s'!A:H,6,0) -> 1 | K9: =VLOOKUP(A9,'Cruce APP Velocidad ultimas 5 s'!A:H,7,0) -> 18 | L9: =VLOOKUP(A9,'Cruce APP Velocidad ultimas 5 s'!A:H,8,0) -> 4 | M9: =VLOOKUP(A9,'Cruce APP Velocidad ultimas 5 s'!A:I,9,0) -> 7 | N9: =VLOOKUP(A9,'Cruce APP Velocidad ultimas 5 s'!A:J,10,0) -> 1 | P9: Listo
A10: GUIELEFV004NEG | B10: =VLOOKUP(A10,'Cruce APP Velocidad ultimas 5 s'!A:B,2,0) -> Guitarra Electrica Flying V 39" Ibrah Music Amplificador 20W | C10: =VLOOKUP(A10,'App dashboard año actual'!A:I,9,0) -> 30,22 | D10: =VLOOKUP(A10,'App dashboard año actual'!A:K,11,0)/VLOOKUP(A10,'App dashboard año actual'!A:N,3,0) -> 0.21495704 | E10: =IFERROR(VLOOKUP(A10,'App dashboard año actual'!A:E,3,0)/VLOOKUP(A10,'App dashboard año actual'!A:E,5,0),"Sin ventas") -> 229644.33 | F10: 1.2 | G10: 4.7 | H10: 46072 | I10: =TODAY()-H10 -> 61 | J10: =VLOOKUP(A10,'Cruce APP Velocidad ultimas 5 s'!A:H,6,0) -> 1 | K10: =VLOOKUP(A10,'Cruce APP Velocidad ultimas 5 s'!A:H,7,0) -> 0 | L10: =VLOOKUP(A10,'Cruce APP Velocidad ultimas 5 s'!A:H,8,0) -> 2 | M10: =VLOOKUP(A10,'Cruce APP Velocidad ultimas 5 s'!A:I,9,0) -> 1 | N10: =VLOOKUP(A10,'Cruce APP Velocidad ultimas 5 s'!A:J,10,0) -> 0 | P10: revisar en reunion de el miercoles con el equipo
A11: GUIELEBG005NEG | B11: =VLOOKUP(A11,'Cruce APP Velocidad ultimas 5 s'!A:B,2,0) -> Guitarra Electrica BG 39" Ibrah Music + Amplificador 20 W | C11: =VLOOKUP(A11,'App dashboard año actual'!A:I,9,0) -> 36,44 | D11: =VLOOKUP(A11,'App dashboard año actual'!A:K,11,0)/VLOOKUP(A11,'App dashboard año actual'!A:N,3,0) -> 0.17945893 | E11: =IFERROR(VLOOKUP(A11,'App dashboard año actual'!A:E,3,0)/VLOOKUP(A11,'App dashboard año actual'!A:E,5,0),"Sin ventas") -> 229059.1 | F11: 1.2 | G11: 4.7 | H11: 46072 | I11: =TODAY()-H11 -> 61 | J11: =VLOOKUP(A11,'Cruce APP Velocidad ultimas 5 s'!A:H,6,0) -> 0 | K11: =VLOOKUP(A11,'Cruce APP Velocidad ultimas 5 s'!A:H,7,0) -> 3 | L11: =VLOOKUP(A11,'Cruce APP Velocidad ultimas 5 s'!A:H,8,0) -> 3 | M11: =VLOOKUP(A11,'Cruce APP Velocidad ultimas 5 s'!A:I,9,0) -> 3 | N11: =VLOOKUP(A11,'Cruce APP Velocidad ultimas 5 s'!A:J,10,0) -> 0 | P11: revisar en reunion de el miercoles con el equipo
A12: BICE003 | B12: =VLOOKUP(A12,'Cruce APP Velocidad ultimas 5 s'!A:B,2,0) -> Bicicleta de Spinning Pro Overfit Estatica Fitness Gym 4 kg | C12: =VLOOKUP(A12,'App dashboard año actual'!A:I,9,0) -> 35,05 | D12: =VLOOKUP(A12,'App dashboard año actual'!A:K,11,0)/VLOOKUP(A12,'App dashboard año actual'!A:N,3,0) -> 0.036313353 | E12: =IFERROR(VLOOKUP(A12,'App dashboard año actual'!A:E,3,0)/VLOOKUP(A12,'App dashboard año actual'!A:E,5,0),"Sin ventas") -> 121356.88 | F12: 1.2 | G12: 4.7 | H12: 46077 | I12: =TODAY()-H12 -> 56 | J12: =VLOOKUP(A12,'Cruce APP Velocidad ultimas 5 s'!A:H,6,0) -> 2 | K12: =VLOOKUP(A12,'Cruce APP Velocidad ultimas 5 s'!A:H,7,0) -> 8 | L12: =VLOOKUP(A12,'Cruce APP Velocidad ultimas 5 s'!A:H,8,0) -> 3 | M12: =VLOOKUP(A12,'Cruce APP Velocidad ultimas 5 s'!A:I,9,0) -> 0 | N12: =VLOOKUP(A12,'Cruce APP Velocidad ultimas 5 s'!A:J,10,0) -> 0 | P12: Listo
A13: BICE004 | B13: =VLOOKUP(A13,'Cruce APP Velocidad ultimas 5 s'!A:B,2,0) -> Bicicleta de Spinning Pro Overfit Estatica Fitness Gym 6 kg | C13: =VLOOKUP(A13,'App dashboard año actual'!A:I,9,0) -> 0 | D13: =VLOOKUP(A13,'App dashboard año actual'!A:K,11,0)/VLOOKUP(A13,'App dashboard año actual'!A:N,3,0) -> #DIV/0! | E13: =IFERROR(VLOOKUP(A13,'App dashboard año actual'!A:E,3,0)/VLOOKUP(A13,'App dashboard año actual'!A:E,5,0),"Sin ventas") -> Sin ventas | F13: 1.2 | G13: 4.7 | H13: 46077 | I13: =TODAY()-H13 -> 56 | J13: =VLOOKUP(A13,'Cruce APP Velocidad ultimas 5 s'!A:H,6,0) -> 0 | K13: =VLOOKUP(A13,'Cruce APP Velocidad ultimas 5 s'!A:H,7,0) -> 0 | L13: =VLOOKUP(A13,'Cruce APP Velocidad ultimas 5 s'!A:H,8,0) -> 0 | M13: =VLOOKUP(A13,'Cruce APP Velocidad ultimas 5 s'!A:I,9,0) -> 0 | N13: =VLOOKUP(A13,'Cruce APP Velocidad ultimas 5 s'!A:J,10,0) -> 0 | P13: se le sumo mas visibilidad
A14: BICE005MAGNETIC | B14: =VLOOKUP(A14,'Cruce APP Velocidad ultimas 5 s'!A:B,2,0) -> Bicicleta Spinning Magnetica Pro Overfit Estatica Gym 6kg | C14: =VLOOKUP(A14,'App dashboard año actual'!A:I,9,0) -> 36,7 | D14: =VLOOKUP(A14,'App dashboard año actual'!A:K,11,0)/VLOOKUP(A14,'App dashboard año actual'!A:N,3,0) -> 0.044585922 | E14: =IFERROR(VLOOKUP(A14,'App dashboard año actual'!A:E,3,0)/VLOOKUP(A14,'App dashboard año actual'!A:E,5,0),"Sin ventas") -> 185571.78 | F14: 1.2 | G14: 4.7 | H14: 46077 | I14: =TODAY()-H14 -> 56 | J14: =VLOOKUP(A14,'Cruce APP Velocidad ultimas 5 s'!A:H,6,0) -> 1 | K14: =VLOOKUP(A14,'Cruce APP Velocidad ultimas 5 s'!A:H,7,0) -> 2 | L14: =VLOOKUP(A14,'Cruce APP Velocidad ultimas 5 s'!A:H,8,0) -> 1 | M14: =VLOOKUP(A14,'Cruce APP Velocidad ultimas 5 s'!A:I,9,0) -> 0 | N14: =VLOOKUP(A14,'Cruce APP Velocidad ultimas 5 s'!A:J,10,0) -> 0 | P14: aplicar relampagos | Q14: Aplicar Relámpago
A15: MOCHBOMBA001 | B15: =VLOOKUP(A15,'Cruce APP Velocidad ultimas 5 s'!A:B,2,0) -> Mochila De Viaje con Bomba al Vacío 900D Luxgear 40 Litros | C15: =VLOOKUP(A15,'App dashboard año actual'!A:I,9,0) -> 17,75 | D15: =VLOOKUP(A15,'App dashboard año actual'!A:K,11,0)/VLOOKUP(A15,'App dashboard año actual'!A:N,3,0) -> 0.18240792 | E15: =IFERROR(VLOOKUP(A15,'App dashboard año actual'!A:E,3,0)/VLOOKUP(A15,'App dashboard año actual'!A:E,5,0),"Sin ventas") -> 69730 | F15: 1.2 | G15: 4.7 | H15: 46078 | I15: =TODAY()-H15 -> 55 | J15: =VLOOKUP(A15,'Cruce APP Velocidad ultimas 5 s'!A:H,6,0) -> 1 | K15: =VLOOKUP(A15,'Cruce APP Velocidad ultimas 5 s'!A:H,7,0) -> 2 | L15: =VLOOKUP(A15,'Cruce APP Velocidad ultimas 5 s'!A:H,8,0) -> 3 | M15: =VLOOKUP(A15,'Cruce APP Velocidad ultimas 5 s'!A:I,9,0) -> 1 | N15: =VLOOKUP(A15,'Cruce APP Velocidad ultimas 5 s'!A:J,10,0) -> 0 | P15: Listo
A16: MOCHBOMBA002 | B16: =VLOOKUP(A16,'Cruce APP Velocidad ultimas 5 s'!A:B,2,0) -> Mochila De Viaje con Bomba al Vacio Luxgear 900D 40 Litros | C16: =VLOOKUP(A16,'App dashboard año actual'!A:I,9,0) -> 26,57 | D16: =VLOOKUP(A16,'App dashboard año actual'!A:K,11,0)/VLOOKUP(A16,'App dashboard año actual'!A:N,3,0) -> 0.095256083 | E16: =IFERROR(VLOOKUP(A16,'App dashboard año actual'!A:E,3,0)/VLOOKUP(A16,'App dashboard año actual'!A:E,5,0),"Sin ventas") -> 69492.5 | F16: 1.2 | G16: 4.7 | H16: 46078 | I16: =TODAY()-H16 -> 55 | J16: =VLOOKUP(A16,'Cruce APP Velocidad ultimas 5 s'!A:H,6,0) -> 3 | K16: =VLOOKUP(A16,'Cruce APP Velocidad ultimas 5 s'!A:H,7,0) -> 3 | L16: =VLOOKUP(A16,'Cruce APP Velocidad ultimas 5 s'!A:H,8,0) -> 0 | M16: =VLOOKUP(A16,'Cruce APP Velocidad ultimas 5 s'!A:I,9,0) -> 0 | N16: =VLOOKUP(A16,'Cruce APP Velocidad ultimas 5 s'!A:J,10,0) -> 0 | P16: Listo
A17: MOCHBOMBA003 | B17: =VLOOKUP(A17,'Cruce APP Velocidad ultimas 5 s'!A:B,2,0) -> Mochila De Viaje con Bomba al Vacio 900D Luxgear 22 Litros | C17: =VLOOKUP(A17,'App dashboard año actual'!A:I,9,0) -> 24,27 | D17: =VLOOKUP(A17,'App dashboard año actual'!A:K,11,0)/VLOOKUP(A17,'App dashboard año actual'!A:N,3,0) -> 0.11940882 | E17: =IFERROR(VLOOKUP(A17,'App dashboard año actual'!A:E,3,0)/VLOOKUP(A17,'App dashboard año actual'!A:E,5,0),"Sin ventas") -> 64768.25 | F17: 1.2 | G17: 4.7 | H17: 46078 | I17: =TODAY()-H17 -> 55 | J17: =VLOOKUP(A17,'Cruce APP Velocidad ultimas 5 s'!A:H,6,0) -> 2 | K17: =VLOOKUP(A17,'Cruce APP Velocidad ultimas 5 s'!A:H,7,0) -> 1 | L17: =VLOOKUP(A17,'Cruce APP Velocidad ultimas 5 s'!A:H,8,0) -> 2 | M17: =VLOOKUP(A17,'Cruce APP Velocidad ultimas 5 s'!A:I,9,0) -> 3 | N17: =VLOOKUP(A17,'Cruce APP Velocidad ultimas 5 s'!A:J,10,0) -> 0 | P17: Listo
A18: MOCHVIAJE010 | B18: =VLOOKUP(A18,'Cruce APP Velocidad ultimas 5 s'!A:B,2,0) -> Mochila De Viaje 900D Luxgear Cabina 40 Litros Verde Olivo | C18: =VLOOKUP(A18,'App dashboard año actual'!A:I,9,0) -> 34,07 | D18: =VLOOKUP(A18,'App dashboard año actual'!A:K,11,0)/VLOOKUP(A18,'App dashboard año actual'!A:N,3,0) -> 0.031686048 | E18: =IFERROR(VLOOKUP(A18,'App dashboard año actual'!A:E,3,0)/VLOOKUP(A18,'App dashboard año actual'!A:E,5,0),"Sin ventas") -> 40437.75 | F18: 1.2 | G18: 4.7 | H18: 46078 | I18: =TODAY()-H18 -> 55 | J18: =VLOOKUP(A18,'Cruce APP Velocidad ultimas 5 s'!A:H,6,0) -> 3 | K18: =VLOOKUP(A18,'Cruce APP Velocidad ultimas 5 s'!A:H,7,0) -> 2 | L18: =VLOOKUP(A18,'Cruce APP Velocidad ultimas 5 s'!A:H,8,0) -> 3 | M18: =VLOOKUP(A18,'Cruce APP Velocidad ultimas 5 s'!A:I,9,0) -> 5 | N18: =VLOOKUP(A18,'Cruce APP Velocidad ultimas 5 s'!A:J,10,0) -> 0 | P18: Listo
A19: MOCHVIAJE011 | B19: =VLOOKUP(A19,'Cruce APP Velocidad ultimas 5 s'!A:B,2,0) -> Mochila De Viaje 900D Luxgear Notebook Cabina 28 Litros | C19: =VLOOKUP(A19,'App dashboard año actual'!A:I,9,0) -> 28,28 | D19: =VLOOKUP(A19,'App dashboard año actual'!A:K,11,0)/VLOOKUP(A19,'App dashboard año actual'!A:N,3,0) -> 0.16434358 | E19: =IFERROR(VLOOKUP(A19,'App dashboard año actual'!A:E,3,0)/VLOOKUP(A19,'App dashboard año actual'!A:E,5,0),"Sin ventas") -> 33878.889 | F19: 1.2 | G19: 4.7 | H19: 46078 | I19: =TODAY()-H19 -> 55 | J19: =VLOOKUP(A19,'Cruce APP Velocidad ultimas 5 s'!A:H,6,0) -> 2 | K19: =VLOOKUP(A19,'Cruce APP Velocidad ultimas 5 s'!A:H,7,0) -> 1 | L19: =VLOOKUP(A19,'Cruce APP Velocidad ultimas 5 s'!A:H,8,0) -> 1 | M19: =VLOOKUP(A19,'Cruce APP Velocidad ultimas 5 s'!A:I,9,0) -> 1 | N19: =VLOOKUP(A19,'Cruce APP Velocidad ultimas 5 s'!A:J,10,0) -> 0 | P19: aplicar relampagos | Q19: Aplicar Relámpago
A20: FRAZADAKING003AZUL | B20: =VLOOKUP(A20,'Cruce APP Velocidad ultimas 5 s'!A:B,2,0) -> Frazada king medida 250x230cm 300GSM color azul | C20: =VLOOKUP(A20,'App dashboard año actual'!A:I,9,0) -> 24,45 | D20: =VLOOKUP(A20,'App dashboard año actual'!A:K,11,0)/VLOOKUP(A20,'App dashboard año actual'!A:N,3,0) -> 0.22159849 | E20: =IFERROR(VLOOKUP(A20,'App dashboard año actual'!A:E,3,0)/VLOOKUP(A20,'App dashboard año actual'!A:E,5,0),"Sin ventas") -> 27179.962 | F20: 0.9 | G20: 4.2 | H20: 46083 | I20: =TODAY()-H20 -> 50 | J20: =VLOOKUP(A20,'Cruce APP Velocidad ultimas 5 s'!A:H,6,0) -> 1 | K20: =VLOOKUP(A20,'Cruce APP Velocidad ultimas 5 s'!A:H,7,0) -> 7 | L20: =VLOOKUP(A20,'Cruce APP Velocidad ultimas 5 s'!A:H,8,0) -> 5 | M20: =VLOOKUP(A20,'Cruce APP Velocidad ultimas 5 s'!A:I,9,0) -> 4 | N20: =VLOOKUP(A20,'Cruce APP Velocidad ultimas 5 s'!A:J,10,0) -> 1 | P20: Listo
A21: FRAZADAKING003GRIS | B21: =VLOOKUP(A21,'Cruce APP Velocidad ultimas 5 s'!A:B,2,0) -> Frazada king medida 250x230cm 300GSM color gris | C21: =VLOOKUP(A21,'App dashboard año actual'!A:I,9,0) -> 25,09 | D21: =VLOOKUP(A21,'App dashboard año actual'!A:K,11,0)/VLOOKUP(A21,'App dashboard año actual'!A:N,3,0) -> 0.23371515 | E21: =IFERROR(VLOOKUP(A21,'App dashboard año actual'!A:E,3,0)/VLOOKUP(A21,'App dashboard año actual'!A:E,5,0),"Sin ventas") -> 29429.2 | F21: 0.9 | G21: 4.2 | H21: 46083 | I21: =TODAY()-H21 -> 50 | J21: =VLOOKUP(A21,'Cruce APP Velocidad ultimas 5 s'!A:H,6,0) -> 11 | K21: =VLOOKUP(A21,'Cruce APP Velocidad ultimas 5 s'!A:H,7,0) -> 11 | L21: =VLOOKUP(A21,'Cruce APP Velocidad ultimas 5 s'!A:H,8,0) -> 4 | M21: =VLOOKUP(A21,'Cruce APP Velocidad ultimas 5 s'!A:I,9,0) -> 10 | N21: =VLOOKUP(A21,'Cruce APP Velocidad ultimas 5 s'!A:J,10,0) -> 0 | P21: Listo
A22: FRAZADAQUEEN004AZUL | B22: =VLOOKUP(A22,'Cruce APP Velocidad ultimas 5 s'!A:B,2,0) -> Frazada Queen medida 220x220cm 300GSM color azul | C22: =VLOOKUP(A22,'App dashboard año actual'!A:I,9,0) -> 2,09 | D22: =VLOOKUP(A22,'App dashboard año actual'!A:K,11,0)/VLOOKUP(A22,'App dashboard año actual'!A:N,3,0) -> 0.41602842 | E22: =IFERROR(VLOOKUP(A22,'App dashboard año actual'!A:E,3,0)/VLOOKUP(A22,'App dashboard año actual'!A:E,5,0),"Sin ventas") -> 18769 | F22: 0.9 | G22: 4.2 | H22: 46083 | I22: =TODAY()-H22 -> 50 | J22: =VLOOKUP(A22,'Cruce APP Velocidad ultimas 5 s'!A:H,6,0) -> 3 | K22: =VLOOKUP(A22,'Cruce APP Velocidad ultimas 5 s'!A:H,7,0) -> 6 | L22: =VLOOKUP(A22,'Cruce APP Velocidad ultimas 5 s'!A:H,8,0) -> 1 | M22: =VLOOKUP(A22,'Cruce APP Velocidad ultimas 5 s'!A:I,9,0) -> 2 | N22: =VLOOKUP(A22,'Cruce APP Velocidad ultimas 5 s'!A:J,10,0) -> 0 | P22: Listo
A23: FRAZADAQUEEN004GRIS | B23: =VLOOKUP(A23,'Cruce APP Velocidad ultimas 5 s'!A:B,2,0) -> Frazada Queen medida 220x220cm 300GSM color gris | C23: =VLOOKUP(A23,'App dashboard año actual'!A:I,9,0) -> 26,77 | D23: =VLOOKUP(A23,'App dashboard año actual'!A:K,11,0)/VLOOKUP(A23,'App dashboard año actual'!A:N,3,0) -> 0.15913441 | E23: =IFERROR(VLOOKUP(A23,'App dashboard año actual'!A:E,3,0)/VLOOKUP(A23,'App dashboard año actual'!A:E,5,0),"Sin ventas") -> 18548 | F23: 0.9 | G23: 4.2 | H23: 46083 | I23: =TODAY()-H23 -> 50 | J23: =VLOOKUP(A23,'Cruce APP Velocidad ultimas 5 s'!A:H,6,0) -> 3 | K23: =VLOOKUP(A23,'Cruce APP Velocidad ultimas 5 s'!A:H,7,0) -> 5 | L23: =VLOOKUP(A23,'Cruce APP Velocidad ultimas 5 s'!A:H,8,0) -> 6 | M23: =VLOOKUP(A23,'Cruce APP Velocidad ultimas 5 s'!A:I,9,0) -> 1 | N23: =VLOOKUP(A23,'Cruce APP Velocidad ultimas 5 s'!A:J,10,0) -> 0 | P23: Listo
A24: COLCHONETALIS002NEG | B24: =VLOOKUP(A24,'Cruce APP Velocidad ultimas 5 s'!A:B,2,0) -> Colchoneta Deportiva lisa 100x50x5cm oxford | C24: =VLOOKUP(A24,'App dashboard año actual'!A:I,9,0) -> 32,12 | D24: =VLOOKUP(A24,'App dashboard año actual'!A:K,11,0)/VLOOKUP(A24,'App dashboard año actual'!A:N,3,0) -> 0.1141145 | E24: =IFERROR(VLOOKUP(A24,'App dashboard año actual'!A:E,3,0)/VLOOKUP(A24,'App dashboard año actual'!A:E,5,0),"Sin ventas") -> 16966.558 | F24: 3.7 | G24: 11.7 | H24: 46083 | I24: =TODAY()-H24 -> 50 | J24: =VLOOKUP(A24,'Cruce APP Velocidad ultimas 5 s'!A:H,6,0) -> 6 | K24: =VLOOKUP(A24,'Cruce APP Velocidad ultimas 5 s'!A:H,7,0) -> 0 | L24: =VLOOKUP(A24,'Cruce APP Velocidad ultimas 5 s'!A:H,8,0) -> 18 | M24: =VLOOKUP(A24,'Cruce APP Velocidad ultimas 5 s'!A:I,9,0) -> 1 | N24: =VLOOKUP(A24,'Cruce APP Velocidad ultimas 5 s'!A:J,10,0) -> 0 | P24: Listo
A25: AMPLIFGUI001 | B25: =VLOOKUP(A25,'Cruce APP Velocidad ultimas 5 s'!A:B,2,0) -> Amplificador para guitarra eléctrica 20W Ibrah Music | C25: =VLOOKUP(A25,'App dashboard año actual'!A:I,9,0) -> 38 | D25: =VLOOKUP(A25,'App dashboard año actual'!A:K,11,0)/VLOOKUP(A25,'App dashboard año actual'!A:N,3,0) -> 0.070889656 | E25: =IFERROR(VLOOKUP(A25,'App dashboard año actual'!A:E,3,0)/VLOOKUP(A25,'App dashboard año actual'!A:E,5,0),"Sin ventas") -> 49040.263 | F25: 3.7 | G25: 11.7 | H25: 46084 | I25: =TODAY()-H25 -> 49 | J25: =VLOOKUP(A25,'Cruce APP Velocidad ultimas 5 s'!A:H,6,0) -> 6 | K25: =VLOOKUP(A25,'Cruce APP Velocidad ultimas 5 s'!A:H,7,0) -> 12 | L25: =VLOOKUP(A25,'Cruce APP Velocidad ultimas 5 s'!A:H,8,0) -> 9 | M25: =VLOOKUP(A25,'Cruce APP Velocidad ultimas 5 s'!A:I,9,0) -> 9 | N25: =VLOOKUP(A25,'Cruce APP Velocidad ultimas 5 s'!A:J,10,0) -> 1 | P25: Listo
